Workbook

Sheet 1-Waste Input
A1: URBAN RIG — Waste Input & Composition (V2)
A2: Defines all incoming waste characteristics. Blue cells = user inputs.
A4: Ref | B4: Parameter | C4: Value | D4: Unit | E4: Source / Notes
B5: A — MACHINE & CAPACITY
A6: A1 | B6: Machine nominal capacity | C6: 200 | D6: T/day (volumetric) | E6: Urban Rig URC-2000 spec
A7: A2 | B7: Waste bulk density (volume to weight) | C7: 0.7 | D7: T/m³ | E7: Typical MSW. Airport/industrial may differ.
A8: A3 | B8: Daily waste input (actual weight) | C8: =C6*C7 -> 140 | D8: T/day | E8: Derived: nominal × density
A9: A4 | B9: Number of URC-2000 units | C9: 1 | D9: units | E9: Default 1. Scale by adding units.
A10: A5 | B10: Operating days per year | C10: 330 | D10: days/year | E10: ~90% uptime. 35 days maintenance.
A11: A6 | B11: Annual throughput (per unit) | C11: =C8*C10 -> 46200 | D11: T/year | E11: Derived: daily × operating days
A12: A7 | B12: Total annual throughput (all units) | C12: =C11*C9 -> 46200 | D12: T/year | E12: Derived: per unit × number of units
B14: B — GENERAL WASTE COMPOSITION (as received)
A15: B1 | B15: Plastic fraction | C15: 0.3 | E15: Typical MSW ~30%. Airport/industrial higher.
A16: B2 | B16: Organic + cellulose fraction | C16: 0.47 | E16: Food, paper, wood, cotton, garden waste.
A17: B3 | B17: Metal fraction (total) | C17: 0.05 | E17: Ferrous + aluminium + other metals.
A18: B4 | B18: Glass fraction | C18: 0.055 | E18: Bottles, jars, flat glass.
A19: B5 | B19: Mineral inerts (ceramic, stone, soil) | C19: 0.02 | E19: Non-combustible, non-recyclable.
A20: B6 | B20: Moisture content | C20: 0.08 | E20: Varies by source. MSW 25-35%, pre-dried 5-10%.
A21: B7 | B21: Other / unclassified | C21: =1-SUM(C15:C20) -> 0.025 | E21: Residual balance. Should be ≥0.
B22: Composition check | C22: =IF(ABS(SUM(C15:C21)-1)<0.001,"OK ✓","ERROR") -> OK ✓
B24: B2 — METAL BREAKDOWN (% of total metal fraction)
A25: B2.1 | B25: Ferrous (% of metals) | C25: 0.8 | E25: Steel, iron. Dominant in MSW.
A26: B2.2 | B26: Aluminium (% of metals) | C26: 0.15 | E26: Cans, foil, profiles.
A27: B2.3 | B27: Other metals (% of metals) | C27: =1-C25-C26 -> 0.05 | E27: Copper, zinc, etc.
B29: C — PLASTIC POLYMER MIX
A30: Ref | B30: Polymer | C30: Mix % | D30: Oil yield (wt%) | E30: Off-gas yield (wt%) | F30: Residue (wt%) | G30: Off-gas CV (MJ/kg) | H30: Source
A31: C1 | B31: LDPE | C31: 0.32 | D31: 0.77 | E31: 0.22 | F31: 0.01 | G31: 5.54 | H31: Ichimura test data
A32: C2 | B32: HDPE | C32: 0.2 | D32: 0.77 | E32: 0.22 | F32: 0.01 | G32: 5.54 | H32: Ichimura test data
A33: C3 | B33: PP | C33: 0.2 | D33: 0.8 | E33: 0.18 | F33: 0.02 | G33: 5.54 | H33: Ichimura test #6
A34: C4 | B34: PET | C34: 0.18 | D34: 0.45 | E34: 0.17 | F34: 0.38 | G34: 5.54 | H34: Literature — HYPOTHESIS
A35: C5 | B35: PS | C35: 0.07 | D35: 0.58 | E35: 0.14 | F35: 0.28 | G35: 5.54 | H35: Ichimura tests #3/#4
A36: C6 | B36: PVC | C36: 0.02 | D36: 0.32 | E36: 0.02 | F36: 0.13 | G36: 5.54 | H36: Literature — HYPOTHESIS
A37: C7 | B37: ABS | C37: 0.005 | D37: 0.55 | E37: 0.18 | F37: 0.27 | G37: 5.54 | H37: Literature — HYPOTHESIS
A38: C8 | B38: Other | C38: 0.005 | D38: 0.4 | E38: 0.18 | F38: 0.42 | G38: 5.54 | H38: Catch-all — HYPOTHESIS
B39: TOTAL | C39: =SUM(C31:C38) -> 1
B40: Mix check | C40: =IF(ABS(C39-1)<0.001,"OK ✓","ERROR") -> OK ✓
B42: D — CONVERSION PARAMETERS
A43: D1 | B43: Char yield from organic+cellulose fraction | C43: 0.69 | D43: wt% | E43: Annex F §11.2. HYPOTHESIS — not UR-measured.
A44: D2 | B44: Oil density | C44: 0.85 | D44: kg/L | E44: Standard pyrolysis oil density.
A45: D3 | B45: Off-gas energy from organic fraction | C45: 0.5 | D45: MJ/kg | E45: Literature: 0.3-0.8 MJ/kg. NOT UR-measured.
A46: D4 | B46: Char CV — organic/cellulose (MJ/kg) | C46: 15 | D46: MJ/kg | E46: HYPOTHESIS. Literature: 11-20 MJ/kg.
A47: D5 | B47: Char CV — plastic residue (MJ/kg) | C47: 25 | D47: MJ/kg | E47: HYPOTHESIS. Carbon black ~32 MJ/kg.
A48: D6 | B48: Heating demand per ton processed | C48: 2714 | D48: MJ/T | E48: 10,000L diesel × 38 MJ/L ÷ 140 T/day.
A49: D7 | B49: Waste rejection rate (unsuitable for processing) | C49: 0.02 | D49: wt% | E49: Oversize, hazardous, non-processable.
B51: E — WEIGHTED YIELDS (calculated from polymer mix)
A52: E1 | B52: Weighted oil yield from plastic (wt%) | C52: =SUMPRODUCT(C31:C38,D31:D38) -> 0.69315 | D52: wt% | E52: Derived from mix × yield per polymer
A53: E2 | B53: Weighted off-gas yield from plastic (wt%) | C53: =SUMPRODUCT(C31:C38,E31:E38) -> 0.193 | D53: wt% | E53: Derived
A54: E3 | B54: Weighted residue from plastic (wt%) | C54: =SUMPRODUCT(C31:C38,F31:F38) -> 0.10325 | D54: wt% | E54: Derived
A55: E4 | B55: Weighted off-gas CV (MJ/kg) | C55: =SUMPRODUCT(C31:C38,G31:G38) -> 5.54 | D55: MJ/kg | E55: Derived
A56: E5 | B56: Off-gas energy per kg plastic (MJ/kg) | C56: =C53*C55 -> 1.06922 | D56: MJ/kg | E56: yield × CV

Sheet 2-Financial Inputs
A1: URBAN RIG — Financial & Market Inputs (V2)
A2: All pricing, financing, and cost assumptions. Blue cells = user inputs.
A4: Ref | B4: Parameter | C4: Value | D4: Unit | E4: Source / Notes
B5: F — FINANCING STRUCTURE
A6: F1 | B6: Bank loan percentage | C6: 0.7 | E6: 70% debt, 30% equity
A7: F2 | B7: Annual interest rate | C7: 0.12 | E7: Variable — adjust per project.
A8: F3 | B8: Loan term | C8: 10 | D8: years | E8: 120 monthly payments
A9: F4 | B9: Corporate tax rate | C9: 0.25 | E9: France standard rate
A10: F5 | B10: Depreciation period (straight-line) | C10: 15 | D10: years | E10: Equipment depreciation
A11: F6 | B11: Annual inflation rate | C11: 0.02 | E11: Applied to revenues and OPEX from Year 2
A12: F7 | B12: Discount rate / WACC | C12: 0.1 | E12: For NPV and IRR calculations
A13: F8 | B13: Working capital (% of revenue) | C13: 0.05 | E13: Receivables minus payables
B15: G — GATE FEES BY WASTE TYPE (EUR/T)
A16: G1 | B16: Tier 1: MSW (municipal) | C16: 100 | D16: EUR/T | E16: French incineration ~€131-140/T. Competitive at €100.
A17: G2 | B17: Tier 2: Industrial / logistics waste | C17: 120 | D17: EUR/T | E17: Plastic-rich, higher value.
A18: G3 | B18: Tier 3: Aircraft / aviation waste | C18: 150 | D18: EUR/T | E18: Biosecurity compliance premium.
A19: G4 | B19: Tier 4: Composites (wind blades) | C19: 130 | D19: EUR/T | E19: No alternative. EU landfill ban 2030.
A20: G5 | B20: Tier 5: Medical / DASRI waste | C20: 800 | D20: EUR/T | E20: Highest margin. Regulatory premium.
A21: G6 | B21: Tier 6: Tyre waste | C21: 30 | D21: EUR/T | E21: Often low/zero (EPR-funded collection).
A22: G7 | B22: Blended average gate fee (used in model) | C22: 110 | D22: EUR/T | E22: INPUT: Weighted average. Adjust per project.
B24: H — OIL FRACTION PRICING (EUR/T by quality grade)
A25: Ref | B25: Fraction | C25: Share | D25: Low (EUR/T) | E25: Medium (EUR/T) | F25: High (EUR/T) | G25: Source
A26: H1 | B26: Light Oil (Heating Oil / Naphtha) | C26: 0.1 | D26: 450 | E26: 600 | F26: 800 | G26: C5-C8 range. ~150°C zone.
A27: H2 | B27: Gas Oil (Diesel) | C27: 0.8 | D27: 500 | E27: 670 | F27: 950 | G27: C8-C16 middle distillate. ~300°C zone. Main product.
A28: H3 | B28: Heavy Oil (Fuel Oil / Waxes) | C28: 0.1 | D28: 350 | E28: 450 | F28: 550 | G28: C16+ waxes. ~450°C zone. Marine fuel or cracker feed.
B29: TOTAL share | C29: =SUM(C26:C28) -> 1
B31: H — OIL SCENARIO SELECTION
A32: H4 | B32: Oil price scenario (1=Low, 2=Medium, 3=High) | C32: 2 | E32: Determines weighted oil price
A33: H5 | B33: Weighted oil price (EUR/T) | C33: =IF(C32=1,SUMPRODUCT(C26:C28,D26:D28),IF(C32=2,SUMPRODUCT(C26:C28,E26:E28),SUMPRODUCT(C26:C28,F26:F28))) -> 641 | D33: EUR/T | E33: Derived from scenario selection
A34: H6 | B34: Weighted oil price (EUR/L) | C34: =C33*'1-Waste Input'!C44/1000 -> 0.54485 | D34: EUR/L | E34: EUR/T × density / 1000
B36: Scenario summary:
B37: Low | C37: =SUMPRODUCT(C26:C28,D26:D28) -> 480 | D37: EUR/T
B38: Medium | C38: =SUMPRODUCT(C26:C28,E26:E28) -> 641 | D38: EUR/T
B39: High | C39: =SUMPRODUCT(C26:C28,F26:F28) -> 895 | D39: EUR/T
B41: I — CHAR / SOLID OUTPUT PRICING (EUR/T by grade)
A42: I1 | B42: SRF-grade char (cement kiln fuel) | C42: 30 | D42: EUR/T | E42: Low value. Requires NCV/Cl/Hg compliance.
A43: I2 | B43: Fuel briquette char | C43: 100 | D43: EUR/T | E43: Pelletised, standardised CV.
A44: I3 | B44: Agricultural biochar (if certified) | C44: 350 | D44: EUR/T | E44: Only for clean feedstock. Unlikely for MSW.
A45: I4 | B45: Char grade used in model (1=SRF, 2=Briquette, 3=Biochar) | C45: 2 | E45: Determines char sale price
A46: I5 | B46: Char sale price (derived from grade) | C46: =IF(C45=1,C42,IF(C45=2,C43,C44)) -> 100 | D46: EUR/T | E46: Derived from grade selection
B48: J — METAL PRICING (EUR/T by type)
A49: J1 | B49: Ferrous scrap price | C49: 250 | D49: EUR/T | E49: Sorted ferrous. Market: €200-350/T.
A50: J2 | B50: Aluminium scrap price | C50: 1400 | D50: EUR/T | E50: Sorted aluminium. Market: €1,200-1,800/T.
A51: J3 | B51: Other metals price | C51: 500 | D51: EUR/T | E51: Copper, zinc, etc.
A52: J4 | B52: Mixed unsorted metal price | C52: 300 | D52: EUR/T | E52: If no separation. Conservative.
A53: J5 | B53: Glass cullet price (if sorted) | C53: 30 | D53: EUR/T | E53: Clean cullet. Negative if contaminated.
B55: K — DISPOSAL COSTS & OTHER PRICES
A56: K1 | B56: Non-recoverable residue disposal cost | C56: 110 | D56: EUR/T | E56: French landfill €80-140/T incl. TGAP.
A57: K2 | B57: Heating oil / fuel purchase price | C57: 0.4 | D57: EUR/L | E57: V2: Used for reactor heating (all energy purchased externally).
A58: K3 | B58: Electricity purchase price | C58: 0.15 | D58: EUR/kWh | E58: Grid electricity cost.
B59: (removed — consolidated into K1 disposal cost) | E59: Ashes, sand, glass fines, non-sellable byproducts. User input.
B60: L — CARBON CREDITS
A61: L1 | B61: Carbon credit price | C61: 50 | D61: EUR/T CO₂ | E61: EU ETS ~€50-80. VCS/Gold Standard lower.
A62: L2 | B62: CO₂ per ton waste (incineration baseline) | C62: 1.8 | D62: T CO₂/T waste | E62: IPCC standard for MSW incineration.
A63: L3 | B63: CO₂ from diesel combustion | C63: 2.68 | D63: kg CO₂/L | E63: ADEME/IPCC emission factor.
B65: M — OPERATING COST INPUTS
A66: M1 | B66: Core plant operators (FTE) | C66: 10 | D66: FTE | E66: 24/7 shift coverage for reactor operations.
A67: M2 | B67: Maintenance staff (FTE) | C67: 3 | D67: FTE | E67: Preventive + corrective maintenance.
A68: M3 | B68: Management & admin (FTE) | C68: 2 | D68: FTE | E68: Site manager, admin, HSE.
A69: M4 | B69: Average loaded cost per FTE | C69: 56000 | D69: EUR/year | E69: Salary + social charges + benefits.
A70: M5 | B70: Pre-sorting additional staff (FTE) | C70: 4 | D70: FTE | E70: Only applies if pre-sorting active.
A71: M6 | B71: Post-sorting additional staff (FTE) | C71: 3 | D71: FTE | E71: Only applies if post-sorting active.
A72: M7 | B72: Maintenance as % of equipment CAPEX | C72: 0.04 | E72: 4% of machine cost per year.
A73: M8 | B73: Contingency / other OPEX | C73: 0.02 | E73: 2% of total CAPEX as annual provision.
A74: M9 | B74: Grid electricity consumption | C74: 4800 | D74: kWh/day | E74: Instrumentation, lighting, auxiliaries.
A75: M10 | B75: Insurance (% of total CAPEX) | C75: 0.005 | E75: 0.5% of CAPEX per year.
B77: N — PRE-SORTING RECOVERABLE MATERIAL PRICES
A78: N1 | B78: Recyclable PET price | C78: 250 | D78: EUR/T | E78: Clean sorted PET bales.
A79: N2 | B79: Recyclable HDPE price | C79: 300 | D79: EUR/T | E79: Clean sorted HDPE bales.
A80: N3 | B80: Cardboard / paper price | C80: 80 | D80: EUR/T | E80: Sorted bales.
A81: N4 | B81: Pre-sort ferrous price | C81: =C49 -> 250 | D81: EUR/T | E81: Same as ferrous scrap price (J1)
A82: N5 | B82: Pre-sort aluminium price | C82: =C50 -> 1400 | D82: EUR/T | E82: Same as aluminium scrap price (J2)
A83: N6 | B83: Pre-sort glass cullet price | C83: =C53 -> 30 | D83: EUR/T | E83: Same as glass cullet price (J5)

Sheet 3-Operations
A1: URBAN RIG — Operational Configuration (V2)
A2: Sorting configurations, energy strategy, ramp-up. Blue cells = user inputs.
A4: Ref | B4: Parameter | C4: Value | D4: Unit | E4: Source / Notes
B5: O — SORTING CONFIGURATION
A6: O1 | B6: Pre-sorting enabled (1=Yes, 0=No) | C6: 1 | E6: Activates pre-sorting calculations and P&L.
A7: O2 | B7: Post-sorting enabled (1=Yes, 0=No) | C7: 1 | E7: Activates post-sorting calculations and P&L.
B9: Active configuration:
B10: Configuration description | C10: =IF(AND(C6=0,C7=0),"No sorting",IF(AND(C6=1,C7=0),"Pre-sorting only",IF(AND(C6=0,C7=1),"Post-sorting only","Pre + Post sorting"))) -> Pre + Post sorting
B12: P — PRE-SORTING RECOVERY RATES (% of each fraction removed before reactor)
A13: P1 | B13: Ferrous metal recovery rate | C13: 0.9 | E13: Magnetic separator efficiency.
A14: P2 | B14: Aluminium recovery rate | C14: 0.75 | E14: Eddy current separator efficiency.
A15: P3 | B15: Glass recovery rate | C15: 0.7 | E15: Trommel + optical sorter.
A16: P4 | B16: Recyclable plastic recovery (PET/HDPE) | C16: 0 | E16: % of total plastic diverted for recycling.
A17: P5 | B17: Cardboard/paper recovery | C17: 0 | E17: % of organic fraction recovered as paper.
A18: P6 | B18: Inert removal rate (pre-sort) | C18: 0.5 | E18: Stone, ceramic removed by trommel.
B20: Q — POST-SORTING PARAMETERS (reactor output separation)
A21: Q1 | B21: Char screening efficiency (combustible char recovered) | C21: 0.85 | E21: Vibrating screen. Removes mineral fines.
A22: Q2 | B22: Metal recovery from char (magnetic) | C22: 0.8 | E22: Post-reactor ferrous from char matrix.
A23: Q3 | B23: Mineral inert separation from char | C23: 0.7 | E23: Density separation of non-combustible fines.
B25: R — ENERGY STRATEGY (V2: Off-gas + purchased oil hybrid)
A26: R1 | B26: Energy source | C26: Off-gas + purchased oil | E26: V2: All reactor heating from purchased heating oil. Grid electricity for auxiliaries.
A27: R2 | B27: Char market strategy | C27: Sell all | E27: V2: All char sold on market. No internal combustion.
B29: S — RAMP-UP PROFILE
A30: S1 | B30: Year 1 capacity utilisation | C30: 0.7 | E30: First year ramp-up.
A31: S2 | B31: Year 2 capacity utilisation | C31: 0.85 | E31: Second year.
A32: S3 | B32: Year 3+ capacity utilisation | C32: 1 | E32: Full capacity from Year 3.

Sheet 4-Production Calcs
A1: URBAN RIG — Production & Process Calculations (V2)
A2: All values derived from Tabs 1-3. No manual inputs. Green = cross-sheet reference.
A4: Ref | B4: Calculation | C4: Value | D4: Unit | E4: Formula logic
B5: T1 — DAILY INPUT MASS BALANCE
A6: T1.1 | B6: Gross daily input (kg/day) | C6: ='1-Waste Input'!C8*1000 -> 140000 | D6: kg/day | E6: Daily throughput × 1000
A7: T1.2 | B7: Rejected waste (kg/day) | C7: ='1-Waste Input'!C49*C6 -> 2800 | D7: kg/day | E7: Rejection rate × gross input
A8: T1.3 | B8: Net processable input (kg/day) | C8: =C6-C7 -> 137200 | D8: kg/day | E8: Gross minus rejected
B10: T2 — INPUT COMPOSITION (kg/day, before pre-sorting)
A11: T2.1 | B11: Plastic (kg/day) | C11: =C8*'1-Waste Input'!C15 -> 41160 | D11: kg/day | E11: Net input × plastic fraction
A12: T2.2 | B12: Organic + cellulose (kg/day) | C12: =C8*'1-Waste Input'!C16 -> 64484 | D12: kg/day | E12: Net input × organic fraction
A13: T2.3 | B13: Ferrous metal (kg/day) | C13: =C8*'1-Waste Input'!C17*'1-Waste Input'!C25 -> 5488 | D13: kg/day | E13: Net input × metal × ferrous share
A14: T2.4 | B14: Aluminium (kg/day) | C14: =C8*'1-Waste Input'!C17*'1-Waste Input'!C26 -> 1029 | D14: kg/day | E14: Net input × metal × Al share
A15: T2.5 | B15: Other metals (kg/day) | C15: =C8*'1-Waste Input'!C17*'1-Waste Input'!C27 -> 343 | D15: kg/day | E15: Net input × metal × other share
A16: T2.6 | B16: Glass (kg/day) | C16: =C8*'1-Waste Input'!C18 -> 7546 | D16: kg/day | E16: Net input × glass fraction
A17: T2.7 | B17: Mineral inerts (kg/day) | C17: =C8*'1-Waste Input'!C19 -> 2744 | D17: kg/day | E17: Net input × inert fraction
A18: T2.8 | B18: Moisture (kg/day) | C18: =C8*'1-Waste Input'!C20 -> 10976 | D18: kg/day | E18: Net input × moisture content
A19: T2.9 | B19: Other (kg/day) | C19: =C8*'1-Waste Input'!C21 -> 3430 | D19: kg/day | E19: Net input × other fraction
B20: Input mass check | C20: =C8-SUM(C11:C19) -> 0 | D20: kg/day | E20: Should be 0 (±1 rounding)
B22: T3 — PRE-SORTING REMOVALS (kg/day) — only if pre-sorting enabled
A23: T3.1 | B23: Ferrous removed (pre-sort) | C23: =IF('3-Operations'!C6=1,C13*'3-Operations'!C13,0) -> 4939.2 | D23: kg/day | E23: If pre-sort ON: ferrous × recovery rate
A24: T3.2 | B24: Aluminium removed (pre-sort) | C24: =IF('3-Operations'!C6=1,C14*'3-Operations'!C14,0) -> 771.75 | D24: kg/day | E24: If pre-sort ON: Al × recovery rate
A25: T3.3 | B25: Glass removed (pre-sort) | C25: =IF('3-Operations'!C6=1,C16*'3-Operations'!C15,0) -> 5282.2 | D25: kg/day | E25: If pre-sort ON: glass × recovery rate
A26: T3.4 | B26: Recyclable plastic removed (pre-sort) | C26: =IF('3-Operations'!C6=1,C11*'3-Operations'!C16,0) -> 0 | D26: kg/day | E26: If pre-sort ON: plastic × recyclable share
A27: T3.5 | B27: Paper/cardboard removed (pre-sort) | C27: =IF('3-Operations'!C6=1,C12*'3-Operations'!C17,0) -> 0 | D27: kg/day | E27: If pre-sort ON: organic × paper share
A28: T3.6 | B28: Inerts removed (pre-sort) | C28: =IF('3-Operations'!C6=1,C17*'3-Operations'!C18,0) -> 1372 | D28: kg/day | E28: If pre-sort ON: inerts × removal rate
A29: T3.7 | B29: Total pre-sorted removals | C29: =SUM(C23:C28) -> 12365.15 | D29: kg/day | E29: All materials removed before reactor
B31: T4 — MODIFIED REACTOR FEED (after pre-sorting)
A32: T4.1 | B32: Plastic entering reactor (kg/day) | C32: =C11-C26 -> 41160 | D32: kg/day | E32: Original plastic minus recyclables removed
A33: T4.2 | B33: Organic+cellulose entering reactor (kg/day) | C33: =C12-C27 -> 64484 | D33: kg/day | E33: Original organic minus paper removed
A34: T4.3 | B34: Ferrous entering reactor (kg/day) | C34: =C13-C23 -> 548.8 | D34: kg/day | E34: Residual ferrous
A35: T4.4 | B35: Aluminium entering reactor (kg/day) | C35: =C14-C24 -> 257.25 | D35: kg/day | E35: Residual aluminium
A36: T4.5 | B36: Other metals entering reactor (kg/day) | C36: =C15 -> 343 | D36: kg/day | E36: Other metals not pre-sorted
A37: T4.6 | B37: Glass entering reactor (kg/day) | C37: =C16-C25 -> 2263.8 | D37: kg/day | E37: Residual glass
A38: T4.7 | B38: Inerts entering reactor (kg/day) | C38: =C17-C28 -> 1372 | D38: kg/day | E38: Residual inerts
A39: T4.8 | B39: Moisture entering reactor (kg/day) | C39: =C18 -> 10976 | D39: kg/day | E39: Moisture unchanged by pre-sort
A40: T4.9 | B40: Other entering reactor (kg/day) | C40: =C19 -> 3430 | D40: kg/day | E40: Other fraction unchanged
A41: T4.10 | B41: Total reactor feed (kg/day) | C41: =SUM(C32:C40) -> 124834.85 | D41: kg/day | E41: Should equal net input minus pre-sort removals
B43: T5 — REACTOR OUTPUTS (kg/day)
A44: T5.1 | B44: Oil produced (kg/day) | C44: =C32*'1-Waste Input'!C52 -> 28530.054 | D44: kg/day | E44: Plastic in × weighted oil yield
A45: T5.2 | B45: Oil produced (litres/day) | C45: =C44/'1-Waste Input'!C44 -> 33564.769 | D45: L/day | E45: kg ÷ density
A46: T5.3 | B46: Off-gas from plastic (kg/day) | C46: =C32*'1-Waste Input'!C53 -> 7943.88 | D46: kg/day | E46: Plastic in × off-gas yield
A47: T5.4 | B47: Plastic residue / char (kg/day) | C47: =C32*'1-Waste Input'!C54 -> 4249.77 | D47: kg/day | E47: Plastic in × residue yield
A48: T5.5 | B48: Organic char (kg/day) | C48: =C33*'1-Waste Input'!C43 -> 44493.96 | D48: kg/day | E48: Organic in × char yield
A49: T5.6 | B49: Off-gas from organic (kg/day) | C49: =C33*(1-'1-Waste Input'!C43) -> 19990.04 | D49: kg/day | E49: Organic in × (1 - char yield)
A50: T5.7 | B50: Metals passing through reactor (kg/day) | C50: =C34+C35+C36 -> 1149.05 | D50: kg/day | E50: Metals in char matrix (ferrous+Al+other)
A51: T5.8 | B51: Glass/inerts in char matrix (kg/day) | C51: =C37+C38 -> 3635.8 | D51: kg/day | E51: Glass + inerts become mineral fraction in char
A52: T5.9 | B52: Moisture driven off as steam (kg/day) | C52: =C39 -> 10976 | D52: kg/day | E52: All moisture exits as steam
A53: T5.10 | B53: Other fraction (gas/residue) | C53: =C40 -> 3430 | D53: kg/day | E53: Minor fraction
B54: Reactor mass balance check | C54: =C41-(C44+C46+C47+C48+C49+C50+C51+C52+C53) -> 436.296 | D54: kg/day | E54: Should be 0 (±1 rounding)
B56: T6 — TOTAL SOLID OUTPUT FROM REACTOR (before post-sorting)
A57: T6.1 | B57: Total combustible char (kg/day) | C57: =C47+C48 -> 48743.73 | D57: kg/day | E57: Plastic char + organic char
A58: T6.2 | B58: Total metals in char (kg/day) | C58: =C50 -> 1149.05 | D58: kg/day | E58: Metals embedded in char matrix
A59: T6.3 | B59: Total mineral/glass in char (kg/day) | C59: =C51 -> 3635.8 | D59: kg/day | E59: Non-combustible fines in char
A60: T6.4 | B60: Total mixed solids output (kg/day) | C60: =C57+C58+C59 -> 53528.58 | D60: kg/day | E60: Everything solid exiting the reactor
B62: T7 — POST-SORTING OUTPUT (kg/day) — only if post-sorting enabled
A63: T7.1 | B63: Screened combustible char (kg/day) | C63: =IF('3-Operations'!C7=1,C57*'3-Operations'!C21,0) -> 41432.171 | D63: kg/day | E63: If post-sort ON: char × screening efficiency
A64: T7.2 | B64: Metals recovered from char (kg/day) | C64: =IF('3-Operations'!C7=1,C58*'3-Operations'!C22,0) -> 919.24 | D64: kg/day | E64: If post-sort ON: metals × recovery rate
A65: T7.3 | B65: Mineral inerts separated (kg/day) | C65: =IF('3-Operations'!C7=1,C59*'3-Operations'!C23,0) -> 2545.06 | D65: kg/day | E65: If post-sort ON: inerts × separation rate
A66: T7.4 | B66: Residue for disposal (kg/day) | C66: =IF('3-Operations'!C7=1,C60-C63-C64-C65,0) -> 8632.1095 | D66: kg/day | E66: Unseparated remainder — disposal cost
B68: T8 — NET SALEABLE OUTPUTS SUMMARY (kg/day)
A69: T8.1 | B69: Oil for sale (kg/day) | C69: =C44 -> 28530.054 | D69: kg/day | E69: All oil produced (or net of internal use, see R2)
A70: T8.2 | B70: Oil for sale (L/day) | C70: =C45 -> 33564.769 | D70: L/day
A71: T8.3 | B71: Char for sale (kg/day) | C71: =IF('3-Operations'!C7=1,C63,C57) -> 41432.171 | D71: kg/day | E71: V2: All char for sale (no internal burning). Post-sort=screened, else=total.
A72: T8.4 | B72: Metals for sale — pre-sorted (kg/day) | C72: =C23+C24 -> 5710.95 | D72: kg/day | E72: Pre-sort: ferrous + Al removed before reactor
A73: T8.5 | B73: Metals for sale — post-sorted (kg/day) | C73: =C64 -> 919.24 | D73: kg/day | E73: Post-sort: metals recovered from char
A74: T8.6 | B74: Glass for sale (pre-sorted) (kg/day) | C74: =C25 -> 5282.2 | D74: kg/day | E74: Pre-sort glass only
A75: T8.9 | B75: Total for disposal (kg/day) | C75: =C7+IF('3-Operations'!C6=1,C28,0)+IF('3-Operations'!C7=1,C66,IF('3-Operations'!C7=0,C58+C59,0))+C65 -> 15349.169 | D75: kg/day | E75: Rejected + pre-sort inerts + post-sort residue + separated mineral inerts
B77: T9 — ENERGY BALANCE (V2: External energy model)
A78: T9.1 | B78: Off-gas energy from plastic (MJ/day) | C78: =C32*'1-Waste Input'!C56 -> 44009.095 | D78: MJ/day | E78: Off-gas mass × energy per kg plastic × (yield ratio)
A79: T9.2 | B79: Off-gas energy from organic (MJ/day) | C79: =C33*(1-'1-Waste Input'!C43)*'1-Waste Input'!C45 -> 9995.02 | D79: MJ/day | E79: Organic off-gas mass × CV per kg organic off-gas
A80: T9.3 | B80: Total off-gas energy (MJ/day) | C80: =C78+C79 -> 54004.115 | D80: MJ/day
A81: T9.4 | B81: Char energy — organic char (MJ/day) | C81: =C48*'1-Waste Input'!C46 -> 667409.4 | D81: MJ/day | E81: Organic char × CV organic
A82: T9.5 | B82: Char energy — plastic char (MJ/day) | C82: =C47*'1-Waste Input'!C47 -> 106244.25 | D82: MJ/day | E82: Plastic char × CV plastic
A83: T9.6 | B83: Total char energy available (MJ/day) | C83: =C81+C82 -> 773653.65 | D83: MJ/day
A84: T9.7 | B84: Total heating demand (MJ/day) | C84: =C41/1000*'1-Waste Input'!C48 -> 338801.78 | D84: MJ/day | E84: Reactor feed (T) × MJ/T
A85: T9.8 | B85: Off-gas coverage (%) | C85: =IF(C84=0,0,C80/C84) -> 0.15939738 | D85: % | E85: Off-gas energy ÷ heating demand
A87: T9.12 | B87: Surplus char available for sale (kg/day) | C87: =C57 -> 48743.73 | D87: kg/day | E87: V2: All combustible char available for sale.
A88: T9.13 | B88: External heating oil needed after off-gas offset (L/day) | C88: =MAX(0,(C84-C80))/38 -> 7494.6755 | D88: L/day | E88: V2: All heating from purchased oil. 38 MJ/L energy content.
A89: T9.14 | B89: Annual fuel cost (EUR) | C89: =C88*'1-Waste Input'!C10*'2-Financial Inputs'!C57 -> 989297.16 | D89: EUR/year | E89: V2: Full-capacity annual heating oil cost. Ramp-up applied in OPEX.
A90: T9.15 | B90: Annual electricity cost (EUR/year) | C90: ='2-Financial Inputs'!C74*'1-Waste Input'!C10*'2-Financial Inputs'!C58 -> 237600 | D90: EUR/year | E90: V2: kWh/day × operating days × EUR/kWh. Full capacity.
B91: T10 — ANNUAL VOLUMES (steady state)
A92: T10.1 | B92: Annual oil production (litres) | C92: =C70*'1-Waste Input'!C10 -> 11076374 | D92: L/year | E92: Daily litres × operating days
A93: T10.2 | B93: Annual oil production (tonnes) | C93: =C69*'1-Waste Input'!C10/1000 -> 9414.9178 | D93: T/year | E93: Daily kg × days ÷ 1000
A94: T10.3 | B94: Annual char for sale (tonnes) | C94: =C71*'1-Waste Input'!C10/1000 -> 13672.616 | D94: T/year
A95: T10.4 | B95: Annual pre-sorted metals (tonnes) | C95: =C72*'1-Waste Input'!C10/1000 -> 1884.6135 | D95: T/year
A96: T10.5 | B96: Annual post-sorted metals (tonnes) | C96: =C73*'1-Waste Input'!C10/1000 -> 303.3492 | D96: T/year
A97: T10.6 | B97: Annual pre-sorted glass (tonnes) | C97: =C74*'1-Waste Input'!C10/1000 -> 1743.126 | D97: T/year
A98: T10.9 | B98: Annual disposal volume (tonnes) | C98: =C75*'1-Waste Input'!C10/1000 -> 5065.2259 | D98: T/year
B100: T11 — CARBON CREDITS
A101: T11.1 | B101: CO₂ avoided vs incineration (T/year) | C101: ='1-Waste Input'!C12*'2-Financial Inputs'!C62*0.8 -> 66528 | D101: T CO₂/year | E101: Throughput × baseline × 80% creditable
A102: T11.2 | B102: CO₂ from process + fuel (T/year) | C102: ='1-Waste Input'!C12*0.4 -> 18480 | D102: T CO₂/year | E102: Estimate: 0.4 T CO₂ per T waste processed
A103: T11.3 | B103: Net CO₂ reduction (T/year) | C103: =MAX(0,C101-C102) -> 48048 | D103: T CO₂/year

Sheet CAPEX
A1: Capital Expenditure Breakdown (V2)
A2: All values in EUR. Blue = input assumption.
A4: # | B4: Item | C4: Amount (EUR) | D4: % of Total | E4: Notes
B5: CORE PROCESSING CAPEX
A6: 1 | B6: URC-2000 machine price | C6: 50000000 | E6: Urban Rig URC-2000 spec. Scales with capacity.
A7: 2 | B7: Installation & commissioning | C7: 200000 | E7: Site installation.
A8: 3 | B8: Freight | C8: 400000 | E8: Transport from manufacturing site.
A9: 4 | B9: Training package | C9: 300000 | E9: Operator and maintenance training.
A10: 5 | B10: Accessories & spares | C10: 2000000 | E10: Spare parts, tools, monitoring.
A11: 6 | B11: Building / site preparation | C11: 5000000 | E11: Civil works, foundations, utilities.
B12: Core subtotal | C12: =SUM(C6:C11) -> 57900000
B14: PRE-SORTING CAPEX (revised — equipment FOB + install)
A15: 7 | B15: Trommel / screening unit | C15: 250000 | E15: Komptech/Doppstadt class, 6 T/hr MSW. EU OEM €200-350K.
A16: 8 | B16: Overband magnetic separator (ferrous) | C16: 60000 | E16: Steinert/Eriez/Bunting 1200mm belt. EU OEM €40-80K.
A17: 9 | B17: Eddy current separator (aluminium) | C17: 120000 | E17: Steinert NES 150, 1500mm belt. EU OEM €80-150K.
A18: 10 | B18: Optical / NIR sorter (PET/HDPE) | C18: 300000 | E18: TOMRA AUTOSORT or Pellenc ST. EU OEM €250-450K. OPTIONAL.
A19: 11 | B19: Conveyors, hoppers, platforms | C19: 250000 | E19: ~70m belt conveyor + structural steel. €1.5-3K/m installed.
A20: 12 | B20: Pre-sorting installation & integration | C20: 100000 | E20: Mechanical + electrical integration.
B21: Pre-sorting subtotal (if enabled) | C21: =IF('3-Operations'!C6=1,SUM(C15:C20),0) -> 1080000
B23: POST-SORTING CAPEX (revised — equipment FOB + install)
A24: 13 | B24: Vibrating screen / char trommel | C24: 80000 | E24: 3-5 T/hr char screening. EU OEM €60-120K.
A25: 14 | B25: Magnetic separator (post-reactor) | C25: 40000 | E25: Drum magnet for ferrous from char. EU OEM €30-60K.
A26: 15 | B26: Density separator (mineral fines) | C26: 80000 | E26: Air table or jig. EU OEM €60-120K.
A27: 16 | B27: Briquetting / pelletising press | C27: 150000 | E27: RUF/WEIMA/C.F. Nielsen 2-3 T/hr. OPTIONAL. EU OEM €100-200K.
A28: 17 | B28: Post-sorting installation & integration | C28: 80000 | E28: Mechanical + electrical integration.
B29: Post-sorting subtotal (if enabled) | C29: =IF('3-Operations'!C7=1,SUM(C24:C28),0) -> 430000
B31: SITE COMPLIANCE & ENGINEERING (NEW)
A32: 18 | B32: ATEX compliance (zonage, ventilation, éclairage) | C32: 400000 | E32: Mandatory for char dust. Zonage + captation + détection. €300-500K.
A33: 19 | B33: Dépoussiérage / dust extraction system | C33: 250000 | E33: Filtration, extraction, cyclones. €150-350K depending on config.
A34: 20 | B34: Ingénierie détaillée / detailed engineering | C34: 350000 | E34: Process design, P&ID, civil, electrical, structural. €250-500K.
A35: 21 | B35: Études environnementales & ICPE permitting | C35: 150000 | E35: EIA, ICPE dossier, public enquiry. France: €100-200K.
A36: 22 | B36: Maîtrise d'œuvre / project management | C36: 200000 | E36: Construction supervision, commissioning oversight. 12-18 months.
A37: 23 | B37: Assurance décennale & contrôles techniques | C37: 50000 | E37: Bureau Veritas / Apave inspections, certifications.
B38: Compliance & engineering subtotal | C38: =SUM(C32:C37) -> 1400000
B40: CONTINGENCY & TOTAL
A41: 24 | B41: Contingency (5% of total equipment) | C41: =(C12+C21+C29)*0.05 -> 2970500 | E41: Risk buffer on equipment only.
B43: TOTAL CAPEX | C43: =C12+C21+C29+C38+C41 -> 63780500
B45: FINANCING BREAKDOWN
B46: Loan amount (debt) | C46: =C43*'2-Financial Inputs'!C6 -> 44646350 | D46: EUR
B47: Equity required | C47: =C43-C46 -> 19134150 | D47: EUR
B48: Annual depreciation | C48: =C43/'2-Financial Inputs'!C10 -> 4252033.3 | D48: EUR/year
B50: CAPEX BREAKDOWN (%)
B51: Core processing | C51: =IF(C43=0,0,C12/C43) -> 0.90780097
B52: Pre-sorting | C52: =IF(C43=0,0,C21/C43) -> 0.016933075
B53: Post-sorting | C53: =IF(C43=0,0,C29/C43) -> 0.0067418725
B54: Compliance & engineering | C54: =IF(C43=0,0,C38/C43) -> 0.021950283
B55: Contingency | C55: =IF(C43=0,0,C41/C43) -> 0.046573796

Sheet Revenue
A1: Revenue Model — 15-Year Projection (V2)
C3: Year 1 | D3: Year 2 | E3: Year 3 | F3: Year 4 | G3: Year 5 | H3: Year 6 | I3: Year 7 | J3: Year 8 | K3: Year 9 | L3: Year 10 | M3: Year 11 | N3: Year 12 | O3: Year 13 | P3: Year 14 | Q3: Year 15
B4: Capacity utilisation | C4: ='3-Operations'!C30 -> 0.7 | D4: ='3-Operations'!C31 -> 0.85 | E4: ='3-Operations'!C32 -> 1 | F4: ='3-Operations'!C32 -> 1 | G4: ='3-Operations'!C32 -> 1 | H4: ='3-Operations'!C32 -> 1 | I4: ='3-Operations'!C32 -> 1 | J4: ='3-Operations'!C32 -> 1 | K4: ='3-Operations'!C32 -> 1 | L4: ='3-Operations'!C32 -> 1 | M4: ='3-Operations'!C32 -> 1 | N4: ='3-Operations'!C32 -> 1 | O4: ='3-Operations'!C32 -> 1 | P4: ='3-Operations'!C32 -> 1 | Q4: ='3-Operations'!C32 -> 1
B5: Annual throughput (T) | C5: ='1-Waste Input'!C12*C4 -> 32340 | D5: ='1-Waste Input'!C12*D4 -> 39270 | E5: ='1-Waste Input'!C12*E4 -> 46200 | F5: ='1-Waste Input'!C12*F4 -> 46200 | G5: ='1-Waste Input'!C12*G4 -> 46200 | H5: ='1-Waste Input'!C12*H4 -> 46200 | I5: ='1-Waste Input'!C12*I4 -> 46200 | J5: ='1-Waste Input'!C12*J4 -> 46200 | K5: ='1-Waste Input'!C12*K4 -> 46200 | L5: ='1-Waste Input'!C12*L4 -> 46200 | M5: ='1-Waste Input'!C12*M4 -> 46200 | N5: ='1-Waste Input'!C12*N4 -> 46200 | O5: ='1-Waste Input'!C12*O4 -> 46200 | P5: ='1-Waste Input'!C12*P4 -> 46200 | Q5: ='1-Waste Input'!C12*Q4 -> 46200
B7: GATE FEE REVENUE
B8: Gate fee revenue | C8: ='2-Financial Inputs'!$C$22*C5*(1+'2-Financial Inputs'!$C$11)^0 -> 3557400 | D8: ='2-Financial Inputs'!$C$22*D5*(1+'2-Financial Inputs'!$C$11)^1 -> 4406094 | E8: ='2-Financial Inputs'!$C$22*E5*(1+'2-Financial Inputs'!$C$11)^2 -> 5287312.8 | F8: ='2-Financial Inputs'!$C$22*F5*(1+'2-Financial Inputs'!$C$11)^3 -> 5393059.1 | G8: ='2-Financial Inputs'!$C$22*G5*(1+'2-Financial Inputs'!$C$11)^4 -> 5500920.2 | H8: ='2-Financial Inputs'!$C$22*H5*(1+'2-Financial Inputs'!$C$11)^5 -> 5610938.6 | I8: ='2-Financial Inputs'!$C$22*I5*(1+'2-Financial Inputs'!$C$11)^6 -> 5723157.4 | J8: ='2-Financial Inputs'!$C$22*J5*(1+'2-Financial Inputs'!$C$11)^7 -> 5837620.6 | K8: ='2-Financial Inputs'!$C$22*K5*(1+'2-Financial Inputs'!$C$11)^8 -> 5954373 | L8: ='2-Financial Inputs'!$C$22*L5*(1+'2-Financial Inputs'!$C$11)^9 -> 6073460.4 | M8: ='2-Financial Inputs'!$C$22*M5*(1+'2-Financial Inputs'!$C$11)^10 -> 6194929.6 | N8: ='2-Financial Inputs'!$C$22*N5*(1+'2-Financial Inputs'!$C$11)^11 -> 6318828.2 | O8: ='2-Financial Inputs'!$C$22*O5*(1+'2-Financial Inputs'!$C$11)^12 -> 6445204.8 | P8: ='2-Financial Inputs'!$C$22*P5*(1+'2-Financial Inputs'!$C$11)^13 -> 6574108.9 | Q8: ='2-Financial Inputs'!$C$22*Q5*(1+'2-Financial Inputs'!$C$11)^14 -> 6705591.1
B10: OIL REVENUE
B11: Oil volume (litres) | C11: ='4-Production Calcs'!C92*C4 -> 7753461.7 | D11: ='4-Production Calcs'!C92*D4 -> 9414917.8 | E11: ='4-Production Calcs'!C92*E4 -> 11076374 | F11: ='4-Production Calcs'!C92*F4 -> 11076374 | G11: ='4-Production Calcs'!C92*G4 -> 11076374 | H11: ='4-Production Calcs'!C92*H4 -> 11076374 | I11: ='4-Production Calcs'!C92*I4 -> 11076374 | J11: ='4-Production Calcs'!C92*J4 -> 11076374 | K11: ='4-Production Calcs'!C92*K4 -> 11076374 | L11: ='4-Production Calcs'!C92*L4 -> 11076374 | M11: ='4-Production Calcs'!C92*M4 -> 11076374 | N11: ='4-Production Calcs'!C92*N4 -> 11076374 | O11: ='4-Production Calcs'!C92*O4 -> 11076374 | P11: ='4-Production Calcs'!C92*P4 -> 11076374 | Q11: ='4-Production Calcs'!C92*Q4 -> 11076374
B12: Oil revenue | C12: =C11*'2-Financial Inputs'!$C$34*(1+'2-Financial Inputs'!$C$11)^0 -> 4224473.6 | D12: =D11*'2-Financial Inputs'!$C$34*(1+'2-Financial Inputs'!$C$11)^1 -> 5232312.3 | E12: =E11*'2-Financial Inputs'!$C$34*(1+'2-Financial Inputs'!$C$11)^2 -> 6278774.8 | F12: =F11*'2-Financial Inputs'!$C$34*(1+'2-Financial Inputs'!$C$11)^3 -> 6404350.3 | G12: =G11*'2-Financial Inputs'!$C$34*(1+'2-Financial Inputs'!$C$11)^4 -> 6532437.3 | H12: =H11*'2-Financial Inputs'!$C$34*(1+'2-Financial Inputs'!$C$11)^5 -> 6663086 | I12: =I11*'2-Financial Inputs'!$C$34*(1+'2-Financial Inputs'!$C$11)^6 -> 6796347.8 | J12: =J11*'2-Financial Inputs'!$C$34*(1+'2-Financial Inputs'!$C$11)^7 -> 6932274.7 | K12: =K11*'2-Financial Inputs'!$C$34*(1+'2-Financial Inputs'!$C$11)^8 -> 7070920.2 | L12: =L11*'2-Financial Inputs'!$C$34*(1+'2-Financial Inputs'!$C$11)^9 -> 7212338.6 | M12: =M11*'2-Financial Inputs'!$C$34*(1+'2-Financial Inputs'!$C$11)^10 -> 7356585.4 | N12: =N11*'2-Financial Inputs'!$C$34*(1+'2-Financial Inputs'!$C$11)^11 -> 7503717.1 | O12: =O11*'2-Financial Inputs'!$C$34*(1+'2-Financial Inputs'!$C$11)^12 -> 7653791.4 | P12: =P11*'2-Financial Inputs'!$C$34*(1+'2-Financial Inputs'!$C$11)^13 -> 7806867.3 | Q12: =Q11*'2-Financial Inputs'!$C$34*(1+'2-Financial Inputs'!$C$11)^14 -> 7963004.6
B14: CHAR REVENUE
B15: Char for sale (T/year) | C15: ='4-Production Calcs'!C94*C4 -> 9570.8314 | D15: ='4-Production Calcs'!C94*D4 -> 11621.724 | E15: ='4-Production Calcs'!C94*E4 -> 13672.616 | F15: ='4-Production Calcs'!C94*F4 -> 13672.616 | G15: ='4-Production Calcs'!C94*G4 -> 13672.616 | H15: ='4-Production Calcs'!C94*H4 -> 13672.616 | I15: ='4-Production Calcs'!C94*I4 -> 13672.616 | J15: ='4-Production Calcs'!C94*J4 -> 13672.616 | K15: ='4-Production Calcs'!C94*K4 -> 13672.616 | L15: ='4-Production Calcs'!C94*L4 -> 13672.616 | M15: ='4-Production Calcs'!C94*M4 -> 13672.616 | N15: ='4-Production Calcs'!C94*N4 -> 13672.616 | O15: ='4-Production Calcs'!C94*O4 -> 13672.616 | P15: ='4-Production Calcs'!C94*P4 -> 13672.616 | Q15: ='4-Production Calcs'!C94*Q4 -> 13672.616
B16: Char revenue | C16: =C15*'2-Financial Inputs'!$C$46*(1+'2-Financial Inputs'!$C$11)^0 -> 957083.14 | D16: =D15*'2-Financial Inputs'!$C$46*(1+'2-Financial Inputs'!$C$11)^1 -> 1185415.8 | E16: =E15*'2-Financial Inputs'!$C$46*(1+'2-Financial Inputs'!$C$11)^2 -> 1422499 | F16: =F15*'2-Financial Inputs'!$C$46*(1+'2-Financial Inputs'!$C$11)^3 -> 1450949 | G16: =G15*'2-Financial Inputs'!$C$46*(1+'2-Financial Inputs'!$C$11)^4 -> 1479968 | H16: =H15*'2-Financial Inputs'!$C$46*(1+'2-Financial Inputs'!$C$11)^5 -> 1509567.3 | I16: =I15*'2-Financial Inputs'!$C$46*(1+'2-Financial Inputs'!$C$11)^6 -> 1539758.7 | J16: =J15*'2-Financial Inputs'!$C$46*(1+'2-Financial Inputs'!$C$11)^7 -> 1570553.8 | K16: =K15*'2-Financial Inputs'!$C$46*(1+'2-Financial Inputs'!$C$11)^8 -> 1601964.9 | L16: =L15*'2-Financial Inputs'!$C$46*(1+'2-Financial Inputs'!$C$11)^9 -> 1634004.2 | M16: =M15*'2-Financial Inputs'!$C$46*(1+'2-Financial Inputs'!$C$11)^10 -> 1666684.3 | N16: =N15*'2-Financial Inputs'!$C$46*(1+'2-Financial Inputs'!$C$11)^11 -> 1700018 | O16: =O15*'2-Financial Inputs'!$C$46*(1+'2-Financial Inputs'!$C$11)^12 -> 1734018.3 | P16: =P15*'2-Financial Inputs'!$C$46*(1+'2-Financial Inputs'!$C$11)^13 -> 1768698.7 | Q16: =Q15*'2-Financial Inputs'!$C$46*(1+'2-Financial Inputs'!$C$11)^14 -> 1804072.7
B18: METAL REVENUE
B19: Pre-sorted metals (T/year) | C19: ='4-Production Calcs'!C95*C4 -> 1319.2295 | D19: ='4-Production Calcs'!C95*D4 -> 1601.9215 | E19: ='4-Production Calcs'!C95*E4 -> 1884.6135 | F19: ='4-Production Calcs'!C95*F4 -> 1884.6135 | G19: ='4-Production Calcs'!C95*G4 -> 1884.6135 | H19: ='4-Production Calcs'!C95*H4 -> 1884.6135 | I19: ='4-Production Calcs'!C95*I4 -> 1884.6135 | J19: ='4-Production Calcs'!C95*J4 -> 1884.6135 | K19: ='4-Production Calcs'!C95*K4 -> 1884.6135 | L19: ='4-Production Calcs'!C95*L4 -> 1884.6135 | M19: ='4-Production Calcs'!C95*M4 -> 1884.6135 | N19: ='4-Production Calcs'!C95*N4 -> 1884.6135 | O19: ='4-Production Calcs'!C95*O4 -> 1884.6135 | P19: ='4-Production Calcs'!C95*P4 -> 1884.6135 | Q19: ='4-Production Calcs'!C95*Q4 -> 1884.6135
B20: Post-sorted metals (T/year) | C20: ='4-Production Calcs'!C96*C4 -> 212.34444 | D20: ='4-Production Calcs'!C96*D4 -> 257.84682 | E20: ='4-Production Calcs'!C96*E4 -> 303.3492 | F20: ='4-Production Calcs'!C96*F4 -> 303.3492 | G20: ='4-Production Calcs'!C96*G4 -> 303.3492 | H20: ='4-Production Calcs'!C96*H4 -> 303.3492 | I20: ='4-Production Calcs'!C96*I4 -> 303.3492 | J20: ='4-Production Calcs'!C96*J4 -> 303.3492 | K20: ='4-Production Calcs'!C96*K4 -> 303.3492 | L20: ='4-Production Calcs'!C96*L4 -> 303.3492 | M20: ='4-Production Calcs'!C96*M4 -> 303.3492 | N20: ='4-Production Calcs'!C96*N4 -> 303.3492 | O20: ='4-Production Calcs'!C96*O4 -> 303.3492 | P20: ='4-Production Calcs'!C96*P4 -> 303.3492 | Q20: ='4-Production Calcs'!C96*Q4 -> 303.3492
B21: Metal revenue (all sources) | C21: =(C19*'2-Financial Inputs'!$C$49+C20*'2-Financial Inputs'!$C$52)*(1+'2-Financial Inputs'!$C$11)^0 -> 393510.69 | D21: =(D19*'2-Financial Inputs'!$C$49+D20*'2-Financial Inputs'!$C$52)*(1+'2-Financial Inputs'!$C$11)^1 -> 487391.1 | E21: =(E19*'2-Financial Inputs'!$C$49+E20*'2-Financial Inputs'!$C$52)*(1+'2-Financial Inputs'!$C$11)^2 -> 584869.32 | F21: =(F19*'2-Financial Inputs'!$C$49+F20*'2-Financial Inputs'!$C$52)*(1+'2-Financial Inputs'!$C$11)^3 -> 596566.71 | G21: =(G19*'2-Financial Inputs'!$C$49+G20*'2-Financial Inputs'!$C$52)*(1+'2-Financial Inputs'!$C$11)^4 -> 608498.04 | H21: =(H19*'2-Financial Inputs'!$C$49+H20*'2-Financial Inputs'!$C$52)*(1+'2-Financial Inputs'!$C$11)^5 -> 620668.01 | I21: =(I19*'2-Financial Inputs'!$C$49+I20*'2-Financial Inputs'!$C$52)*(1+'2-Financial Inputs'!$C$11)^6 -> 633081.37 | J21: =(J19*'2-Financial Inputs'!$C$49+J20*'2-Financial Inputs'!$C$52)*(1+'2-Financial Inputs'!$C$11)^7 -> 645742.99 | K21: =(K19*'2-Financial Inputs'!$C$49+K20*'2-Financial Inputs'!$C$52)*(1+'2-Financial Inputs'!$C$11)^8 -> 658657.85 | L21: =(L19*'2-Financial Inputs'!$C$49+L20*'2-Financial Inputs'!$C$52)*(1+'2-Financial Inputs'!$C$11)^9 -> 671831.01 | M21: =(M19*'2-Financial Inputs'!$C$49+M20*'2-Financial Inputs'!$C$52)*(1+'2-Financial Inputs'!$C$11)^10 -> 685267.63 | N21: =(N19*'2-Financial Inputs'!$C$49+N20*'2-Financial Inputs'!$C$52)*(1+'2-Financial Inputs'!$C$11)^11 -> 698972.98 | O21: =(O19*'2-Financial Inputs'!$C$49+O20*'2-Financial Inputs'!$C$52)*(1+'2-Financial Inputs'!$C$11)^12 -> 712952.44 | P21: =(P19*'2-Financial Inputs'!$C$49+P20*'2-Financial Inputs'!$C$52)*(1+'2-Financial Inputs'!$C$11)^13 -> 727211.49 | Q21: =(Q19*'2-Financial Inputs'!$C$49+Q20*'2-Financial Inputs'!$C$52)*(1+'2-Financial Inputs'!$C$11)^14 -> 741755.72
B23: PRE-SORTED RECYCLABLES REVENUE
B24: Glass revenue | C24: ='4-Production Calcs'!C97*C4*'2-Financial Inputs'!$C$53*(1+'2-Financial Inputs'!$C$11)^0 -> 36605.646 | D24: ='4-Production Calcs'!C97*D4*'2-Financial Inputs'!$C$53*(1+'2-Financial Inputs'!$C$11)^1 -> 45338.707 | E24: ='4-Production Calcs'!C97*E4*'2-Financial Inputs'!$C$53*(1+'2-Financial Inputs'!$C$11)^2 -> 54406.449 | F24: ='4-Production Calcs'!C97*F4*'2-Financial Inputs'!$C$53*(1+'2-Financial Inputs'!$C$11)^3 -> 55494.578 | G24: ='4-Production Calcs'!C97*G4*'2-Financial Inputs'!$C$53*(1+'2-Financial Inputs'!$C$11)^4 -> 56604.469 | H24: ='4-Production Calcs'!C97*H4*'2-Financial Inputs'!$C$53*(1+'2-Financial Inputs'!$C$11)^5 -> 57736.559 | I24: ='4-Production Calcs'!C97*I4*'2-Financial Inputs'!$C$53*(1+'2-Financial Inputs'!$C$11)^6 -> 58891.29 | J24: ='4-Production Calcs'!C97*J4*'2-Financial Inputs'!$C$53*(1+'2-Financial Inputs'!$C$11)^7 -> 60069.116 | K24: ='4-Production Calcs'!C97*K4*'2-Financial Inputs'!$C$53*(1+'2-Financial Inputs'!$C$11)^8 -> 61270.498 | L24: ='4-Production Calcs'!C97*L4*'2-Financial Inputs'!$C$53*(1+'2-Financial Inputs'!$C$11)^9 -> 62495.908 | M24: ='4-Production Calcs'!C97*M4*'2-Financial Inputs'!$C$53*(1+'2-Financial Inputs'!$C$11)^10 -> 63745.826 | N24: ='4-Production Calcs'!C97*N4*'2-Financial Inputs'!$C$53*(1+'2-Financial Inputs'!$C$11)^11 -> 65020.743 | O24: ='4-Production Calcs'!C97*O4*'2-Financial Inputs'!$C$53*(1+'2-Financial Inputs'!$C$11)^12 -> 66321.157 | P24: ='4-Production Calcs'!C97*P4*'2-Financial Inputs'!$C$53*(1+'2-Financial Inputs'!$C$11)^13 -> 67647.581 | Q24: ='4-Production Calcs'!C97*Q4*'2-Financial Inputs'!$C$53*(1+'2-Financial Inputs'!$C$11)^14 -> 69000.532
B25: Total recyclables revenue | C25: =SUM(C24) -> 36605.646 | D25: =SUM(D24) -> 45338.707 | E25: =SUM(E24) -> 54406.449 | F25: =SUM(F24) -> 55494.578 | G25: =SUM(G24) -> 56604.469 | H25: =SUM(H24) -> 57736.559 | I25: =SUM(I24) -> 58891.29 | J25: =SUM(J24) -> 60069.116 | ... Q25: =SUM(Q24) -> 69000.532
B27: CARBON CREDIT REVENUE
B28: Carbon credit revenue | C28: ='4-Production Calcs'!C103*C4*'2-Financial Inputs'!$C$61*(1+'2-Financial Inputs'!$C$11)^0 -> 1681680 | D28: ='4-Production Calcs'!C103*D4*'2-Financial Inputs'!$C$61*(1+'2-Financial Inputs'!$C$11)^1 -> 2082880.8 | E28: ='4-Production Calcs'!C103*E4*'2-Financial Inputs'!$C$61*(1+'2-Financial Inputs'!$C$11)^2 -> 2499457 | F28: ='4-Production Calcs'!C103*F4*'2-Financial Inputs'!$C$61*(1+'2-Financial Inputs'!$C$11)^3 -> 2549446.1 | G28: ='4-Production Calcs'!C103*G4*'2-Financial Inputs'!$C$61*(1+'2-Financial Inputs'!$C$11)^4 -> 2600435 | H28: ='4-Production Calcs'!C103*H4*'2-Financial Inputs'!$C$61*(1+'2-Financial Inputs'!$C$11)^5 -> 2652443.7 | I28: ='4-Production Calcs'!C103*I4*'2-Financial Inputs'!$C$61*(1+'2-Financial Inputs'!$C$11)^6 -> 2705492.6 | J28: ='4-Production Calcs'!C103*J4*'2-Financial Inputs'!$C$61*(1+'2-Financial Inputs'!$C$11)^7 -> 2759602.4 | K28: ='4-Production Calcs'!C103*K4*'2-Financial Inputs'!$C$61*(1+'2-Financial Inputs'!$C$11)^8 -> 2814794.5 | L28: ='4-Production Calcs'!C103*L4*'2-Financial Inputs'!$C$61*(1+'2-Financial Inputs'!$C$11)^9 -> 2871090.4 | M28: ='4-Production Calcs'!C103*M4*'2-Financial Inputs'!$C$61*(1+'2-Financial Inputs'!$C$11)^10 -> 2928512.2 | N28: ='4-Production Calcs'!C103*N4*'2-Financial Inputs'!$C$61*(1+'2-Financial Inputs'!$C$11)^11 -> 2987082.4 | O28: ='4-Production Calcs'!C103*O4*'2-Financial Inputs'!$C$61*(1+'2-Financial Inputs'!$C$11)^12 -> 3046824.1 | P28: ='4-Production Calcs'!C103*P4*'2-Financial Inputs'!$C$61*(1+'2-Financial Inputs'!$C$11)^13 -> 3107760.6 | Q28: ='4-Production Calcs'!C103*Q4*'2-Financial Inputs'!$C$61*(1+'2-Financial Inputs'!$C$11)^14 -> 3169915.8
B30: DISPOSAL COSTS (negative)
B33: TOTAL REVENUE | C33: =C8+C12+C16+C21+C25+C28+C31 -> 10850753 | D33: =D8+D12+D16+D21+D25+D28+D31 -> 13439433 | E33: =E8+E12+E16+E21+E25+E28+E31 -> 16127319 | F33: =F8+F12+F16+F21+F25+F28+F31 -> 16449866 | G33: =G8+G12+G16+G21+G25+G28+G31 -> 16778863 | H33: =H8+H12+H16+H21+H25+H28+H31 -> 17114440 | I33: =I8+I12+I16+I21+I25+I28+I31 -> 17456729 | J33: =J8+J12+J16+J21+J25+J28+J31 -> 17805864 | ... Q33: =Q8+Q12+Q16+Q21+Q25+Q28+Q31 -> 20453340

Sheet OPEX
A1: Operating Expenditure — 15-Year Projection (V2)
C3: Year 1 | D3: Year 2 | E3: Year 3 | F3: Year 4 | G3: Year 5 | H3: Year 6 | I3: Year 7 | J3: Year 8 | K3: Year 9 | L3: Year 10 | M3: Year 11 | N3: Year 12 | O3: Year 13 | P3: Year 14 | Q3: Year 15
B4: CORE PROCESSING OPEX
B5: Core staff costs | C5: =('2-Financial Inputs'!$C$66+'2-Financial Inputs'!$C$67+'2-Financial Inputs'!$C$68)*'2-Financial Inputs'!$C$69*Revenue!C4*(1+'2-Financial Inputs'!$C$11)^0 -> 588000 | D5: =('2-Financial Inputs'!$C$66+'2-Financial Inputs'!$C$67+'2-Financial Inputs'!$C$68)*'2-Financial Inputs'!$C$69*Revenue!D4*(1+'2-Financial Inputs'!$C$11)^1 -> 728280 | E5: =('2-Financial Inputs'!$C$66+'2-Financial Inputs'!$C$67+'2-Financial Inputs'!$C$68)*'2-Financial Inputs'!$C$69*Revenue!E4*(1+'2-Financial Inputs'!$C$11)^2 -> 873936 | F5: =('2-Financial Inputs'!$C$66+'2-Financial Inputs'!$C$67+'2-Financial Inputs'!$C$68)*'2-Financial Inputs'!$C$69*Revenue!F4*(1+'2-Financial Inputs'!$C$11)^3 -> 891414.72 | G5: =('2-Financial Inputs'!$C$66+'2-Financial Inputs'!$C$67+'2-Financial Inputs'!$C$68)*'2-Financial Inputs'!$C$69*Revenue!G4*(1+'2-Financial Inputs'!$C$11)^4 -> 909243.01 | H5: =('2-Financial Inputs'!$C$66+'2-Financial Inputs'!$C$67+'2-Financial Inputs'!$C$68)*'2-Financial Inputs'!$C$69*Revenue!H4*(1+'2-Financial Inputs'!$C$11)^5 -> 927427.87 | I5: =('2-Financial Inputs'!$C$66+'2-Financial Inputs'!$C$67+'2-Financial Inputs'!$C$68)*'2-Financial Inputs'!$C$69*Revenue!I4*(1+'2-Financial Inputs'!$C$11)^6 -> 945976.43 | J5: =('2-Financial Inputs'!$C$66+'2-Financial Inputs'!$C$67+'2-Financial Inputs'!$C$68)*'2-Financial Inputs'!$C$69*Revenue!J4*(1+'2-Financial Inputs'!$C$11)^7 -> 964895.96 | K5: =('2-Financial Inputs'!$C$66+'2-Financial Inputs'!$C$67+'2-Financial Inputs'!$C$68)*'2-Financial Inputs'!$C$69*Revenue!K4*(1+'2-Financial Inputs'!$C$11)^8 -> 984193.88 | L5: =('2-Financial Inputs'!$C$66+'2-Financial Inputs'!$C$67+'2-Financial Inputs'!$C$68)*'2-Financial Inputs'!$C$69*Revenue!L4*(1+'2-Financial Inputs'!$C$11)^9 -> 1003877.8 | M5: =('2-Financial Inputs'!$C$66+'2-Financial Inputs'!$C$67+'2-Financial Inputs'!$C$68)*'2-Financial Inputs'!$C$69*Revenue!M4*(1+'2-Financial Inputs'!$C$11)^10 -> 1023955.3 | N5: =('2-Financial Inputs'!$C$66+'2-Financial Inputs'!$C$67+'2-Financial Inputs'!$C$68)*'2-Financial Inputs'!$C$69*Revenue!N4*(1+'2-Financial Inputs'!$C$11)^11 -> 1044434.4 | O5: =('2-Financial Inputs'!$C$66+'2-Financial Inputs'!$C$67+'2-Financial Inputs'!$C$68)*'2-Financial Inputs'!$C$69*Revenue!O4*(1+'2-Financial Inputs'!$C$11)^12 -> 1065323.1 | P5: =('2-Financial Inputs'!$C$66+'2-Financial Inputs'!$C$67+'2-Financial Inputs'!$C$68)*'2-Financial Inputs'!$C$69*Revenue!P4*(1+'2-Financial Inputs'!$C$11)^13 -> 1086629.6 | Q5: =('2-Financial Inputs'!$C$66+'2-Financial Inputs'!$C$67+'2-Financial Inputs'!$C$68)*'2-Financial Inputs'!$C$69*Revenue!Q4*(1+'2-Financial Inputs'!$C$11)^14 -> 1108362.2
B6: Maintenance | C6: ='2-Financial Inputs'!$C$72*CAPEX!$C$12*Revenue!C4*(1+'2-Financial Inputs'!$C$11)^0 -> 1621200 | D6: ='2-Financial Inputs'!$C$72*CAPEX!$C$12*Revenue!D4*(1+'2-Financial Inputs'!$C$11)^1 -> 2007972 | E6: ='2-Financial Inputs'!$C$72*CAPEX!$C$12*Revenue!E4*(1+'2-Financial Inputs'!$C$11)^2 -> 2409566.4 | F6: ='2-Financial Inputs'!$C$72*CAPEX!$C$12*Revenue!F4*(1+'2-Financial Inputs'!$C$11)^3 -> 2457757.7 | G6: ='2-Financial Inputs'!$C$72*CAPEX!$C$12*Revenue!G4*(1+'2-Financial Inputs'!$C$11)^4 -> 2506912.9 | H6: ='2-Financial Inputs'!$C$72*CAPEX!$C$12*Revenue!H4*(1+'2-Financial Inputs'!$C$11)^5 -> 2557051.1 | I6: ='2-Financial Inputs'!$C$72*CAPEX!$C$12*Revenue!I4*(1+'2-Financial Inputs'!$C$11)^6 -> 2608192.2 | J6: ='2-Financial Inputs'!$C$72*CAPEX!$C$12*Revenue!J4*(1+'2-Financial Inputs'!$C$11)^7 -> 2660356 | K6: ='2-Financial Inputs'!$C$72*CAPEX!$C$12*Revenue!K4*(1+'2-Financial Inputs'!$C$11)^8 -> 2713563.1 | L6: ='2-Financial Inputs'!$C$72*CAPEX!$C$12*Revenue!L4*(1+'2-Financial Inputs'!$C$11)^9 -> 2767834.4 | M6: ='2-Financial Inputs'!$C$72*CAPEX!$C$12*Revenue!M4*(1+'2-Financial Inputs'!$C$11)^10 -> 2823191.1 | N6: ='2-Financial Inputs'!$C$72*CAPEX!$C$12*Revenue!N4*(1+'2-Financial Inputs'!$C$11)^11 -> 2879654.9 | O6: ='2-Financial Inputs'!$C$72*CAPEX!$C$12*Revenue!O4*(1+'2-Financial Inputs'!$C$11)^12 -> 2937248 | P6: ='2-Financial Inputs'!$C$72*CAPEX!$C$12*Revenue!P4*(1+'2-Financial Inputs'!$C$11)^13 -> 2995993 | Q6: ='2-Financial Inputs'!$C$72*CAPEX!$C$12*Revenue!Q4*(1+'2-Financial Inputs'!$C$11)^14 -> 3055912.8
B7: Grid electricity | C7: ='2-Financial Inputs'!$C$74*'1-Waste Input'!$C$10*'2-Financial Inputs'!$C$58*Revenue!C4*(1+'2-Financial Inputs'!$C$11)^0 -> 166320 | D7: ='2-Financial Inputs'!$C$74*'1-Waste Input'!$C$10*'2-Financial Inputs'!$C$58*Revenue!D4*(1+'2-Financial Inputs'!$C$11)^1 -> 205999.2 | E7: ='2-Financial Inputs'!$C$74*'1-Waste Input'!$C$10*'2-Financial Inputs'!$C$58*Revenue!E4*(1+'2-Financial Inputs'!$C$11)^2 -> 247199.04 | F7: ='2-Financial Inputs'!$C$74*'1-Waste Input'!$C$10*'2-Financial Inputs'!$C$58*Revenue!F4*(1+'2-Financial Inputs'!$C$11)^3 -> 252143.02 | G7: ='2-Financial Inputs'!$C$74*'1-Waste Input'!$C$10*'2-Financial Inputs'!$C$58*Revenue!G4*(1+'2-Financial Inputs'!$C$11)^4 -> 257185.88 | H7: ='2-Financial Inputs'!$C$74*'1-Waste Input'!$C$10*'2-Financial Inputs'!$C$58*Revenue!H4*(1+'2-Financial Inputs'!$C$11)^5 -> 262329.6 | I7: ='2-Financial Inputs'!$C$74*'1-Waste Input'!$C$10*'2-Financial Inputs'!$C$58*Revenue!I4*(1+'2-Financial Inputs'!$C$11)^6 -> 267576.19 | J7: ='2-Financial Inputs'!$C$74*'1-Waste Input'!$C$10*'2-Financial Inputs'!$C$58*Revenue!J4*(1+'2-Financial Inputs'!$C$11)^7 -> 272927.71 | K7: ='2-Financial Inputs'!$C$74*'1-Waste Input'!$C$10*'2-Financial Inputs'!$C$58*Revenue!K4*(1+'2-Financial Inputs'!$C$11)^8 -> 278386.27 | L7: ='2-Financial Inputs'!$C$74*'1-Waste Input'!$C$10*'2-Financial Inputs'!$C$58*Revenue!L4*(1+'2-Financial Inputs'!$C$11)^9 -> 283953.99 | M7: ='2-Financial Inputs'!$C$74*'1-Waste Input'!$C$10*'2-Financial Inputs'!$C$58*Revenue!M4*(1+'2-Financial Inputs'!$C$11)^10 -> 289633.07 | N7: ='2-Financial Inputs'!$C$74*'1-Waste Input'!$C$10*'2-Financial Inputs'!$C$58*Revenue!N4*(1+'2-Financial Inputs'!$C$11)^11 -> 295425.74 | O7: ='2-Financial Inputs'!$C$74*'1-Waste Input'!$C$10*'2-Financial Inputs'!$C$58*Revenue!O4*(1+'2-Financial Inputs'!$C$11)^12 -> 301334.25 | P7: ='2-Financial Inputs'!$C$74*'1-Waste Input'!$C$10*'2-Financial Inputs'!$C$58*Revenue!P4*(1+'2-Financial Inputs'!$C$11)^13 -> 307360.94 | Q7: ='2-Financial Inputs'!$C$74*'1-Waste Input'!$C$10*'2-Financial Inputs'!$C$58*Revenue!Q4*(1+'2-Financial Inputs'!$C$11)^14 -> 313508.15
B8: Heating oil (reactor heating) | C8: ='4-Production Calcs'!C89*Revenue!C4*(1+'2-Financial Inputs'!$C$11)^0 -> 692508.01 | D8: ='4-Production Calcs'!C89*Revenue!D4*(1+'2-Financial Inputs'!$C$11)^1 -> 857720.64 | E8: ='4-Production Calcs'!C89*Revenue!E4*(1+'2-Financial Inputs'!$C$11)^2 -> 1029264.8 | F8: ='4-Production Calcs'!C89*Revenue!F4*(1+'2-Financial Inputs'!$C$11)^3 -> 1049850.1 | G8: ='4-Production Calcs'!C89*Revenue!G4*(1+'2-Financial Inputs'!$C$11)^4 -> 1070847.1 | H8: ='4-Production Calcs'!C89*Revenue!H4*(1+'2-Financial Inputs'!$C$11)^5 -> 1092264 | I8: ='4-Production Calcs'!C89*Revenue!I4*(1+'2-Financial Inputs'!$C$11)^6 -> 1114109.3 | J8: ='4-Production Calcs'!C89*Revenue!J4*(1+'2-Financial Inputs'!$C$11)^7 -> 1136391.5 | K8: ='4-Production Calcs'!C89*Revenue!K4*(1+'2-Financial Inputs'!$C$11)^8 -> 1159119.3 | L8: ='4-Production Calcs'!C89*Revenue!L4*(1+'2-Financial Inputs'!$C$11)^9 -> 1182301.7 | M8: ='4-Production Calcs'!C89*Revenue!M4*(1+'2-Financial Inputs'!$C$11)^10 -> 1205947.7 | N8: ='4-Production Calcs'!C89*Revenue!N4*(1+'2-Financial Inputs'!$C$11)^11 -> 1230066.7 | O8: ='4-Production Calcs'!C89*Revenue!O4*(1+'2-Financial Inputs'!$C$11)^12 -> 1254668 | P8: ='4-Production Calcs'!C89*Revenue!P4*(1+'2-Financial Inputs'!$C$11)^13 -> 1279761.4 | Q8: ='4-Production Calcs'!C89*Revenue!Q4*(1+'2-Financial Inputs'!$C$11)^14 -> 1305356.6
B9: Insurance | C9: ='2-Financial Inputs'!$C$75*CAPEX!$C$43*(1+'2-Financial Inputs'!$C$11)^0 -> 318902.5 | D9: ='2-Financial Inputs'!$C$75*CAPEX!$C$43*(1+'2-Financial Inputs'!$C$11)^1 -> 325280.55 | E9: ='2-Financial Inputs'!$C$75*CAPEX!$C$43*(1+'2-Financial Inputs'!$C$11)^2 -> 331786.16 | F9: ='2-Financial Inputs'!$C$75*CAPEX!$C$43*(1+'2-Financial Inputs'!$C$11)^3 -> 338421.88 | G9: ='2-Financial Inputs'!$C$75*CAPEX!$C$43*(1+'2-Financial Inputs'!$C$11)^4 -> 345190.32 | H9: ='2-Financial Inputs'!$C$75*CAPEX!$C$43*(1+'2-Financial Inputs'!$C$11)^5 -> 352094.13 | I9: ='2-Financial Inputs'!$C$75*CAPEX!$C$43*(1+'2-Financial Inputs'!$C$11)^6 -> 359136.01 | J9: ='2-Financial Inputs'!$C$75*CAPEX!$C$43*(1+'2-Financial Inputs'!$C$11)^7 -> 366318.73 | K9: ='2-Financial Inputs'!$C$75*CAPEX!$C$43*(1+'2-Financial Inputs'!$C$11)^8 -> 373645.11 | L9: ='2-Financial Inputs'!$C$75*CAPEX!$C$43*(1+'2-Financial Inputs'!$C$11)^9 -> 381118.01 | M9: ='2-Financial Inputs'!$C$75*CAPEX!$C$43*(1+'2-Financial Inputs'!$C$11)^10 -> 388740.37 | N9: ='2-Financial Inputs'!$C$75*CAPEX!$C$43*(1+'2-Financial Inputs'!$C$11)^11 -> 396515.18 | O9: ='2-Financial Inputs'!$C$75*CAPEX!$C$43*(1+'2-Financial Inputs'!$C$11)^12 -> 404445.48 | P9: ='2-Financial Inputs'!$C$75*CAPEX!$C$43*(1+'2-Financial Inputs'!$C$11)^13 -> 412534.39 | Q9: ='2-Financial Inputs'!$C$75*CAPEX!$C$43*(1+'2-Financial Inputs'!$C$11)^14 -> 420785.08
B10: Contingency / other | C10: ='2-Financial Inputs'!$C$73*CAPEX!$C$43*Revenue!C4*(1+'2-Financial Inputs'!$C$11)^0 -> 892927 | D10: ='2-Financial Inputs'!$C$73*CAPEX!$C$43*Revenue!D4*(1+'2-Financial Inputs'!$C$11)^1 -> 1105953.9 | E10: ='2-Financial Inputs'!$C$73*CAPEX!$C$43*Revenue!E4*(1+'2-Financial Inputs'!$C$11)^2 -> 1327144.6 | F10: ='2-Financial Inputs'!$C$73*CAPEX!$C$43*Revenue!F4*(1+'2-Financial Inputs'!$C$11)^3 -> 1353687.5 | G10: ='2-Financial Inputs'!$C$73*CAPEX!$C$43*Revenue!G4*(1+'2-Financial Inputs'!$C$11)^4 -> 1380761.3 | H10: ='2-Financial Inputs'!$C$73*CAPEX!$C$43*Revenue!H4*(1+'2-Financial Inputs'!$C$11)^5 -> 1408376.5 | I10: ='2-Financial Inputs'!$C$73*CAPEX!$C$43*Revenue!I4*(1+'2-Financial Inputs'!$C$11)^6 -> 1436544 | J10: ='2-Financial Inputs'!$C$73*CAPEX!$C$43*Revenue!J4*(1+'2-Financial Inputs'!$C$11)^7 -> 1465274.9 | K10: ='2-Financial Inputs'!$C$73*CAPEX!$C$43*Revenue!K4*(1+'2-Financial Inputs'!$C$11)^8 -> 1494580.4 | L10: ='2-Financial Inputs'!$C$73*CAPEX!$C$43*Revenue!L4*(1+'2-Financial Inputs'!$C$11)^9 -> 1524472 | M10: ='2-Financial Inputs'!$C$73*CAPEX!$C$43*Revenue!M4*(1+'2-Financial Inputs'!$C$11)^10 -> 1554961.5 | N10: ='2-Financial Inputs'!$C$73*CAPEX!$C$43*Revenue!N4*(1+'2-Financial Inputs'!$C$11)^11 -> 1586060.7 | O10: ='2-Financial Inputs'!$C$73*CAPEX!$C$43*Revenue!O4*(1+'2-Financial Inputs'!$C$11)^12 -> 1617781.9 | P10: ='2-Financial Inputs'!$C$73*CAPEX!$C$43*Revenue!P4*(1+'2-Financial Inputs'!$C$11)^13 -> 1650137.6 | Q10: ='2-Financial Inputs'!$C$73*CAPEX!$C$43*Revenue!Q4*(1+'2-Financial Inputs'!$C$11)^14 -> 1683140.3
B11: Core OPEX subtotal | C11: =SUM(C5:C10) -> 4279857.5 | D11: =SUM(D5:D10) -> 5231206.3 | E11: =SUM(E5:E10) -> 6218897 | F11: =SUM(F5:F10) -> 6343275 | G11: =SUM(G5:G10) -> 6470140.5 | H11: =SUM(H5:H10) -> 6599543.3 | I11: =SUM(I5:I10) -> 6731534.1 | J11: =SUM(J5:J10) -> 6866164.8 | ... Q11: =SUM(Q5:Q10) -> 7887065.1
B13: PRE-SORTING OPEX
B14: Pre-sorting staff | C14: =IF('3-Operations'!$C$6=1,'2-Financial Inputs'!$C$70*'2-Financial Inputs'!$C$69*Revenue!C4*(1+'2-Financial Inputs'!$C$11)^0,0) -> 156800 | D14: =IF('3-Operations'!$C$6=1,'2-Financial Inputs'!$C$70*'2-Financial Inputs'!$C$69*Revenue!D4*(1+'2-Financial Inputs'!$C$11)^1,0) -> 194208 | E14: =IF('3-Operations'!$C$6=1,'2-Financial Inputs'!$C$70*'2-Financial Inputs'!$C$69*Revenue!E4*(1+'2-Financial Inputs'!$C$11)^2,0) -> 233049.6 | F14: =IF('3-Operations'!$C$6=1,'2-Financial Inputs'!$C$70*'2-Financial Inputs'!$C$69*Revenue!F4*(1+'2-Financial Inputs'!$C$11)^3,0) -> 237710.59 | G14: =IF('3-Operations'!$C$6=1,'2-Financial Inputs'!$C$70*'2-Financial Inputs'!$C$69*Revenue!G4*(1+'2-Financial Inputs'!$C$11)^4,0) -> 242464.8 | H14: =IF('3-Operations'!$C$6=1,'2-Financial Inputs'!$C$70*'2-Financial Inputs'!$C$69*Revenue!H4*(1+'2-Financial Inputs'!$C$11)^5,0) -> 247314.1 | I14: =IF('3-Operations'!$C$6=1,'2-Financial Inputs'!$C$70*'2-Financial Inputs'!$C$69*Revenue!I4*(1+'2-Financial Inputs'!$C$11)^6,0) -> 252260.38 | J14: =IF('3-Operations'!$C$6=1,'2-Financial Inputs'!$C$70*'2-Financial Inputs'!$C$69*Revenue!J4*(1+'2-Financial Inputs'!$C$11)^7,0) -> 257305.59 | K14: =IF('3-Operations'!$C$6=1,'2-Financial Inputs'!$C$70*'2-Financial Inputs'!$C$69*Revenue!K4*(1+'2-Financial Inputs'!$C$11)^8,0) -> 262451.7 | L14: =IF('3-Operations'!$C$6=1,'2-Financial Inputs'!$C$70*'2-Financial Inputs'!$C$69*Revenue!L4*(1+'2-Financial Inputs'!$C$11)^9,0) -> 267700.74 | M14: =IF('3-Operations'!$C$6=1,'2-Financial Inputs'!$C$70*'2-Financial Inputs'!$C$69*Revenue!M4*(1+'2-Financial Inputs'!$C$11)^10,0) -> 273054.75 | N14: =IF('3-Operations'!$C$6=1,'2-Financial Inputs'!$C$70*'2-Financial Inputs'!$C$69*Revenue!N4*(1+'2-Financial Inputs'!$C$11)^11,0) -> 278515.85 | O14: =IF('3-Operations'!$C$6=1,'2-Financial Inputs'!$C$70*'2-Financial Inputs'!$C$69*Revenue!O4*(1+'2-Financial Inputs'!$C$11)^12,0) -> 284086.16 | P14: =IF('3-Operations'!$C$6=1,'2-Financial Inputs'!$C$70*'2-Financial Inputs'!$C$69*Revenue!P4*(1+'2-Financial Inputs'!$C$11)^13,0) -> 289767.89 | Q14: =IF('3-Operations'!$C$6=1,'2-Financial Inputs'!$C$70*'2-Financial Inputs'!$C$69*Revenue!Q4*(1+'2-Financial Inputs'!$C$11)^14,0) -> 295563.24
B15: Pre-sorting maintenance & electricity | C15: =IF('3-Operations'!$C$6=1,'2-Financial Inputs'!$C$72*CAPEX!$C$21*Revenue!C4*(1+'2-Financial Inputs'!$C$11)^0,0) -> 30240 | D15: =IF('3-Operations'!$C$6=1,'2-Financial Inputs'!$C$72*CAPEX!$C$21*Revenue!D4*(1+'2-Financial Inputs'!$C$11)^1,0) -> 37454.4 | E15: =IF('3-Operations'!$C$6=1,'2-Financial Inputs'!$C$72*CAPEX!$C$21*Revenue!E4*(1+'2-Financial Inputs'!$C$11)^2,0) -> 44945.28 | F15: =IF('3-Operations'!$C$6=1,'2-Financial Inputs'!$C$72*CAPEX!$C$21*Revenue!F4*(1+'2-Financial Inputs'!$C$11)^3,0) -> 45844.186 | G15: =IF('3-Operations'!$C$6=1,'2-Financial Inputs'!$C$72*CAPEX!$C$21*Revenue!G4*(1+'2-Financial Inputs'!$C$11)^4,0) -> 46761.069 | H15: =IF('3-Operations'!$C$6=1,'2-Financial Inputs'!$C$72*CAPEX!$C$21*Revenue!H4*(1+'2-Financial Inputs'!$C$11)^5,0) -> 47696.291 | I15: =IF('3-Operations'!$C$6=1,'2-Financial Inputs'!$C$72*CAPEX!$C$21*Revenue!I4*(1+'2-Financial Inputs'!$C$11)^6,0) -> 48650.217 | J15: =IF('3-Operations'!$C$6=1,'2-Financial Inputs'!$C$72*CAPEX!$C$21*Revenue!J4*(1+'2-Financial Inputs'!$C$11)^7,0) -> 49623.221 | K15: =IF('3-Operations'!$C$6=1,'2-Financial Inputs'!$C$72*CAPEX!$C$21*Revenue!K4*(1+'2-Financial Inputs'!$C$11)^8,0) -> 50615.685 | L15: =IF('3-Operations'!$C$6=1,'2-Financial Inputs'!$C$72*CAPEX!$C$21*Revenue!L4*(1+'2-Financial Inputs'!$C$11)^9,0) -> 51627.999 | M15: =IF('3-Operations'!$C$6=1,'2-Financial Inputs'!$C$72*CAPEX!$C$21*Revenue!M4*(1+'2-Financial Inputs'!$C$11)^10,0) -> 52660.559 | N15: =IF('3-Operations'!$C$6=1,'2-Financial Inputs'!$C$72*CAPEX!$C$21*Revenue!N4*(1+'2-Financial Inputs'!$C$11)^11,0) -> 53713.77 | O15: =IF('3-Operations'!$C$6=1,'2-Financial Inputs'!$C$72*CAPEX!$C$21*Revenue!O4*(1+'2-Financial Inputs'!$C$11)^12,0) -> 54788.046 | P15: =IF('3-Operations'!$C$6=1,'2-Financial Inputs'!$C$72*CAPEX!$C$21*Revenue!P4*(1+'2-Financial Inputs'!$C$11)^13,0) -> 55883.806 | Q15: =IF('3-Operations'!$C$6=1,'2-Financial Inputs'!$C$72*CAPEX!$C$21*Revenue!Q4*(1+'2-Financial Inputs'!$C$11)^14,0) -> 57001.483
B16: Pre-sorting OPEX subtotal | C16: =SUM(C14:C15) -> 187040 | D16: =SUM(D14:D15) -> 231662.4 | E16: =SUM(E14:E15) -> 277994.88 | F16: =SUM(F14:F15) -> 283554.78 | G16: =SUM(G14:G15) -> 289225.87 | H16: =SUM(H14:H15) -> 295010.39 | I16: =SUM(I14:I15) -> 300910.6 | J16: =SUM(J14:J15) -> 306928.81 | ... Q16: =SUM(Q14:Q15) -> 352564.73
B18: POST-SORTING OPEX
B19: Post-sorting staff | C19: =IF('3-Operations'!$C$7=1,'2-Financial Inputs'!$C$71*'2-Financial Inputs'!$C$69*Revenue!C4*(1+'2-Financial Inputs'!$C$11)^0,0) -> 117600 | D19: =IF('3-Operations'!$C$7=1,'2-Financial Inputs'!$C$71*'2-Financial Inputs'!$C$69*Revenue!D4*(1+'2-Financial Inputs'!$C$11)^1,0) -> 145656 | E19: =IF('3-Operations'!$C$7=1,'2-Financial Inputs'!$C$71*'2-Financial Inputs'!$C$69*Revenue!E4*(1+'2-Financial Inputs'!$C$11)^2,0) -> 174787.2 | F19: =IF('3-Operations'!$C$7=1,'2-Financial Inputs'!$C$71*'2-Financial Inputs'!$C$69*Revenue!F4*(1+'2-Financial Inputs'!$C$11)^3,0) -> 178282.94 | G19: =IF('3-Operations'!$C$7=1,'2-Financial Inputs'!$C$71*'2-Financial Inputs'!$C$69*Revenue!G4*(1+'2-Financial Inputs'!$C$11)^4,0) -> 181848.6 | H19: =IF('3-Operations'!$C$7=1,'2-Financial Inputs'!$C$71*'2-Financial Inputs'!$C$69*Revenue!H4*(1+'2-Financial Inputs'!$C$11)^5,0) -> 185485.57 | I19: =IF('3-Operations'!$C$7=1,'2-Financial Inputs'!$C$71*'2-Financial Inputs'!$C$69*Revenue!I4*(1+'2-Financial Inputs'!$C$11)^6,0) -> 189195.29 | J19: =IF('3-Operations'!$C$7=1,'2-Financial Inputs'!$C$71*'2-Financial Inputs'!$C$69*Revenue!J4*(1+'2-Financial Inputs'!$C$11)^7,0) -> 192979.19 | K19: =IF('3-Operations'!$C$7=1,'2-Financial Inputs'!$C$71*'2-Financial Inputs'!$C$69*Revenue!K4*(1+'2-Financial Inputs'!$C$11)^8,0) -> 196838.78 | L19: =IF('3-Operations'!$C$7=1,'2-Financial Inputs'!$C$71*'2-Financial Inputs'!$C$69*Revenue!L4*(1+'2-Financial Inputs'!$C$11)^9,0) -> 200775.55 | M19: =IF('3-Operations'!$C$7=1,'2-Financial Inputs'!$C$71*'2-Financial Inputs'!$C$69*Revenue!M4*(1+'2-Financial Inputs'!$C$11)^10,0) -> 204791.06 | N19: =IF('3-Operations'!$C$7=1,'2-Financial Inputs'!$C$71*'2-Financial Inputs'!$C$69*Revenue!N4*(1+'2-Financial Inputs'!$C$11)^11,0) -> 208886.88 | O19: =IF('3-Operations'!$C$7=1,'2-Financial Inputs'!$C$71*'2-Financial Inputs'!$C$69*Revenue!O4*(1+'2-Financial Inputs'!$C$11)^12,0) -> 213064.62 | P19: =IF('3-Operations'!$C$7=1,'2-Financial Inputs'!$C$71*'2-Financial Inputs'!$C$69*Revenue!P4*(1+'2-Financial Inputs'!$C$11)^13,0) -> 217325.91 | Q19: =IF('3-Operations'!$C$7=1,'2-Financial Inputs'!$C$71*'2-Financial Inputs'!$C$69*Revenue!Q4*(1+'2-Financial Inputs'!$C$11)^14,0) -> 221672.43
B20: Post-sorting maintenance & electricity | C20: =IF('3-Operations'!$C$7=1,'2-Financial Inputs'!$C$72*CAPEX!$C$29*Revenue!C4*(1+'2-Financial Inputs'!$C$11)^0,0) -> 12040 | D20: =IF('3-Operations'!$C$7=1,'2-Financial Inputs'!$C$72*CAPEX!$C$29*Revenue!D4*(1+'2-Financial Inputs'!$C$11)^1,0) -> 14912.4 | E20: =IF('3-Operations'!$C$7=1,'2-Financial Inputs'!$C$72*CAPEX!$C$29*Revenue!E4*(1+'2-Financial Inputs'!$C$11)^2,0) -> 17894.88 | F20: =IF('3-Operations'!$C$7=1,'2-Financial Inputs'!$C$72*CAPEX!$C$29*Revenue!F4*(1+'2-Financial Inputs'!$C$11)^3,0) -> 18252.778 | G20: =IF('3-Operations'!$C$7=1,'2-Financial Inputs'!$C$72*CAPEX!$C$29*Revenue!G4*(1+'2-Financial Inputs'!$C$11)^4,0) -> 18617.833 | H20: =IF('3-Operations'!$C$7=1,'2-Financial Inputs'!$C$72*CAPEX!$C$29*Revenue!H4*(1+'2-Financial Inputs'!$C$11)^5,0) -> 18990.19 | I20: =IF('3-Operations'!$C$7=1,'2-Financial Inputs'!$C$72*CAPEX!$C$29*Revenue!I4*(1+'2-Financial Inputs'!$C$11)^6,0) -> 19369.994 | J20: =IF('3-Operations'!$C$7=1,'2-Financial Inputs'!$C$72*CAPEX!$C$29*Revenue!J4*(1+'2-Financial Inputs'!$C$11)^7,0) -> 19757.393 | K20: =IF('3-Operations'!$C$7=1,'2-Financial Inputs'!$C$72*CAPEX!$C$29*Revenue!K4*(1+'2-Financial Inputs'!$C$11)^8,0) -> 20152.541 | L20: =IF('3-Operations'!$C$7=1,'2-Financial Inputs'!$C$72*CAPEX!$C$29*Revenue!L4*(1+'2-Financial Inputs'!$C$11)^9,0) -> 20555.592 | M20: =IF('3-Operations'!$C$7=1,'2-Financial Inputs'!$C$72*CAPEX!$C$29*Revenue!M4*(1+'2-Financial Inputs'!$C$11)^10,0) -> 20966.704 | N20: =IF('3-Operations'!$C$7=1,'2-Financial Inputs'!$C$72*CAPEX!$C$29*Revenue!N4*(1+'2-Financial Inputs'!$C$11)^11,0) -> 21386.038 | O20: =IF('3-Operations'!$C$7=1,'2-Financial Inputs'!$C$72*CAPEX!$C$29*Revenue!O4*(1+'2-Financial Inputs'!$C$11)^12,0) -> 21813.759 | P20: =IF('3-Operations'!$C$7=1,'2-Financial Inputs'!$C$72*CAPEX!$C$29*Revenue!P4*(1+'2-Financial Inputs'!$C$11)^13,0) -> 22250.034 | Q20: =IF('3-Operations'!$C$7=1,'2-Financial Inputs'!$C$72*CAPEX!$C$29*Revenue!Q4*(1+'2-Financial Inputs'!$C$11)^14,0) -> 22695.035
B21: Post-sorting OPEX subtotal | C21: =SUM(C19:C20) -> 129640 | D21: =SUM(D19:D20) -> 160568.4 | E21: =SUM(E19:E20) -> 192682.08 | F21: =SUM(F19:F20) -> 196535.72 | G21: =SUM(G19:G20) -> 200466.44 | H21: =SUM(H19:H20) -> 204475.76 | I21: =SUM(I19:I20) -> 208565.28 | J21: =SUM(J19:J20) -> 212736.59 | ... Q21: =SUM(Q19:Q20) -> 244367.47
B22: Ash & non-sellable disposal | C22: ='4-Production Calcs'!$C$98*Revenue!C4*'2-Financial Inputs'!$C$56*(1+'2-Financial Inputs'!$C$11)^0 -> 390022.4 | D22: ='4-Production Calcs'!$C$98*Revenue!D4*'2-Financial Inputs'!$C$56*(1+'2-Financial Inputs'!$C$11)^1 -> 483070.6 | E22: ='4-Production Calcs'!$C$98*Revenue!E4*'2-Financial Inputs'!$C$56*(1+'2-Financial Inputs'!$C$11)^2 -> 579684.72 | F22: ='4-Production Calcs'!$C$98*Revenue!F4*'2-Financial Inputs'!$C$56*(1+'2-Financial Inputs'!$C$11)^3 -> 591278.41 | G22: ='4-Production Calcs'!$C$98*Revenue!G4*'2-Financial Inputs'!$C$56*(1+'2-Financial Inputs'!$C$11)^4 -> 603103.98 | H22: ='4-Production Calcs'!$C$98*Revenue!H4*'2-Financial Inputs'!$C$56*(1+'2-Financial Inputs'!$C$11)^5 -> 615166.06 | I22: ='4-Production Calcs'!$C$98*Revenue!I4*'2-Financial Inputs'!$C$56*(1+'2-Financial Inputs'!$C$11)^6 -> 627469.38 | J22: ='4-Production Calcs'!$C$98*Revenue!J4*'2-Financial Inputs'!$C$56*(1+'2-Financial Inputs'!$C$11)^7 -> 640018.77 | K22: ='4-Production Calcs'!$C$98*Revenue!K4*'2-Financial Inputs'!$C$56*(1+'2-Financial Inputs'!$C$11)^8 -> 652819.14 | L22: ='4-Production Calcs'!$C$98*Revenue!L4*'2-Financial Inputs'!$C$56*(1+'2-Financial Inputs'!$C$11)^9 -> 665875.53 | M22: ='4-Production Calcs'!$C$98*Revenue!M4*'2-Financial Inputs'!$C$56*(1+'2-Financial Inputs'!$C$11)^10 -> 679193.04 | N22: ='4-Production Calcs'!$C$98*Revenue!N4*'2-Financial Inputs'!$C$56*(1+'2-Financial Inputs'!$C$11)^11 -> 692776.9 | O22: ='4-Production Calcs'!$C$98*Revenue!O4*'2-Financial Inputs'!$C$56*(1+'2-Financial Inputs'!$C$11)^12 -> 706632.44 | P22: ='4-Production Calcs'!$C$98*Revenue!P4*'2-Financial Inputs'!$C$56*(1+'2-Financial Inputs'!$C$11)^13 -> 720765.08 | Q22: ='4-Production Calcs'!$C$98*Revenue!Q4*'2-Financial Inputs'!$C$56*(1+'2-Financial Inputs'!$C$11)^14 -> 735180.39
B23: TOTAL OPEX | C23: =C11+C16+C21+C22 -> 4986559.9 | D23: =D11+D16+D21+D22 -> 6106507.7 | E23: =E11+E16+E21+E22 -> 7269258.7 | F23: =F11+F16+F21+F22 -> 7414643.9 | G23: =G11+G16+G21+G22 -> 7562936.7 | H23: =H11+H16+H21+H22 -> 7714195.5 | I23: =I11+I16+I21+I22 -> 7868479.4 | J23: =J11+J16+J21+J22 -> 8025849 | ... Q23: =Q11+Q16+Q21+Q22 -> 9219177.7

Sheet Amortization
A1: Loan Amortization Schedule — Annual Summary (V2)
A2: Monthly PMT annualised.
A3: Loan amount: | B3: =CAPEX!C46 -> 44646350 | C3: Annual payment: | D3: =PMT('2-Financial Inputs'!C7,'2-Financial Inputs'!C8,-CAPEX!C46) -> 7901696.9
A5: Year | B5: Opening Balance | C5: Annual Payment | D5: Interest | E5: Principal | F5: Closing Balance
A6: 1 | B6: =CAPEX!C46 -> 44646350 | C6: =$D$3 -> 7901696.9 | D6: =B6*'2-Financial Inputs'!$C$7 -> 5357562 | E6: =C6-D6 -> 2544134.9 | F6: =B6-E6 -> 42102215
A7: 2 | B7: =F6 -> 42102215 | C7: =$D$3 -> 7901696.9 | D7: =B7*'2-Financial Inputs'!$C$7 -> 5052265.8 | E7: =C7-D7 -> 2849431.1 | F7: =B7-E7 -> 39252784
A8: 3 | B8: =F7 -> 39252784 | C8: =$D$3 -> 7901696.9 | D8: =B8*'2-Financial Inputs'!$C$7 -> 4710334.1 | E8: =C8-D8 -> 3191362.9 | F8: =B8-E8 -> 36061421
A9: 4 | B9: =F8 -> 36061421 | C9: =$D$3 -> 7901696.9 | D9: =B9*'2-Financial Inputs'!$C$7 -> 4327370.5 | E9: =C9-D9 -> 3574326.4 | F9: =B9-E9 -> 32487095
A10: 5 | B10: =F9 -> 32487095 | C10: =$D$3 -> 7901696.9 | D10: =B10*'2-Financial Inputs'!$C$7 -> 3898451.4 | E10: =C10-D10 -> 4003245.6 | F10: =B10-E10 -> 28483849
A11: 6 | B11: =F10 -> 28483849 | C11: =$D$3 -> 7901696.9 | D11: =B11*'2-Financial Inputs'!$C$7 -> 3418061.9 | E11: =C11-D11 -> 4483635 | F11: =B11-E11 -> 24000214
A12: 7 | B12: =F11 -> 24000214 | C12: =$D$3 -> 7901696.9 | D12: =B12*'2-Financial Inputs'!$C$7 -> 2880025.7 | E12: =C12-D12 -> 5021671.3 | F12: =B12-E12 -> 18978543
A13: 8 | B13: =F12 -> 18978543 | C13: =$D$3 -> 7901696.9 | D13: =B13*'2-Financial Inputs'!$C$7 -> 2277425.1 | E13: =C13-D13 -> 5624271.8 | F13: =B13-E13 -> 13354271
A14: 9 | B14: =F13 -> 13354271 | C14: =$D$3 -> 7901696.9 | D14: =B14*'2-Financial Inputs'!$C$7 -> 1602512.5 | E14: =C14-D14 -> 6299184.4 | F14: =B14-E14 -> 7055086.6
A15: 10 | B15: =F14 -> 7055086.6 | C15: =$D$3 -> 7901696.9 | D15: =B15*'2-Financial Inputs'!$C$7 -> 846610.39 | E15: =C15-D15 -> 7055086.6 | F15: =B15-E15 -> 2.514571e-08
A16: Total | C16: =SUM(C6:C15) -> 79016969 | D16: =SUM(D6:D15) -> 34370619 | E16: =SUM(E6:E15) -> 44646350

Sheet P&L Consolidated
A1: Consolidated Profit & Loss — 15-Year Projection (V2)
C3: Year 1 | D3: Year 2 | E3: Year 3 | F3: Year 4 | G3: Year 5 | H3: Year 6 | I3: Year 7 | J3: Year 8 | K3: Year 9 | L3: Year 10 | M3: Year 11 | N3: Year 12 | O3: Year 13 | P3: Year 14 | Q3: Year 15
B4: Total Revenue | C4: =Revenue!C33 -> 10850753 | D4: =Revenue!D33 -> 13439433 | E4: =Revenue!E33 -> 16127319 | F4: =Revenue!F33 -> 16449866 | G4: =Revenue!G33 -> 16778863 | H4: =Revenue!H33 -> 17114440 | I4: =Revenue!I33 -> 17456729 | J4: =Revenue!J33 -> 17805864 | ... Q4: =Revenue!Q33 -> 20453340
B5: Total OPEX | C5: =-OPEX!C23 -> -4986559.9 | D5: =-OPEX!D23 -> -6106507.7 | E5: =-OPEX!E23 -> -7269258.7 | F5: =-OPEX!F23 -> -7414643.9 | G5: =-OPEX!G23 -> -7562936.7 | H5: =-OPEX!H23 -> -7714195.5 | I5: =-OPEX!I23 -> -7868479.4 | J5: =-OPEX!J23 -> -8025849 | ... Q5: =-OPEX!Q23 -> -9219177.7
B6: EBITDA | C6: =C4+C5 -> 5864193.2 | D6: =D4+D5 -> 7332925.1 | E6: =E4+E5 -> 8858060.6 | F6: =F4+F5 -> 9035221.9 | G6: =G4+G5 -> 9215926.3 | H6: =H4+H5 -> 9400244.8 | I6: =I4+I5 -> 9588249.7 | J6: =J4+J5 -> 9780014.7 | ... Q6: =Q4+Q5 -> 11234163
B7: EBITDA margin | C7: =IF(C4=0,0,C6/C4) -> 0.54044112 | D7: =IF(D4=0,0,D6/D4) -> 0.54562758 | E7: =IF(E4=0,0,E6/E4) -> 0.54925809 | F7: =IF(F4=0,0,F6/F4) -> 0.54925809 | G7: =IF(G4=0,0,G6/G4) -> 0.54925809 | H7: =IF(H4=0,0,H6/H4) -> 0.54925809 | I7: =IF(I4=0,0,I6/I4) -> 0.54925809 | J7: =IF(J4=0,0,J6/J4) -> 0.54925809 | ... Q7: =IF(Q4=0,0,Q6/Q4) -> 0.54925809
B8: Depreciation | C8: =-CAPEX!$C$48 -> -4252033.3 | D8: =-CAPEX!$C$48 -> -4252033.3 | E8: =-CAPEX!$C$48 -> -4252033.3 | F8: =-CAPEX!$C$48 -> -4252033.3 | G8: =-CAPEX!$C$48 -> -4252033.3 | H8: =-CAPEX!$C$48 -> -4252033.3 | I8: =-CAPEX!$C$48 -> -4252033.3 | J8: =-CAPEX!$C$48 -> -4252033.3 | ... Q8: =-CAPEX!$C$48 -> -4252033.3
B9: EBIT | C9: =C6+C8 -> 1612159.9 | D9: =D6+D8 -> 3080891.8 | E9: =E6+E8 -> 4606027.3 | F9: =F6+F8 -> 4783188.5 | G9: =G6+G8 -> 4963893 | H9: =H6+H8 -> 5148211.5 | I9: =I6+I8 -> 5336216.4 | J9: =J6+J8 -> 5527981.4 | ... Q9: =Q6+Q8 -> 6982129.4
B10: Interest expense | C10: =-Amortization!D6 -> -5357562 | D10: =-Amortization!D7 -> -5052265.8 | E10: =-Amortization!D8 -> -4710334.1 | F10: =-Amortization!D9 -> -4327370.5 | G10: =-Amortization!D10 -> -3898451.4 | H10: =-Amortization!D11 -> -3418061.9 | I10: =-Amortization!D12 -> -2880025.7 | J10: =-Amortization!D13 -> -2277425.1 | K10: =-Amortization!D14 -> -1602512.5 | L10: =-Amortization!D15 -> -846610.39 | M10: 0 | N10: 0 | O10: 0 | P10: 0 | Q10: 0
B11: EBT | C11: =C9+C10 -> -3745402.1 | D11: =D9+D10 -> -1971374 | E11: =E9+E10 -> -104306.76 | F11: =F9+F10 -> 455817.99 | G11: =G9+G10 -> 1065441.6 | H11: =H9+H10 -> 1730149.6 | I11: =I9+I10 -> 2456190.7 | J11: =J9+J10 -> 3250556.2 | ... Q11: =Q9+Q10 -> 6982129.4
B12: Corporate tax | C12: =IF(C11>0,-C11*'2-Financial Inputs'!$C$9,0) -> 0 | D12: =IF(D11>0,-D11*'2-Financial Inputs'!$C$9,0) -> 0 | E12: =IF(E11>0,-E11*'2-Financial Inputs'!$C$9,0) -> 0 | F12: =IF(F11>0,-F11*'2-Financial Inputs'!$C$9,0) -> -113954.5 | G12: =IF(G11>0,-G11*'2-Financial Inputs'!$C$9,0) -> -266360.4 | H12: =IF(H11>0,-H11*'2-Financial Inputs'!$C$9,0) -> -432537.4 | I12: =IF(I11>0,-I11*'2-Financial Inputs'!$C$9,0) -> -614047.67 | J12: =IF(J11>0,-J11*'2-Financial Inputs'!$C$9,0) -> -812639.06 | ... Q12: =IF(Q11>0,-Q11*'2-Financial Inputs'!$C$9,0) -> -1745532.3
B13: NET INCOME | C13: =C11+C12 -> -3745402.1 | D13: =D11+D12 -> -1971374 | E13: =E11+E12 -> -104306.76 | F13: =F11+F12 -> 341863.49 | G13: =G11+G12 -> 799081.2 | H13: =H11+H12 -> 1297612.2 | I13: =I11+I12 -> 1842143 | J13: =J11+J12 -> 2437917.2 | ... Q13: =Q11+Q12 -> 5236597

Sheet P&L Pre-Sorting
A1: Pre-Sorting Segment P&L — 15-Year (V2)
C3: Year 1 | D3: Year 2 | E3: Year 3 | F3: Year 4 | G3: Year 5 | H3: Year 6 | I3: Year 7 | J3: Year 8 | K3: Year 9 | L3: Year 10 | M3: Year 11 | N3: Year 12 | O3: Year 13 | P3: Year 14 | Q3: Year 15
B4: Pre-sorted metals revenue | C4: =IF('3-Operations'!$C$6=1,('4-Production Calcs'!C23*'1-Waste Input'!$C$10/1000*'2-Financial Inputs'!$C$49+'4-Production Calcs'!C24*'1-Waste Input'!$C$10/1000*'2-Financial Inputs'!$C$50)*Revenue!C4*(1+'2-Financial Inputs'!$C$11)^0,0) -> 534822.75 | D4: =IF('3-Operations'!$C$6=1,('4-Production Calcs'!C23*'1-Waste Input'!$C$10/1000*'2-Financial Inputs'!$C$49+'4-Production Calcs'!C24*'1-Waste Input'!$C$10/1000*'2-Financial Inputs'!$C$50)*Revenue!D4*(1+'2-Financial Inputs'!$C$11)^1,0) -> 662416.18 | E4: =IF('3-Operations'!$C$6=1,('4-Production Calcs'!C23*'1-Waste Input'!$C$10/1000*'2-Financial Inputs'!$C$49+'4-Production Calcs'!C24*'1-Waste Input'!$C$10/1000*'2-Financial Inputs'!$C$50)*Revenue!E4*(1+'2-Financial Inputs'!$C$11)^2,0) -> 794899.41 | F4: =IF('3-Operations'!$C$6=1,('4-Production Calcs'!C23*'1-Waste Input'!$C$10/1000*'2-Financial Inputs'!$C$49+'4-Production Calcs'!C24*'1-Waste Input'!$C$10/1000*'2-Financial Inputs'!$C$50)*Revenue!F4*(1+'2-Financial Inputs'!$C$11)^3,0) -> 810797.4 | G4: =IF('3-Operations'!$C$6=1,('4-Production Calcs'!C23*'1-Waste Input'!$C$10/1000*'2-Financial Inputs'!$C$49+'4-Production Calcs'!C24*'1-Waste Input'!$C$10/1000*'2-Financial Inputs'!$C$50)*Revenue!G4*(1+'2-Financial Inputs'!$C$11)^4,0) -> 827013.35 | H4: =IF('3-Operations'!$C$6=1,('4-Production Calcs'!C23*'1-Waste Input'!$C$10/1000*'2-Financial Inputs'!$C$49+'4-Production Calcs'!C24*'1-Waste Input'!$C$10/1000*'2-Financial Inputs'!$C$50)*Revenue!H4*(1+'2-Financial Inputs'!$C$11)^5,0) -> 843553.62 | I4: =IF('3-Operations'!$C$6=1,('4-Production Calcs'!C23*'1-Waste Input'!$C$10/1000*'2-Financial Inputs'!$C$49+'4-Production Calcs'!C24*'1-Waste Input'!$C$10/1000*'2-Financial Inputs'!$C$50)*Revenue!I4*(1+'2-Financial Inputs'!$C$11)^6,0) -> 860424.69 | J4: =IF('3-Operations'!$C$6=1,('4-Production Calcs'!C23*'1-Waste Input'!$C$10/1000*'2-Financial Inputs'!$C$49+'4-Production Calcs'!C24*'1-Waste Input'!$C$10/1000*'2-Financial Inputs'!$C$50)*Revenue!J4*(1+'2-Financial Inputs'!$C$11)^7,0) -> 877633.18 | K4: =IF('3-Operations'!$C$6=1,('4-Production Calcs'!C23*'1-Waste Input'!$C$10/1000*'2-Financial Inputs'!$C$49+'4-Production Calcs'!C24*'1-Waste Input'!$C$10/1000*'2-Financial Inputs'!$C$50)*Revenue!K4*(1+'2-Financial Inputs'!$C$11)^8,0) -> 895185.85 | L4: =IF('3-Operations'!$C$6=1,('4-Production Calcs'!C23*'1-Waste Input'!$C$10/1000*'2-Financial Inputs'!$C$49+'4-Production Calcs'!C24*'1-Waste Input'!$C$10/1000*'2-Financial Inputs'!$C$50)*Revenue!L4*(1+'2-Financial Inputs'!$C$11)^9,0) -> 913089.56 | M4: =IF('3-Operations'!$C$6=1,('4-Production Calcs'!C23*'1-Waste Input'!$C$10/1000*'2-Financial Inputs'!$C$49+'4-Production Calcs'!C24*'1-Waste Input'!$C$10/1000*'2-Financial Inputs'!$C$50)*Revenue!M4*(1+'2-Financial Inputs'!$C$11)^10,0) -> 931351.35 | N4: =IF('3-Operations'!$C$6=1,('4-Production Calcs'!C23*'1-Waste Input'!$C$10/1000*'2-Financial Inputs'!$C$49+'4-Production Calcs'!C24*'1-Waste Input'!$C$10/1000*'2-Financial Inputs'!$C$50)*Revenue!N4*(1+'2-Financial Inputs'!$C$11)^11,0) -> 949978.38 | O4: =IF('3-Operations'!$C$6=1,('4-Production Calcs'!C23*'1-Waste Input'!$C$10/1000*'2-Financial Inputs'!$C$49+'4-Production Calcs'!C24*'1-Waste Input'!$C$10/1000*'2-Financial Inputs'!$C$50)*Revenue!O4*(1+'2-Financial Inputs'!$C$11)^12,0) -> 968977.95 | P4: =IF('3-Operations'!$C$6=1,('4-Production Calcs'!C23*'1-Waste Input'!$C$10/1000*'2-Financial Inputs'!$C$49+'4-Production Calcs'!C24*'1-Waste Input'!$C$10/1000*'2-Financial Inputs'!$C$50)*Revenue!P4*(1+'2-Financial Inputs'!$C$11)^13,0) -> 988357.51 | Q4: =IF('3-Operations'!$C$6=1,('4-Production Calcs'!C23*'1-Waste Input'!$C$10/1000*'2-Financial Inputs'!$C$49+'4-Production Calcs'!C24*'1-Waste Input'!$C$10/1000*'2-Financial Inputs'!$C$50)*Revenue!Q4*(1+'2-Financial Inputs'!$C$11)^14,0) -> 1008124.7
B5: Pre-sorted glass revenue | C5: =Revenue!C24 -> 36605.646 | D5: =Revenue!D24 -> 45338.707 | E5: =Revenue!E24 -> 54406.449 | F5: =Revenue!F24 -> 55494.578 | G5: =Revenue!G24 -> 56604.469 | H5: =Revenue!H24 -> 57736.559 | I5: =Revenue!I24 -> 58891.29 | J5: =Revenue!J24 -> 60069.116 | ... Q5: =Revenue!Q24 -> 69000.532
B6: Total pre-sorting revenue | C6: =C4+C5 -> 571428.4 | D6: =D4+D5 -> 707754.88 | E6: =E4+E5 -> 849305.86 | F6: =F4+F5 -> 866291.98 | G6: =G4+G5 -> 883617.82 | H6: =H4+H5 -> 901290.17 | I6: =I4+I5 -> 919315.98 | J6: =J4+J5 -> 937702.3 | ... Q6: =Q4+Q5 -> 1077125.2
B7: Pre-sorting OPEX | C7: =-OPEX!C16 -> -187040 | D7: =-OPEX!D16 -> -231662.4 | E7: =-OPEX!E16 -> -277994.88 | F7: =-OPEX!F16 -> -283554.78 | G7: =-OPEX!G16 -> -289225.87 | H7: =-OPEX!H16 -> -295010.39 | I7: =-OPEX!I16 -> -300910.6 | J7: =-OPEX!J16 -> -306928.81 | ... Q7: =-OPEX!Q16 -> -352564.73
B8: Pre-sorting EBITDA | C8: =C6+C7 -> 384388.4 | D8: =D6+D7 -> 476092.48 | E8: =E6+E7 -> 571310.98 | F8: =F6+F7 -> 582737.2 | G8: =G6+G7 -> 594391.95 | H8: =H6+H7 -> 606279.78 | I8: =I6+I7 -> 618405.38 | J8: =J6+J7 -> 630773.49 | ... Q8: =Q6+Q7 -> 724560.46
B9: Pre-sorting CAPEX | C9: =CAPEX!C21 -> 1080000
B10: Simple payback (years) | C10: =IF(E8>0,C9/E8,0) -> 1.890389

Sheet P&L Core Processing
A1: Core Processing Segment P&L — 15-Year (V2)
C3: Year 1 | D3: Year 2 | E3: Year 3 | F3: Year 4 | G3: Year 5 | H3: Year 6 | I3: Year 7 | J3: Year 8 | K3: Year 9 | L3: Year 10 | M3: Year 11 | N3: Year 12 | O3: Year 13 | P3: Year 14 | Q3: Year 15
B4: Gate fee revenue | C4: =Revenue!C8 -> 3557400 | D4: =Revenue!D8 -> 4406094 | E4: =Revenue!E8 -> 5287312.8 | F4: =Revenue!F8 -> 5393059.1 | G4: =Revenue!G8 -> 5500920.2 | H4: =Revenue!H8 -> 5610938.6 | I4: =Revenue!I8 -> 5723157.4 | J4: =Revenue!J8 -> 5837620.6 | ... Q4: =Revenue!Q8 -> 6705591.1
B5: Oil revenue | C5: =Revenue!C12 -> 4224473.6 | D5: =Revenue!D12 -> 5232312.3 | E5: =Revenue!E12 -> 6278774.8 | F5: =Revenue!F12 -> 6404350.3 | G5: =Revenue!G12 -> 6532437.3 | H5: =Revenue!H12 -> 6663086 | I5: =Revenue!I12 -> 6796347.8 | J5: =Revenue!J12 -> 6932274.7 | ... Q5: =Revenue!Q12 -> 7963004.6
B6: Char revenue | C6: =Revenue!C16 -> 957083.14 | D6: =Revenue!D16 -> 1185415.8 | E6: =Revenue!E16 -> 1422499 | F6: =Revenue!F16 -> 1450949 | G6: =Revenue!G16 -> 1479968 | H6: =Revenue!H16 -> 1509567.3 | I6: =Revenue!I16 -> 1539758.7 | J6: =Revenue!J16 -> 1570553.8 | ... Q6: =Revenue!Q16 -> 1804072.7
B7: Carbon credit revenue | C7: =Revenue!C28 -> 1681680 | D7: =Revenue!D28 -> 2082880.8 | E7: =Revenue!E28 -> 2499457 | F7: =Revenue!F28 -> 2549446.1 | G7: =Revenue!G28 -> 2600435 | H7: =Revenue!H28 -> 2652443.7 | I7: =Revenue!I28 -> 2705492.6 | J7: =Revenue!J28 -> 2759602.4 | ... Q7: =Revenue!Q28 -> 3169915.8
B8: Total core revenue | C8: =SUM(C4:C7) -> 10420637 | D8: =SUM(D4:D7) -> 12906703 | E8: =SUM(E4:E7) -> 15488044 | F8: =SUM(F4:F7) -> 15797804 | G8: =SUM(G4:G7) -> 16113761 | H8: =SUM(H4:H7) -> 16436036 | I8: =SUM(I4:I7) -> 16764756 | J8: =SUM(J4:J7) -> 17100052 | ... Q8: =SUM(Q4:Q7) -> 19642584
B9: Core OPEX | C9: =-OPEX!C11 -> -4279857.5 | D9: =-OPEX!D11 -> -5231206.3 | E9: =-OPEX!E11 -> -6218897 | F9: =-OPEX!F11 -> -6343275 | G9: =-OPEX!G11 -> -6470140.5 | H9: =-OPEX!H11 -> -6599543.3 | I9: =-OPEX!I11 -> -6731534.1 | J9: =-OPEX!J11 -> -6866164.8 | ... Q9: =-OPEX!Q11 -> -7887065.1
B10: Core processing EBITDA | C10: =C8+C9 -> 6140779.3 | D10: =D8+D9 -> 7675496.7 | E10: =E8+E9 -> 9269146.5 | F10: =F8+F9 -> 9454529.5 | G10: =G8+G9 -> 9643620.1 | H10: =H8+H9 -> 9836492.5 | I10: =I8+I9 -> 10033222 | J10: =J8+J9 -> 10233887 | ... Q10: =Q8+Q9 -> 11755519
B12: Core CAPEX | C12: =CAPEX!C12 -> 57900000

Sheet P&L Post-Sorting
A1: Post-Sorting Segment P&L — 15-Year (V2)
C3: Year 1 | D3: Year 2 | E3: Year 3 | F3: Year 4 | G3: Year 5 | H3: Year 6 | I3: Year 7 | J3: Year 8 | K3: Year 9 | L3: Year 10 | M3: Year 11 | N3: Year 12 | O3: Year 13 | P3: Year 14 | Q3: Year 15
B4: Post-sorted metals revenue | C4: =IF('3-Operations'!$C$7=1,Revenue!C20*'2-Financial Inputs'!$C$52*(1+'2-Financial Inputs'!$C$11)^0,0) -> 63703.332 | D4: =IF('3-Operations'!$C$7=1,Revenue!D20*'2-Financial Inputs'!$C$52*(1+'2-Financial Inputs'!$C$11)^1,0) -> 78901.127 | E4: =IF('3-Operations'!$C$7=1,Revenue!E20*'2-Financial Inputs'!$C$52*(1+'2-Financial Inputs'!$C$11)^2,0) -> 94681.352 | F4: =IF('3-Operations'!$C$7=1,Revenue!F20*'2-Financial Inputs'!$C$52*(1+'2-Financial Inputs'!$C$11)^3,0) -> 96574.979 | G4: =IF('3-Operations'!$C$7=1,Revenue!G20*'2-Financial Inputs'!$C$52*(1+'2-Financial Inputs'!$C$11)^4,0) -> 98506.479 | H4: =IF('3-Operations'!$C$7=1,Revenue!H20*'2-Financial Inputs'!$C$52*(1+'2-Financial Inputs'!$C$11)^5,0) -> 100476.61 | I4: =IF('3-Operations'!$C$7=1,Revenue!I20*'2-Financial Inputs'!$C$52*(1+'2-Financial Inputs'!$C$11)^6,0) -> 102486.14 | J4: =IF('3-Operations'!$C$7=1,Revenue!J20*'2-Financial Inputs'!$C$52*(1+'2-Financial Inputs'!$C$11)^7,0) -> 104535.86 | K4: =IF('3-Operations'!$C$7=1,Revenue!K20*'2-Financial Inputs'!$C$52*(1+'2-Financial Inputs'!$C$11)^8,0) -> 106626.58 | L4: =IF('3-Operations'!$C$7=1,Revenue!L20*'2-Financial Inputs'!$C$52*(1+'2-Financial Inputs'!$C$11)^9,0) -> 108759.11 | M4: =IF('3-Operations'!$C$7=1,Revenue!M20*'2-Financial Inputs'!$C$52*(1+'2-Financial Inputs'!$C$11)^10,0) -> 110934.29 | N4: =IF('3-Operations'!$C$7=1,Revenue!N20*'2-Financial Inputs'!$C$52*(1+'2-Financial Inputs'!$C$11)^11,0) -> 113152.98 | O4: =IF('3-Operations'!$C$7=1,Revenue!O20*'2-Financial Inputs'!$C$52*(1+'2-Financial Inputs'!$C$11)^12,0) -> 115416.04 | P4: =IF('3-Operations'!$C$7=1,Revenue!P20*'2-Financial Inputs'!$C$52*(1+'2-Financial Inputs'!$C$11)^13,0) -> 117724.36 | Q4: =IF('3-Operations'!$C$7=1,Revenue!Q20*'2-Financial Inputs'!$C$52*(1+'2-Financial Inputs'!$C$11)^14,0) -> 120078.85
B6: Total post-sorting value added | C6: =C4 -> 63703.332 | D6: =D4 -> 78901.127 | E6: =E4 -> 94681.352 | F6: =F4 -> 96574.979 | G6: =G4 -> 98506.479 | H6: =H4 -> 100476.61 | I6: =I4 -> 102486.14 | J6: =J4 -> 104535.86 | ... Q6: =Q4 -> 120078.85
B7: Post-sorting OPEX | C7: =-OPEX!C21 -> -129640 | D7: =-OPEX!D21 -> -160568.4 | E7: =-OPEX!E21 -> -192682.08 | F7: =-OPEX!F21 -> -196535.72 | G7: =-OPEX!G21 -> -200466.44 | H7: =-OPEX!H21 -> -204475.76 | I7: =-OPEX!I21 -> -208565.28 | J7: =-OPEX!J21 -> -212736.59 | ... Q7: =-OPEX!Q21 -> -244367.47
B8: Post-sorting EBITDA | C8: =C6+C7 -> -65936.668 | D8: =D6+D7 -> -81667.273 | E8: =E6+E7 -> -98000.728 | F8: =F6+F7 -> -99960.742 | G8: =G6+G7 -> -101959.96 | H8: =H6+H7 -> -103999.16 | I8: =I6+I7 -> -106079.14 | J8: =J6+J7 -> -108200.72 | ... Q8: =Q6+Q7 -> -124288.62
B10: Post-sorting CAPEX | C10: =CAPEX!C29 -> 430000
B11: Simple payback (years) | C11: =IF(E8>0,C10/E8,0) -> 0

Sheet Cash Flow
A1: Cash Flow Statement — 15-Year Projection (V2)
C3: Year 1 | D3: Year 2 | E3: Year 3 | F3: Year 4 | G3: Year 5 | H3: Year 6 | I3: Year 7 | J3: Year 8 | K3: Year 9 | L3: Year 10 | M3: Year 11 | N3: Year 12 | O3: Year 13 | P3: Year 14 | Q3: Year 15
B4: Net income | C4: ='P&L Consolidated'!C13 -> -3745402.1 | D4: ='P&L Consolidated'!D13 -> -1971374 | E4: ='P&L Consolidated'!E13 -> -104306.76 | F4: ='P&L Consolidated'!F13 -> 341863.49 | G4: ='P&L Consolidated'!G13 -> 799081.2 | H4: ='P&L Consolidated'!H13 -> 1297612.2 | I4: ='P&L Consolidated'!I13 -> 1842143 | J4: ='P&L Consolidated'!J13 -> 2437917.2 | ... Q4: ='P&L Consolidated'!Q13 -> 5236597
B5: Add back: Depreciation | C5: =CAPEX!$C$48 -> 4252033.3 | D5: =CAPEX!$C$48 -> 4252033.3 | E5: =CAPEX!$C$48 -> 4252033.3 | F5: =CAPEX!$C$48 -> 4252033.3 | G5: =CAPEX!$C$48 -> 4252033.3 | H5: =CAPEX!$C$48 -> 4252033.3 | I5: =CAPEX!$C$48 -> 4252033.3 | J5: =CAPEX!$C$48 -> 4252033.3 | ... Q5: =CAPEX!$C$48 -> 4252033.3
B6: Change in working capital | C6: =-Revenue!C33*'2-Financial Inputs'!$C$13 -> -542537.66 | D6: =-(Revenue!D33-Revenue!C33)*'2-Financial Inputs'!$C$13 -> -129433.98 | E6: =-(Revenue!E33-Revenue!D33)*'2-Financial Inputs'!$C$13 -> -134394.33 | F6: =-(Revenue!F33-Revenue!E33)*'2-Financial Inputs'!$C$13 -> -16127.319 | G6: =-(Revenue!G33-Revenue!F33)*'2-Financial Inputs'!$C$13 -> -16449.866 | H6: =-(Revenue!H33-Revenue!G33)*'2-Financial Inputs'!$C$13 -> -16778.863 | I6: =-(Revenue!I33-Revenue!H33)*'2-Financial Inputs'!$C$13 -> -17114.44 | J6: =-(Revenue!J33-Revenue!I33)*'2-Financial Inputs'!$C$13 -> -17456.729 | K6: =-(Revenue!K33-Revenue!J33)*'2-Financial Inputs'!$C$13 -> -17805.864 | ... Q6: =-(Revenue!Q33-Revenue!P33)*'2-Financial Inputs'!$C$13 -> -20052.295
B7: Operating cash flow | C7: =C4+C5+C6 -> -35906.46 | D7: =D4+D5+D6 -> 2151225.3 | E7: =E4+E5+E6 -> 4013332.2 | F7: =F4+F5+F6 -> 4577769.5 | G7: =G4+G5+G6 -> 5034664.7 | H7: =H4+H5+H6 -> 5532866.7 | I7: =I4+I5+I6 -> 6077061.9 | J7: =J4+J5+J6 -> 6672493.8 | ... Q7: =Q4+Q5+Q6 -> 9468578.1
B8: Loan principal repayment | C8: =-Amortization!E6 -> -2544134.9 | D8: =-Amortization!E7 -> -2849431.1 | E8: =-Amortization!E8 -> -3191362.9 | F8: =-Amortization!E9 -> -3574326.4 | G8: =-Amortization!E10 -> -4003245.6 | H8: =-Amortization!E11 -> -4483635 | I8: =-Amortization!E12 -> -5021671.3 | J8: =-Amortization!E13 -> -5624271.8 | K8: =-Amortization!E14 -> -6299184.4 | L8: =-Amortization!E15 -> -7055086.6 | M8: 0 | N8: 0 | O8: 0 | P8: 0 | Q8: 0
B9: Free cash flow (after debt) | C9: =C7+C8 -> -2580041.4 | D9: =D7+D8 -> -698205.8 | E9: =E7+E8 -> 821969.38 | F9: =F7+F8 -> 1003443.1 | G9: =G7+G8 -> 1031419.1 | H9: =H7+H8 -> 1049231.6 | I9: =I7+I8 -> 1055390.7 | J9: =J7+J8 -> 1048222 | ... Q9: =Q7+Q8 -> 9468578.1
B10: Cumulative cash flow | C10: =C9 -> -2580041.4 | D10: =C10+D9 -> -3278247.2 | E10: =D10+E9 -> -2456277.8 | F10: =E10+F9 -> -1452834.7 | G10: =F10+G9 -> -421415.64 | H10: =G10+H9 -> 627815.98 | I10: =H10+I9 -> 1683206.6 | J10: =I10+J9 -> 2731428.6 | K10: =J10+K9 -> 3757273.5 | ... Q10: =P10+Q9 -> 50470162
B12: EQUITY INVESTED (Year 0) | C12: =-CAPEX!C47 -> -19134150
B13: Cumulative cash flow net of equity | C13: =C10+$C$12 -> -21714191 | D13: =D10+$C$12 -> -22412397 | E13: =E10+$C$12 -> -21590428 | F13: =F10+$C$12 -> -20586985 | G13: =G10+$C$12 -> -19555566 | H13: =H10+$C$12 -> -18506334 | I13: =I10+$C$12 -> -17450943 | J13: =J10+$C$12 -> -16402721 | ... Q13: =Q10+$C$12 -> 31336012
B15: KEY METRICS
B16: Equity payback (approx years) | C16: =IF(Q13>0,MATCH(TRUE(),INDEX(C13:Q13>0,0),0),">15") -> 12
B17: Annualised ROI on equity | C17: =IF(CAPEX!C47=0,0,AVERAGE(C9:Q9)/CAPEX!C47) -> 0.17584672
