Workbook

Sheet 0-Revisions
A1: URBAN RIG — MODELE FINANCIER V7
A2: Revision du V6. Etablie le 21 septembre 2026. Char en deux hypotheses, PCI du char, modele de cadence.
A4: # | B4: Poste | C4: V3 | D4: V4 | E4: Statut | F4: Justification
A5: BLOC V5 — CORRECTIONS DU 19/09/2026
B6: Flux de tresorerie | C6: EBITDA - impot, sans les interets | D6: EBITDA + impot + interets | E6: CORRIGE | F6: DEUX ERREURS DU V4. Un : la ligne d'impot est negative et etait soustraite, donc l'impot s'AJOUTAIT a la tresorerie. Deux : les interets payes a la banque n'etaient pas deduits du flux libre. Le moteur Python avait la seconde erreur. Effet : flux libre et TRI des fonds propres fortement surestimes dans le V4.
B7: Bilan matiere | C7: 1 565 T/an non comptees | D7: Ecart nul, controle ajoute | E7: CORRIGE | F7: Trois fuites du V4 : fraction non classee de 2,5% (1 132 T/an), fer et aluminium ayant echappe au pre-tri (289 T/an), chlore du PVC (144 T/an). Les deux premieres vont en elimination, le chlore dans le concentrat. Lignes de controle K1 a K4 ajoutees a l'onglet 2-Production.
B8: Recuperation des metaux dans le char | C8: Autres metaux seulement | D8: Fer, aluminium et autres | E8: REINTRODUIT | F8: Le V3 recuperait dans le char 80% du fer et de l'aluminium ayant echappe au pre-tri. Le V4 l'avait perdu.
B9: Besoin en fonds de roulement | C9: Absent | D9: 5% du chiffre d'affaires | E9: REINTRODUIT | F9: Reprise du V3 F8. Variation annuelle en tresorerie, recuperation en annee 15.
B10: VAN et TRI | C10: Absents | D10: VAN au CMPC de 10%, TRI projet, TRI fonds propres | E10: REINTRODUIT | F10: Reprise du V3 F7.
B11: Prix de l'huile | C11: Craqueur 641 ou combustible 350 | D11: Trois fractions, trois scenarios : 480 / 641 / 895 | E11: REINTRODUIT | F11: Reprise du V3 section H. Le 350 EUR/T du V4 n'avait pas de source ; le scenario bas documente est a 480.
B12: Emprunt | C12: Amortissement lineaire du capital | D12: Annuites constantes, mensualites | E12: CORRIGE | F12: Reprise du V3 : 120 mensualites, pratique bancaire francaise.
B13: Humidite | C13: 8%, sans reserve | D13: 8%, avec avertissement | E13: PRECISE | F13: Le V3 precisait que les OMR sont a 25-35% et que 8% suppose une charge presechee. Avertissement retabli.
B14: Gate fees par type de dechet | C14: Moyenne unique a 110 | D14: Six categories + mode de calcul | E14: REINTRODUIT | F14: Reprise du V3 section G. Mode 1 : moyenne saisie (110, valeur par defaut). Mode 2 : melange par type (melange CDG : 119 EUR/T).
A15: BLOC A — ERREURS DE STRUCTURE
B16: Multiplicateur d'unites | C16: N'agit que sur les gate fees | D16: Agit sur tout le modele | E16: CORRIGE | F16: Dans le V3, la cellule A4 de 1-Waste Input multiplie le tonnage utilise pour les gate fees, mais l'huile, le char, les metaux, le verre, les credits carbone et la quasi-totalite de l'OPEX sont calcules a partir de la production journaliere d'UNE unite. Mettre 2 donnait un resultat faux.
B17: Recettes huile, char, metaux, verre | C17: Non multipliees par N | D17: Multipliees par N | E17: CORRIGE | F17: Consequence directe du point precedent.
B18: OPEX electricite, fioul, residus | C18: Non multiplies par N | D18: Multiplies par N | E18: CORRIGE
B19: Personnel de tri | C19: 4 + 3 ETP fixes | D19: 7 ETP par unite | E19: CORRIGE | F19: Le trommel du V3 est dimensionne a 6 T/h, soit 144 T/jour, c'est-a-dire le debit d'une seule machine. Deux machines exigent deux lignes de tri.
B20: Lignes de pre-tri et post-tri (CAPEX) | C20: Montant fixe | D20: x N | E20: CORRIGE | F20: Meme raison.
A21: BLOC B — ENERGIE
B22: PCI du gaz de procede — plastique | C22: 5,54 MJ/kg | D22: 37,3 MJ/kg | E22: CORRIGE | F22: Calcule a partir du rapport de chromatographie B2002600 du 05/12/2020. L'echantillon contient 65,8% de N2 et 12,3% de O2, soit 78,1% de diluant. Sur les 19,7% de gaz reel (H2 12,7%, CH4 3,2%, C2-C3 1,5%, CO 0,6%, CO2 1,7%), le PCI ressort a 37,3 MJ/kg, soit 18,8 MJ/Nm3. Le 5,54 MJ/kg du rapport d'essai est le PCI de l'echantillon DILUE, applique par erreur a la masse de gaz non dilue du bilan matiere.
B23: PCI du gaz de procede — organique | C23: 0,5 MJ/kg | D23: 11,0 MJ/kg | E23: CORRIGE | F23: Neves et al., Chalmers : PCI du gaz de pyrolyse de biomasse d'environ 11 MJ/kg a 600 degres C. Le 0,5 MJ/kg du V3 n'a aucune source. Valeur hors depot, a confirmer par un essai sur charge organique.
B24: Fioul de chauffe | C24: 7 494 L/jour, 989 297 EUR/an | D24: 0 L/jour en regime normal | E24: CORRIGE | F24: Avec les PCI corriges, le gaz de procede couvre 130% du besoin thermique a 30% de plastique. La separation etagee (150 / 300 / 450 degres C) permet d'ajuster la coupure C5 et donc l'arbitrage huile contre gaz. Le bruleur, le separateur et la filtration sont deja installes.
B25: Provision de fioul de secours | C25: Absente | D25: 5% du besoin theorique | E25: AJOUTE | F25: Demarrages, arrets, variations de charge, flamme pilote. Cellule modifiable.
B26: Besoin thermique | C26: 2 714 MJ/T | D26: 2 714 MJ/T | E26: INCHANGE | F26: Recoupement independant : le bruleur est donne a 833 kcal/s dans UR2000-JP, soit 3,49 MW et 301 190 MJ/jour, a comparer aux 338 802 MJ/jour du modele. Coherent a 11% pres.
B27: Rendement du bruleur | C27: Implicite 100% | D27: 85% | E27: AJOUTE | F27: Aucun bruleur ne transfere 100% de l'energie du combustible au procede.
A28: BLOC C — CAPEX
B29: Batiment | C29: 5,0 MEUR fixe | D29: Surface x 1 075 EUR/m2 | E29: CORRIGE | F29: Plans d'implantation UR2000-JP. Une machine : 4 650 m2 batis (usine 3 000, dechets 640, produits 810, bureaux 200). Cinq machines : 21 770 m2 (usine S 14 230, dechets RC 3 450, CSR RC 3 450, bureaux RC 640). La surface par machine ne baisse que de 6%.
B30: Emprise fonciere | C30: Absente | D30: Ligne indicative | E30: AJOUTE | F30: UR2000-JP : 5 265 m2 pour une machine, 28 900 m2 (170 x 170 m) pour cinq. A ne pas confondre avec la surface batie.
B31: Ingenierie, ICPE, MOE | C31: Fixe | D31: +20% par machine ajoutee | E31: CORRIGE | F31: Dossier ICPE et etude d'impact plus lourds.
A32: BLOC D — EXPLOITATION
B33: Electricite | C33: 4 800 kWh/jour | D33: 3 000 kWh/jour | E33: CORRIGE | F33: Quatre valeurs existent dans le depot : 20 kW en continu (fiche UR2000-JP), 600 kW (annexe 9), 4 800 kWh/jour soit 200 kW (V3), et 15 a 20 kWh/T mesures sur site (donnees Ichimura). 3 000 kWh/jour, soit 21,4 kWh/T, se cale sur la seule valeur mesuree. A trancher par un releve d'un mois.
B34: Prix de l'electricite | C34: 0,15 EUR/kWh | D34: 0,15 EUR/kWh | E34: INCHANGE
B35: Prix du fioul | C35: 0,40 EUR/L | D35: 0,95 EUR/L | E35: CORRIGE | F35: Prix GNR livre en France 2026 : 0,90 a 1,10 EUR/L HT. Sans effet materiel puisque la consommation tombe a la provision de secours.
B36: Assurance | C36: 0,5% du CAPEX | D36: 0,5% du CAPEX | E36: INCHANGE
B37: Provision et divers | C37: 2% du CAPEX | D37: 2% du CAPEX | E37: INCHANGE
B38: Maintenance | C38: 4% de l'equipement | D38: 4% de l'equipement | E38: INCHANGE | F38: Reserve : 5 a 8% est plus courant sur un procede haute temperature en atmosphere chloree. Cellule modifiable.
B39: Batiment | C39: 5,0 MEUR forfaitaires | D39: Surfaces x prix de marche par type | E39: CORRIGE | F39: Le 1 075 EUR/m2 de la premiere version du V4 etait un calcul inverse : 5 000 000 EUR du V3 divises par 4 650 m2 de plan. Ce n'etait pas une reference de marche. Remplace par quatre lignes aux prix du marche francais 2026 : usine de traitement 900 EUR/m2 (atelier de production, fourchette 500 a 1 000), stockage 500 EUR/m2 (hangar, fourchette 350 a 450 en charpente metallique), bureaux 1 300 EUR/m2. Le VRD, les fondations renforcees et les raccordements sortent en ligne distincte.
B40: VRD, fondations, raccordements | C40: Inclus dans le forfait | D40: 1,30 MEUR + 0,40 MEUR par unite | E40: AJOUTE | F40: UR2000-JP impose une dalle supportant 5 tonnes au m2. Poste distinct du batiment.
B41: Maintenance | C41: 4% de l'equipement des l'annee 1 | D41: 1% jusqu'en annee 4, montee lineaire a 4% en annee 10, puis 4% | E41: CORRIGE | F41: Equipement neuf sous garantie constructeur les premieres annees. Sur quinze ans le cumul passe de 60% a 40,5% du prix de l'equipement. Reserve a garder en tete : une revision majeure de refractaire tombe generalement entre l'annee 5 et l'annee 7 et n'est pas capturee par un pourcentage lisse.
B42: Couche catalytique d'adsorption des halogenes | C42: Absente | D42: 150 000 EUR/an/unite (valeur d'attente) | E42: AJOUTE | F42: Le document UR2000-JP decrit une couche catalytique placee AVANT le condenseur, qui capte le chlore en phase gazeuse (触媒槽・塩素除去). C'est le mecanisme qui explique le 1 ppm de chlore du certificat NKKK. Mais un adsorbant se sature : ni capacite, ni duree de vie, ni prix ne figurent au dossier. Le constructeur indique par ailleurs que les essais brome et fluor ont ete faits sur materiaux aeronautiques avec une efficacite comparable ; le rapport n'a pas ete produit.
B43: Traitement de l'eau de procede | C43: Absent | D43: Neutralisation + ceramique + charbon actif + concentrat | E43: AJOUTE | F43: Le chlore du PVC est transforme par la vapeur en acide chlorhydrique dilue, qui part dans l'eau (mecanisme decrit page 3 du document UR2000-JP). Chaine retenue : lit de carbonate de calcium en amont, puis SEA CORAL, puis charbon actif d'affinage. Essai constructeur du SEA CORAL sur eau de mer : chlorures de 31 000 a 31 mg/L, soit 99,9% d'abattement, rendement en eau 78%. L'electricite n'est PAS ajoutee, elle est deja dans la ligne H7 (environ 22 modules a 250 W, soit 132 kWh/jour, contre 3 000 kWh/jour pour la machine).
B44: Neutralisation au carbonate de calcium | C44: Absente | D44: 2,5 kg/T traitee | E44: AJOUTE | F44: Correction d'une reserve que j'avais formulee a tort. J'avais ecrit que le HCl, etant volatil, suivrait l'eau a travers le SEA CORAL. C'est exact en l'absence de traitement, mais la parade est elementaire et connue de longue date : un lit de calcaire en amont. CaCO3 + 2 HCl donne CaCl2 + H2O + CO2. Le chlorure de calcium est un sel non volatil, il reste dans le concentrat. Il ne subsiste que du CO2 dissous, d'ou un pH de 5 a 6, sans consequence. Le fluorure de calcium est en outre tres peu soluble et precipite. La reserve ne porte donc plus que sur les composes organiques volatils, traites par charbon actif.
B45: Energie d'evaporation de l'eau | C45: Sans objet | D45: Non comptee | E45: VERIFIE | F45: Le SEA CORAL n'est pas un procede thermique. Le document indique que la seule energie consommee est celle du ventilateur (動力はファンの駆動電力のみ). La chaleur latente est prise a l'air ambiant. Environ 250 W par module de 500 L/jour, soit 22 modules et 132 kWh/jour par machine, compris dans les 3 000 kWh/jour de la ligne H7.
B46: Chlore dans l'huile | C46: Non traite | D46: 1 ppm (certificat NKKK) | E46: CORRIGE | F46: Le fichier TECHNICAL-REFERENCE-VALIDATED-DATA.md du depot indique 'Chlorine Content < 100 ppm'. C'est une ERREUR DE RECOPIE : le 100 ppm est un SEUIL de reference cite dans le commentaire de l'annexe technique, section 2.2, pas une mesure. La valeur mesuree par NKKK est 0,0001%, soit 1 ppm. La specification vapocraqueur est de 3 ppm : l'huile passe. RESERVE posee par l'annexe elle-meme : l'echantillon est peut-etre une fraction legere uniquement (point eclair <= 40 degres C, viscosite 1,11 mm2/s), et la charge d'origine n'est pas documentee. A verifier fraction par fraction sur dechet reel.
B47: Decantation de l'eau de procede | C47: Absente | D47: Cuve de neutralisation et decantation | E47: AJOUTE | F47: Chaine retenue : eau de procede chargee en chlore et en organiques, puis bain de pellets de calcaire, puis decantation, puis separation des phases. La phase organique surnageante est reintroduite en benne avec la charge ; seule la phase aqueuse va au SEA CORAL. L'ordre compte : neutraliser avant de decanter augmente la force ionique de l'eau, donc accentue le relargage salin et ameliore la separation. Trois parametres nouveaux, tous a zero ou inconnus par defaut, lignes H14 a H16.
B48: Recyclage des organiques | C48: Absent | D48: Parametre a zero par defaut | E48: AJOUTE | F48: Les organiques decantes sont reintroduits DANS LES BENNES, avec la charge, ou ils sont absorbes par le papier et le carton. Jamais dans le circuit de vapeur : une chaudiere recevant des goudrons et des phenols se coke sur les tubes et devient le point de defaillance de l'installation. Double effet quand le parametre sera renseigne : moins de tonnage en elimination, et de l'huile supplementaire par recraquage a 600 degres C.
A49: BLOC E — RECETTES
B50: Gate fee | C50: 110 EUR/T | D50: 110 EUR/T | E50: INCHANGE | F50: Variable d'ajustement du modele. Les references de marche sont traitees dans un document distinct, ce fichier ne contient aucune comparaison.
B51: Prix de l'huile | C51: 641 EUR/T (scenario moyen) | D51: 641 EUR/T | E51: INCHANGE AVEC RESERVE | F51: Reserve majeure : ce prix suppose un debouche vapocraqueur. Les specifications industrielles imposent Cl <= 3 ppm ; le certificat NKKK annonce < 100 ppm. Sans hydrotraitement, l'huile se vend en qualite combustible, autour de 350 EUR/T. Un selecteur de qualite est ajoute a l'onglet 1-Inputs.
B52: Rendement char sur organique | C52: 69% | D52: 69% | E52: INCHANGE AVEC RESERVE | F52: Non verifie sur equipement UR (annexe technique F3). Un rendement char de 69% est tres eleve : la litterature donne 25 a 30% a 600 degres C. Attention, ce parametre est lie au gaz par le bilan matiere : plus de char signifie moins de gaz, donc moins d'autonomie energetique. On ne peut pas maximiser les deux.
B53: Prix du char | C53: 100 EUR/T | D53: 100 EUR/T | E53: INCHANGE AVEC RESERVE | F53: Debouche non demontre. Les referentiels IBI, EBC et Puro.earth excluent les OMR melangees. Selecteur de grade reintroduit en V6 (onglet 1-Inputs, K1).
B54: Credits carbone | C54: 2,50 MEUR/an en recette, base 1,80 T CO2/T | D54: Saisie libre, a zero par defaut | E54: CORRIGE | F54: Le V3 calculait une recette a partir d'une comparaison avec l'incineration. Ce modele ne contient plus aucune comparaison : il decrit l'installation seule. La ligne de recette carbone est desormais pilotee par une saisie unique, cellule G2 de l'onglet 1-Inputs, exprimee en tonnes de CO2 par tonne traitee. Elle doit rester a zero tant qu'une certification n'est pas obtenue.
B55: Bilan carbone | C55: Calcul d'emissions evitees | D55: Inventaire de l'installation | E55: CORRIGE | F55: L'onglet 2-Production, bloc T6, suit desormais le carbone fossile entrant (celui des plastiques) et verifie qu'on le retrouve integralement en sortie : brule sur site, parti dans l'huile vendue, parti dans le char vendu, ou stocke dans le char elimine. La ligne C10 controle cette egalite. Deux grandeurs en ressortent : les emissions directes du site, seule assiette possible d'un quota ou d'une taxe, et l'energie exportee, base d'une future certification RED III ou ISCC.
B56: Metaux | C56: Recuperation implicite 100% | D56: Recuperation 100% conservee | E56: INCHANGE AVEC RESERVE | F56: Les taux de recuperation du pre-tri (90% ferreux, 75% alu) sont deja appliques dans le V3. Coherent.
B57: Verre | C57: 30 EUR/T | D57: 30 EUR/T | E57: INCHANGE
A59: BLOC V6 — CORRECTIONS DU 21/09/2026
A60: V6.1 | B60: Dose de carbonate de calcium | C60: 2,5 kg/T fixe (115 T/an) | D60: Liee au HCl : 100/73 x 1,25 | E60: CORRIGE | F60: Le V5 posait moins que le minimum stoechiometrique : 144 T de HCl exigent au moins 197 T de CaCO3. La dose suit desormais le chlore calcule, donc la part de PVC. Le bilan matiere inclut le carbonate en entree, le CO2 degage et le carbonate en exces soutire avec les boues.
A61: V6.2 | B61: Grades de char | C61: 100 EUR/T seul | D61: Selecteur CSR 30 / briquettes 100 / biochar 350 | E61: REINTRODUIT | F61: Point 9. Reprise du V3 section I. Le libelle du V5 annoncait un selecteur qui n existait pas.
A62: V6.3 | B62: Interrupteurs pre-tri et post-tri | C62: Absents | D62: Deux interrupteurs | E62: REINTRODUIT | F62: Point 10. Agissent sur les taux de recuperation, le criblage du char, le CAPEX des lignes et le personnel (4 + 3 ETP par unite).
A63: V6.4 | B63: Comptes par segment | C63: Absents | D63: Onglet 5-Segments | E63: REINTRODUIT | F63: Point 10. Resultat annuel de chaque ligne de tri, annee 3, elimination evitee comprise.
A64: V6.5 | B64: Vente des recyclables au pre-tri | C64: Absente | D64: Option, desactivee par defaut | E64: REINTRODUIT | F64: Point 11. PET, PEHD et carton retires avant reacteur ; recette sur la ligne Verre et recyclables. Le tri optique correspondant n est pas chiffre au CAPEX.
A65: V6.6 | B65: Mode de gate fee par defaut | C65: Libelle : mode 2 | D65: Cellule : mode 1 (110 EUR/T) | E65: PRECISE | F65: Le libelle V5 indiquait le melange CDG par defaut alors que la cellule F1 etait a 1. Mode 1 conserve pour garder le cas de base comparable ; mode 2 donne 119 EUR/T.
A66: V6.7 | B66: Renvoi a l onglet 6-Sensibilite | C66: Onglet inexistant | D66: Renvoi supprime | E66: CORRIGE | F66: Ligne T4.10 de 2-Production.
A68: BLOC V7 — 21/09/2026
A69: V7.1 | B69: Debouche du char | C69: Selecteur a trois grades (CSR, briquettes, biochar) | D69: Deux hypotheses : combustible haute energie ou biochar | E69: MODIFIE | F69: Le char retient les goudrons figes pendant le refroidissement de 600 a 400 degres C : il est proche d un coke. Son prix est calcule par son PCI (25 MJ/kg) x un prix de l energie de substitution (4 EUR/GJ, a confirmer). Base inchangee a 100 EUR/T.
A70: V7.2 | B70: PCI du char | C70: 15 MJ/kg | D70: 25 MJ/kg, lie au selecteur | E70: CORRIGE | F70: Coherence avec les annexes. N agit que sur l energie exportee (bloc T6).
A71: V7.3 | B71: Capacite | C71: 200 m3/j x masse volumique, cadence fixe | D71: Modele de cadence : godets, temps d etape, charge par godet | E71: AJOUTE | F71: Mode 2 : le temps d etape suit la charge par godet, avec une part fixe et un plancher. Les trois parametres L5, L6, L7 sont a confirmer par OneWorld. Mode 1 par defaut.

Sheet 1-Inputs
A1: ENTREES DU MODELE
A2: Bleu = saisie. Orange = valeur corrigee par rapport au V3. Jaune = hypothese structurante non verifiee.
A4: Ref | B4: Parametre | C4: Valeur | D4: Unite | E4: Source / commentaire
A5: A — CAPACITE
A6: A1 | B6: Capacite nominale volumetrique par unite | C6: 200 | D6: m3/j | E6: URC-2000. Capacite volumetrique : 16 lots x 3 godets x 4,17 m3
A7: A2 | B7: Masse volumique des dechets | C7: 0.7 | D7: T/m3 | E7: V3 A2
A8: A3 | B8: Nombre d'unites URC-2000 | C8: 1 | D8: unites | E8: MODIFIABLE. Tout le modele suit desormais ce nombre
A9: A4 | B9: Jours d'exploitation par an | C9: 330 | D9: j/an | E9: V3 A5. 35 jours de maintenance
A11: B — COMPOSITION DU DECHET
A12: B1 | B12: Plastique | C12: 0.3 | D12: % | E12: V3 B1. La fiche constructeur UR2000-JP calcule son cas de reference a 10% de resine
A13: B2 | B13: Organique et cellulose | C13: 0.47 | D13: % | E13: V3 B2
A14: B3 | B14: Metaux | C14: 0.05 | D14: % | E14: V3 B3
A15: B4 | B15: Verre | C15: 0.055 | D15: % | E15: V3 B4
A16: B5 | B16: Inertes mineraux | C16: 0.02 | D16: % | E16: V3 B5
A17: B6 | B17: Humidite | C17: 0.08 | D17: % | E17: ATTENTION : les OMR brutes sont a 25-35% d'humidite. 8% suppose une charge presechee ou un gisement sec (emballages, dechets aeroportuaires). L'annexe 2 fait son controle thermique a ~20%
A18: B7 | B18: Autres | C18: 0.025 | D18: % | E18: V3 B7
A19: B8 | B19: Taux de refus a l'entree | C19: 0.02 | D19: % | E19: V3 D7
A20: B9 | B20: Part ferreuse des metaux | C20: 0.8 | D20: % | E20: V3 B2.1
A21: B10 | B21: Part aluminium des metaux | C21: 0.15 | D21: % | E21: V3 B2.2
A23: C — RENDEMENTS
A24: C1 | B24: Rendement huile sur plastique | C24: 0.69315 | D24: % | E24: V3 E1, moyenne ponderee du mix polymere
A25: C2 | B25: Rendement gaz sur plastique | C25: 0.193 | D25: % | E25: V3 E2
A26: C3 | B26: Rendement residu solide sur plastique | C26: 0.10325 | D26: % | E26: V3 E3
A27: C4 | B27: Rendement char sur organique | C27: 0.69 | D27: % | E27: V3 D1. NON VERIFIE. Litterature : 25 a 30% a 600 degres C. Lie au gaz par le bilan matiere
A28: C5 | B28: Masse volumique de l'huile | C28: 0.85 | D28: kg/L | E28: V3 D2
A30: D — ENERGIE (BLOC CORRIGE)
A31: D1 | B31: PCI du gaz issu du plastique | C31: 37.3 | D31: MJ/kg | E31: CORRIGE. Calcule sur le rapport GC B2002600 apres retrait du diluant (78,1% de N2 et O2). Etait 5,54
A32: D2 | B32: PCI du gaz issu de l'organique | C32: 11 | D32: MJ/kg | E32: CORRIGE. Neves et al., Chalmers, gaz de pyrolyse de biomasse a 600 degres C. Etait 0,5. Valeur hors depot, a mesurer
A33: D3 | B33: Besoin thermique | C33: 2714 | D33: MJ/T | E33: V3 D6. Recoupe par le bruleur de 833 kcal/s soit 3,49 MW
A34: D4 | B34: Rendement du bruleur | C34: 0.85 | D34: % | E34: AJOUTE
A35: D5 | B35: Provision de fioul de secours | C35: 0.05 | D35: % du besoin | E35: AJOUTE. Demarrages, arrets, flamme pilote
A36: D6 | B36: PCI du fioul | C36: 38 | D36: MJ/L | E36: V3
A37: D7 | B37: PCI du char organique | C37: ='1-Inputs'!$C$169 -> 25 | D37: MJ/kg | E37: V7. Lie a K1a. Etait 15 MJ/kg (V3 D4), incoherent avec les annexes (~25)
A39: E — TRI
A40: E1 | B40: Recuperation ferreux au pre-tri | C40: 0.9 | D40: % | E40: V3 P1
A41: E2 | B41: Recuperation aluminium au pre-tri | C41: 0.75 | D41: % | E41: V3 P2
A42: E3 | B42: Recuperation verre au pre-tri | C42: 0.7 | D42: % | E42: V3 P3
A43: E4 | B43: Retrait des inertes au pre-tri | C43: 0.5 | D43: % | E43: V3 P6
A44: E5 | B44: Criblage du char au post-tri | C44: 0.85 | D44: % | E44: V3 Q1
A45: E6 | B45: Metaux recuperes du char | C45: 0.8 | D45: % | E45: V3 Q2
A46: E7 | B46: Separation des inertes du char | C46: 0.7 | D46: % | E46: V3 Q3
A48: F — PRIX
A49: F1 | B49: Mode de gate fee (1 = moyenne saisie, 2 = mix par type de dechet) | C49: 1 | D49: - | E49: V5. Le mode 2 calcule la moyenne a partir du melange ci-dessous
A50: F1a | B50: Gate fee moyen saisi | C50: 110 | D50: EUR/T | E50: Utilise si mode 1. Reference : SYCTOM 103 EUR/T hors TGAP ; melange CDG 109 EUR/T
A51: F1b | B51: Gate fee — OMR municipales | C51: 100 | D51: EUR/T | E51: Grille par type de dechet, reprise du V3 section G
A52: F1c | B52: Part OMR municipales | C52: 0.5 | D52: % du tonnage | E52: Melange CDG de la reference gate fees
A53: F1d | B53: Gate fee — industriel et logistique | C53: 120 | D53: EUR/T
A54: F1e | B54: Part industriel et logistique | C54: 0.14 | D54: % du tonnage
A55: F1f | B55: Gate fee — dechets aeroportuaires | C55: 150 | D55: EUR/T | E55: Prime de biosecurite
A56: F1g | B56: Part dechets aeroportuaires | C56: 0.29 | D56: % du tonnage
A57: F1h | B57: Gate fee — composites | C57: 130 | D57: EUR/T | E57: Pales d'eoliennes, composites aeronautiques
A58: F1i | B58: Part composites | C58: 0.07 | D58: % du tonnage
A59: F1j | B59: Gate fee — DASRI | C59: 800 | D59: EUR/T | E59: Dechets de soins a risques infectieux
A60: F1k | B60: Part DASRI | C60: 0 | D60: % du tonnage | E60: Levier principal pour un retour sur investissement court
A61: F1l | B61: Gate fee — pneus | C61: 30 | D61: EUR/T | E61: Souvent faible, collecte financee par la REP
A62: F1m | B62: Part pneus | C62: 0 | D62: % du tonnage
A63: F1n | B63: Controle : somme des parts | C63: ='1-Inputs'!$C$52+'1-Inputs'!$C$54+'1-Inputs'!$C$56+'1-Inputs'!$C$58+'1-Inputs'!$C$60+'1-Inputs'!$C$62 -> 1 | D63: - | E63: Doit valoir 100%
A64: F1o | B64: Gate fee du melange | C64: =('1-Inputs'!$C$51*'1-Inputs'!$C$52+'1-Inputs'!$C$53*'1-Inputs'!$C$54+'1-Inputs'!$C$55*'1-Inputs'!$C$56+'1-Inputs'!$C$57*'1-Inputs'!$C$58+'1-Inputs'!$C$59*'1-Inputs'!$C$60+'1-Inputs'!$C$61*'1-Inputs'!$C$62)/MAX(0.0001,'1-Inputs'!$C$63) -> 119.4 | D64: EUR/T | E64: Moyenne ponderee par le tonnage
A65: F1p | B65: GATE FEE RETENU | C65: =IF('1-Inputs'!$C$49=1,'1-Inputs'!$C$50,'1-Inputs'!$C$64) -> 110 | D65: EUR/T | E65: Valeur utilisee dans le compte de resultat
A66: F2 | B66: Scenario de prix de l'huile (1 = bas, 2 = moyen, 3 = haut) | C66: 2 | D66: - | E66: V5. Reprise du V3 section H. Bas : brut non differencie. Moyen : spot ICIS par fraction. Haut : prime ISCC
A67: F2a | B67: Part fraction legere (C5-C8) | C67: 0.1 | D67: % | E67: Specification constructeur, annexe 3
A68: F2b | B68: Fraction legere — bas / moyen / haut | C68: 450 | D68: EUR/T | E68: bas
A69: F2c | C69: 600 | D69: EUR/T | E69: moyen
A70: F2d | C70: 800 | D70: EUR/T | E70: haut
A71: F2e | B71: Part fraction gazole (C8-C16) | C71: 0.8 | D71: %
A72: F2f | B72: Fraction gazole — bas / moyen / haut | C72: 500 | D72: EUR/T | E72: bas
A73: F2g | C73: 670 | D73: EUR/T | E73: moyen : spot pyrolyse Pays-Bas ~670 EUR/T
A74: F2h | C74: 950 | D74: EUR/T | E74: haut
A75: F2i | B75: Part fraction lourde (C16+) | C75: 0.1 | D75: %
A76: F2j | B76: Fraction lourde — bas / moyen / haut | C76: 350 | D76: EUR/T | E76: bas
A77: F2k | C77: 450 | D77: EUR/T | E77: moyen
A78: F2l | C78: 550 | D78: EUR/T | E78: haut
A79: F2m | B79: PRIX DE L'HUILE RETENU | C79: ='1-Inputs'!$C$67*CHOOSE('1-Inputs'!$C$66,'1-Inputs'!$C$68,'1-Inputs'!$C$69,'1-Inputs'!$C$70)+'1-Inputs'!$C$71*CHOOSE('1-Inputs'!$C$66,'1-Inputs'!$C$72,'1-Inputs'!$C$73,'1-Inputs'!$C$74)+'1-Inputs'!$C$75*CHOOSE('1-Inputs'!$C$66,'1-Inputs'!$C$76,'1-Inputs'!$C$77,'1-Inputs'!$C$78) -> 641 | D79: EUR/T | E79: Bas 480, moyen 641, haut 895. Remplace le prix combustible a 350 du V4, sans source
A80: F5 | B80: Prix du char | C80: =IF('1-Inputs'!$C$168=1,'1-Inputs'!$C$171,'1-Inputs'!$C$172) -> 100 | D80: EUR/T | E80: V7. Calcule a partir du selecteur K1 (deux hypotheses)
A81: F6 | B81: Prix ferreux | C81: 250 | D81: EUR/T | E81: V3 J1
A82: F7 | B82: Prix aluminium | C82: 1400 | D82: EUR/T | E82: V3 J2
A83: F8 | B83: Prix autres metaux | C83: 500 | D83: EUR/T | E83: V3 J3
A84: F9 | B84: Prix du verre | C84: 30 | D84: EUR/T | E84: V3 J5
A85: F10 | B85: Cout d'elimination des residus | C85: 110 | D85: EUR/T | E85: V3 K1
A86: F11 | B86: Prix du fioul | C86: 0.95 | D86: EUR/L | E86: CORRIGE. GNR livre France 2026. Etait 0,40
A87: F12 | B87: Prix de l'electricite | C87: 0.15 | D87: EUR/kWh | E87: V3 K3
A89: G — CARBONE DE L'INSTALLATION
A90: G1 | B90: Recette carbone active (1 = oui, 0 = non) | C90: 0 | D90: - | E90: Aucun mecanisme eligible identifie a ce jour. Voir la note de l'onglet 0-Revisions
A91: G2 | B91: Reduction carbone certifiee retenue | C91: 0 | D91: T CO2/T traitee | E91: SAISIE LIBRE. A renseigner uniquement sur la base d'une certification obtenue (RED III / RCF, ISCC, ou methodologie volontaire approuvee). Toute valeur non certifiee doit rester a zero
A92: G3 | B92: Prix retenu | C92: 50 | D92: EUR/T CO2 | E92: V3 L1
A93: G4 | B93: Teneur en carbone des plastiques | C93: 0.857 | D93: % | E93: Polyolefines : carbone et hydrogene uniquement, 85,7% de carbone
A94: G5 | B94: Teneur en carbone de la fraction organique | C94: 0.45 | D94: % | E94: Papier, bois, cellulose. Carbone biogenique
A95: G6 | B95: Teneur en carbone du gaz de procede | C95: 0.8 | D95: % | E95: Melange H2, CH4, C2-C3
A96: G7 | B96: Teneur en carbone du residu plastique | C96: 0.8 | D96: %
A97: G8 | B97: Teneur en carbone du char organique | C97: 0.5 | D97: % | E97: Char d'OMR, taux de cendres eleve
A98: G9 | B98: CO2 par tonne d'huile brulee | C98: 3.1 | D98: T CO2/T | E98: Hydrocarbure fossile. Emission de l'utilisateur final, pas du site
A99: G10 | B99: CO2 du fioul | C99: 2.68 | D99: kg/L | E99: V3 L3
A100: G11 | B100: PCI de l'huile | C100: 43 | D100: GJ/T | E100: Mesure NKKK : 43,27 MJ/kg
A101: G12 | B101: PCI du residu plastique | C101: 25 | D101: GJ/T | E101: V3 D5
A103: H — COUTS D'EXPLOITATION
A104: H1 | B104: ETP coeur — premiere unite | C104: 15 | D104: ETP | E104: V3 M1+M2+M3
A105: H2 | B105: ETP coeur — par unite supplementaire | C105: 3 | D105: ETP | E105: AJOUTE
A106: H3 | B106: ETP tri par unite | C106: ='1-Inputs'!$C$173*'1-Inputs'!$C$175+'1-Inputs'!$C$174*'1-Inputs'!$C$176 -> 7 | D106: ETP | E106: V6. Calcule : 4 ETP pre-tri + 3 ETP post-tri, selon les interrupteurs K2 et K3
A107: H4 | B107: Cout charge par ETP | C107: 56000 | D107: EUR/an | E107: V3 M4
A108: H5 | B108: Maintenance — annees 1 a 4 | C108: 0.01 | D108: % equipement | E108: CORRIGE. Equipement neuf sous garantie constructeur
...

Sheet 2-Production
A1: BILAN MATIERE ET ENERGIE
A2: Colonne C : une unite. Colonne D : toutes unites. Base journaliere sauf indication.
A4: Ref | B4: Grandeur | C4: Par unite | D4: Total | E4: Unite | F4: Commentaire
A5: T1 — ENTREE
A6: T1.1 | B6: Debit massique nominal | C6: ='1-Inputs'!$C$204 -> 140 | D6: =C6*'1-Inputs'!$C$8 -> 140 | E6: T/j | F6: V7. Voir onglet 1-Inputs, bloc L. Mode 1 : 200 m3/j x masse volumique
A7: T1.2 | B7: Tonnage annuel | C7: =C6*'1-Inputs'!$C$9 -> 46200 | D7: =C7*'1-Inputs'!$C$8 -> 46200 | E7: T/an
A8: T1.3 | B8: Entree brute | C8: =C6*1000 -> 140000 | D8: =C8*'1-Inputs'!$C$8 -> 140000 | E8: kg/j
A9: T1.4 | B9: Refus a l'entree | C9: =C8*'1-Inputs'!$C$19 -> 2800 | D9: =C9*'1-Inputs'!$C$8 -> 2800 | E9: kg/j
A10: T1.5 | B10: Entree nette traitee | C10: =C8-C9 -> 137200 | D10: =C10*'1-Inputs'!$C$8 -> 137200 | E10: kg/j
A12: T2 — COMPOSITION
A13: T2.1 | B13: Plastique | C13: =C10*'1-Inputs'!$C$12*(1-'1-Inputs'!$C$188*'1-Inputs'!$C$184) -> 41160 | D13: =C13*'1-Inputs'!$C$8 -> 41160 | E13: kg/j | F13: V6. Net des recyclables extraits au pre-tri si l option K11 est active
A14: T2.2 | B14: Organique et cellulose | C14: =C10*'1-Inputs'!$C$13*(1-'1-Inputs'!$C$188*'1-Inputs'!$C$186) -> 64484 | D14: =C14*'1-Inputs'!$C$8 -> 64484 | E14: kg/j
A15: T2.3 | B15: Metaux | C15: =C10*'1-Inputs'!$C$14 -> 6860 | D15: =C15*'1-Inputs'!$C$8 -> 6860 | E15: kg/j
A16: T2.4 | B16: Verre | C16: =C10*'1-Inputs'!$C$15 -> 7546 | D16: =C16*'1-Inputs'!$C$8 -> 7546 | E16: kg/j
A17: T2.5 | B17: Inertes | C17: =C10*'1-Inputs'!$C$16 -> 2744 | D17: =C17*'1-Inputs'!$C$8 -> 2744 | E17: kg/j
A18: T2.6 | B18: Autres, non classes | C18: =C10*'1-Inputs'!$C$18 -> 3430 | D18: =C18*'1-Inputs'!$C$8 -> 3430 | E18: kg/j
A20: T3 — SORTIES DU REACTEUR
A21: T3.1 | B21: Huile | C21: =C13*'1-Inputs'!$C$24 -> 28530.054 | D21: =C21*'1-Inputs'!$C$8 -> 28530.054 | E21: kg/j
A22: T3.2 | B22: Huile | C22: =C21/'1-Inputs'!$C$28 -> 33564.769 | D22: =C22*'1-Inputs'!$C$8 -> 33564.769 | E22: L/j
A23: T3.3 | B23: Gaz de procede issu du plastique | C23: =C13*'1-Inputs'!$C$25 -> 7943.88 | D23: =C23*'1-Inputs'!$C$8 -> 7943.88 | E23: kg/j
A24: T3.4 | B24: Residu solide du plastique | C24: =C13*'1-Inputs'!$C$26 -> 4249.77 | D24: =C24*'1-Inputs'!$C$8 -> 4249.77 | E24: kg/j
A25: T3.5 | B25: Char organique | C25: =C14*'1-Inputs'!$C$27 -> 44493.96 | D25: =C25*'1-Inputs'!$C$8 -> 44493.96 | E25: kg/j
A26: T3.5b | B26: Chlore du PVC capte dans l'eau (HCl) | C26: =C13*(1-'1-Inputs'!$C$24-'1-Inputs'!$C$25-'1-Inputs'!$C$26) -> 436.296 | D26: =C26*'1-Inputs'!$C$8 -> 436.296 | E26: kg/j | F26: V5. Complement a 100% des rendements plastique : 2% de PVC x 53% de chlore. Part dans l'eau, neutralise, finit dans le concentrat
A27: T3.6 | B27: Gaz de procede issu de l'organique | C27: =C14-C25 -> 19990.04 | D27: =C27*'1-Inputs'!$C$8 -> 19990.04 | E27: kg/j | F27: Par difference. Plus le rendement char est eleve, moins il reste de gaz
A29: T4 — BILAN ENERGIE (BLOC CORRIGE)
A30: T4.1 | B30: Energie du gaz issu du plastique | C30: =C23*'1-Inputs'!$C$31 -> 296306.72 | D30: =C30*'1-Inputs'!$C$8 -> 296306.72 | E30: MJ/j | F30: PCI corrige a 37,3 MJ/kg
A31: T4.2 | B31: Energie du gaz issu de l'organique | C31: =C27*'1-Inputs'!$C$32 -> 219890.44 | D31: =C31*'1-Inputs'!$C$8 -> 219890.44 | E31: MJ/j | F31: PCI corrige a 11,0 MJ/kg
A32: T4.3 | B32: Energie totale du gaz de procede | C32: =C30+C31 -> 516197.16 | D32: =C32*'1-Inputs'!$C$8 -> 516197.16 | E32: MJ/j
A33: T4.4 | B33: Chaleur utile delivree par le bruleur | C33: =C32*'1-Inputs'!$C$34 -> 438767.59 | D33: =C33*'1-Inputs'!$C$8 -> 438767.59 | E33: MJ/j | F33: Rendement bruleur 85%
A34: T4.5 | B34: Besoin thermique | C34: =C6*'1-Inputs'!$C$33 -> 379960 | D34: =C34*'1-Inputs'!$C$8 -> 379960 | E34: MJ/j | F34: Recoupement : bruleur de 833 kcal/s soit 301 190 MJ/j
A35: T4.6 | B35: Taux de couverture par le gaz | C35: =C33/C34 -> 1.1547731 | D35: =C35*'1-Inputs'!$C$8 -> 1.1547731 | E35: % | F35: Superieur a 100% : autonomie energetique
A36: T4.7 | B36: Deficit thermique eventuel | C36: =MAX(0,C34-C33) -> 0 | D36: =C36*'1-Inputs'!$C$8 -> 0 | E36: MJ/j
A37: T4.8 | B37: Fioul de secours | C37: =(C36+'1-Inputs'!$C$35*C34)/'1-Inputs'!$C$36/'1-Inputs'!$C$34 -> 588.17337 | D37: =C37*'1-Inputs'!$C$8 -> 588.17337 | E37: L/j | F37: Deficit eventuel plus la provision de securite de 5%
A38: T4.9 | B38: Excedent de gaz non utilise | C38: =MAX(0,C33-C34) -> 58807.589 | D38: =C38*'1-Inputs'!$C$8 -> 58807.589 | E38: MJ/j | F38: Valorisable en vapeur ou en electricite. Non valorise dans ce modele
A39: T4.10 | B39: Teneur en plastique a l'equilibre energetique | E39: % | F39: Non calcule dans ce fichier
A41: T5 — SORTIES COMMERCIALISABLES
A42: T5.1 | B42: Huile vendue | C42: =C21*'1-Inputs'!$C$9/1000+C10*'1-Inputs'!$C$17*'1-Inputs'!$C$9/1000*'1-Inputs'!$C$122*'1-Inputs'!$C$123*'1-Inputs'!$C$124 -> 9414.9178 | D42: =C42*'1-Inputs'!$C$8 -> 9414.9178 | E42: T/an | F42: Production du reacteur plus l'huile issue du recyclage de la phase organique decantee (lignes T5.8c a T5.8e)
A43: T5.2 | B43: Char commercialisable | C43: =(C25+C24)*'1-Inputs'!$C$180*'1-Inputs'!$C$9/1000 -> 13672.616 | D43: =C43*'1-Inputs'!$C$8 -> 13672.616 | E43: T/an | F43: Char organique plus residu plastique, apres criblage a 85%
A44: T5.3 | B44: Ferreux recuperes | C44: =C15*'1-Inputs'!$C$20*('1-Inputs'!$C$177+(1-'1-Inputs'!$C$177)*'1-Inputs'!$C$181)*'1-Inputs'!$C$9/1000 -> 1774.8192 | D44: =C44*'1-Inputs'!$C$8 -> 1774.8192 | E44: T/an | F44: V5. Pre-tri, puis recuperation dans le char de ce qui a echappe au pre-tri (reprise du V3)
A45: T5.4 | B45: Aluminium recupere | C45: =C15*'1-Inputs'!$C$21*('1-Inputs'!$C$178+(1-'1-Inputs'!$C$178)*'1-Inputs'!$C$181)*'1-Inputs'!$C$9/1000 -> 322.5915 | D45: =C45*'1-Inputs'!$C$8 -> 322.5915 | E45: T/an | F45: V5. Idem
A46: T5.5 | B46: Autres metaux | C46: =C15*(1-'1-Inputs'!$C$20-'1-Inputs'!$C$21)*'1-Inputs'!$C$181*'1-Inputs'!$C$9/1000 -> 90.552 | D46: =C46*'1-Inputs'!$C$8 -> 90.552 | E46: T/an
A47: T5.5b | B47: Metaux non recuperes | C47: =C15*'1-Inputs'!$C$9/1000-C44-C45-C46 -> 75.8373 | D47: =C47*'1-Inputs'!$C$8 -> 75.8373 | E47: T/an | F47: V5. Vont en elimination. Etaient ignores dans le V4
A48: T5.6 | B48: Verre recupere | C48: =C16*'1-Inputs'!$C$179*'1-Inputs'!$C$9/1000 -> 1743.126 | D48: =C48*'1-Inputs'!$C$8 -> 1743.126 | E48: T/an
A49: T5.8 | B49: Eau de procede a traiter | C49: =C10*'1-Inputs'!$C$17*'1-Inputs'!$C$9/1000 -> 3622.08 | D49: =C49*'1-Inputs'!$C$8 -> 3622.08 | E49: T/an | F49: Humidite de la charge. Recoit aussi l'acide chlorhydrique dilue issu du PVC (mecanisme decrit page 3 du document UR2000-JP)
A50: T5.8b | B50: Carbonate de calcium consomme | C50: =C26*'1-Inputs'!$C$9/1000*'1-Inputs'!$C$191*'1-Inputs'!$C$190 -> 246.53712 | D50: =C50*'1-Inputs'!$C$8 -> 246.53712 | E50: T/an | F50: V6. Lie au HCl : 100/73 x exces de 25%. Etait 2,5 kg/T fixe, sous le minimum chimique
A51: T5.8c | B51: Phase organique decantee | C51: =C49*'1-Inputs'!$C$122 -> 181.104 | D51: =C51*'1-Inputs'!$C$8 -> 181.104 | E51: T/an | F51: Etape 2 : decantation. La neutralisation prealable augmente la force ionique, donc accentue le relargage salin et ameliore la separation
A52: T5.8d | B52: Phase organique recyclee en benne | C52: =C51*'1-Inputs'!$C$123 -> 0 | D52: =C52*'1-Inputs'!$C$8 -> 0 | E52: T/an | F52: Reintroduite avec la charge, absorbee par le papier et le carton. JAMAIS dans le circuit vapeur : une chaudiere recevant des goudrons se coke
A53: T5.8e | B53: Huile supplementaire issue du recyclage | C53: =C52*'1-Inputs'!$C$124 -> 0 | D53: =C53*'1-Inputs'!$C$8 -> 0 | E53: T/an | F53: Recraquee a 600 degres C. Deja incluse dans la ligne T5.1
A54: T5.9 | B54: Eau douce recuperee | C54: =(C49-C51)*'1-Inputs'!$C$117 -> 2683.9613 | D54: =C54*'1-Inputs'!$C$8 -> 2683.9613 | E54: T/an | F54: Reutilisable en boucle fermee sur site. Apres neutralisation au carbonate, il ne reste en volatil que du CO2 dissous, qui abaisse le pH a 5 ou 6 sans consequence. RESERVE RESIDUELLE : les composes organiques volatils de la pyrolyse de la cellulose (phenols, acides organiques, ammoniaque) ne sont pas retenus par le carbonate et suivent l'eau. D'ou la ligne de charbon actif
A55: T5.10 | B55: Concentrat halogene a eliminer | C55: =C49-C51-C54+C26*'1-Inputs'!$C$9/1000+C26*'1-Inputs'!$C$9/1000*56/73 -> 1011.441 | D55: =C55*'1-Inputs'!$C$8 -> 1011.441 | E55: T/an | F55: Saumure concentree. V6 : inclut le calcium apporte par la neutralisation (CaCl2 au lieu de HCl)
A56: T5.7 | B56: Residus a eliminer | C56: =C51-C52+C47+(C9+(C25+C24)*(1-'1-Inputs'!$C$180)+C16*(1-'1-Inputs'!$C$179)+C17+C18)*'1-Inputs'!$C$9/1000+(C50-C26*'1-Inputs'!$C$9/1000*'1-Inputs'!$C$191) -> 6427.5374 | D56: =C56*'1-Inputs'!$C$8 -> 6427.5374 | E56: T/an | F56: Refus, fines de criblage, verre non trie, inertes, fraction non classee (V5), metaux non recuperes (V5), phase organique decantee non recyclee V6 : plus le carbonate en exces, non reagi, soutire avec les boues
A58: T5b — CONTROLES DU BILAN MATIERE (V5)
A59: K1 | B59: Controle de composition : somme des fractions moins 100% | C59: ='1-Inputs'!$C$12+'1-Inputs'!$C$13+'1-Inputs'!$C$14+'1-Inputs'!$C$15+'1-Inputs'!$C$16+'1-Inputs'!$C$17+'1-Inputs'!$C$18-1 -> 0 | E59: - | F59: DOIT VALOIR 0
A60: K2 | B60: Entrees : dechet brut plus carbonate de calcium | C60: =C8*'1-Inputs'!$C$9/1000+C50 -> 46446.537 | D60: =C60*'1-Inputs'!$C$8 -> 46446.537 | E60: T/an
A61: K3 | B61: Sorties : produits, gaz brule, eau, concentrat, residus, recyclables, CO2 de neutralisation | C61: =C42+(C23+C27)*'1-Inputs'!$C$9/1000+C52*(1-'1-Inputs'!$C$124)+C43+C44+C45+C46+C48+C54+C55+C56+C92+C93+C94 -> 46446.537 | D61: =C61*'1-Inputs'!$C$8 -> 46446.537 | E61: T/an
A62: K4 | B62: ECART DU BILAN MATIERE | C62: =C60-C61 -> 0 | D62: =C62*'1-Inputs'!$C$8 -> 0 | E62: T/an | F62: DOIT VALOIR 0. Le V4 perdait 1 565 T/an : fraction non classee, metaux non recuperes, chlore du PVC
A64: T6 — BILAN CARBONE DE L'INSTALLATION
B65: CARBONE FOSSILE ENTRANT | F65: Le carbone fossile du site vient du plastique, et de lui seul
A66: C1 | B66: Carbone fossile entrant, exprime en CO2 | C66: =C13*'1-Inputs'!$C$93*3.667*'1-Inputs'!$C$9/1000 -> 42685.565 | D66: =C66*'1-Inputs'!$C$8 -> 42685.565 | E66: T CO2/an | F66: Masse de plastique x 85,7% de carbone x 44/12. C'est le total qui devra se retrouver dans les lignes ci-dessous
A67: C2 | B67: Carbone biogenique entrant, pour memoire | C67: =C14*'1-Inputs'!$C$94*3.667*'1-Inputs'!$C$9/1000 -> 35114.73 | D67: =C67*'1-Inputs'!$C$8 -> 35114.73 | E67: T CO2/an | F67: Issu de matiere vegetale recente. Neutre par convention internationale. N'entre dans aucun calcul
B69: EMISSIONS DIRECTES DU SITE (perimetre 1) | F69: Ce dont l'exploitant est responsable devant la reglementation
A70: C3 | B70: CO2 fossile — combustion du gaz de procede | C70: =C23*'1-Inputs'!$C$95*3.667*'1-Inputs'!$C$9/1000 -> 7690.3749 | D70: =C70*'1-Inputs'!$C$8 -> 7690.3749 | E70: T CO2/an | F70: Brule au bruleur pour chauffer le reacteur
A71: C4 | B71: CO2 fossile — fioul de secours | C71: =C37*'1-Inputs'!$C$9*'1-Inputs'!$C$99/1000 -> 520.18053 | D71: =C71*'1-Inputs'!$C$8 -> 520.18053 | E71: T CO2/an
A72: C5 | B72: TOTAL EMISSIONS DIRECTES DU SITE | C72: =C70+C71 -> 8210.5554 | D72: =C72*'1-Inputs'!$C$8 -> 8210.5554 | E72: T CO2/an | F72: Seule assiette possible d'une taxe ou d'un quota au titre du site
A73: C6 | B73: Intensite carbone directe | C73: =C72/C7 -> 0.17771765 | E73: T CO2/T traitee | F73: Grandeur a suivre : c'est elle qui determinera l'exposition a un quota si le site entre dans le champ du SEQE
B75: CARBONE SORTANT DANS LES PRODUITS (perimetre 3 aval) | F75: Emis par l'acheteur, pas par le site. Compte uniquement dans une analyse de cycle de vie
A76: C7 | B76: Carbone fossile sortant dans l'huile vendue | C76: =C42*'1-Inputs'!$C$98 -> 29186.245 | D76: =C76*'1-Inputs'!$C$8 -> 29186.245 | E76: T CO2/an
A77: C8 | B77: Carbone fossile sortant dans le char vendu | C77: =C24*'1-Inputs'!$C$180*'1-Inputs'!$C$96*3.667*'1-Inputs'!$C$9/1000 -> 3497.0286 | D77: =C77*'1-Inputs'!$C$8 -> 3497.0286 | E77: T CO2/an | F77: Part plastique du char uniquement. La part organique est biogenique
A78: C9 | B78: Carbone fossile stocke dans le char elimine | C78: =C24*(1-'1-Inputs'!$C$180)*'1-Inputs'!$C$96*3.667*'1-Inputs'!$C$9/1000 -> 617.1227 | D78: =C78*'1-Inputs'!$C$8 -> 617.1227 | E78: T CO2/an | F78: Fines de criblage envoyees en elimination. Carbone non relache
A79: C10 | B79: Controle : carbone fossile retrouve en sortie | C79: =C70+C76+C77+C78 -> 40990.771 | D79: =C79*'1-Inputs'!$C$8 -> 40990.771 | E79: T CO2/an | F79: A comparer a la ligne C1
A80: C10b | B80: Ecart de bouclage | C80: =C79/C66-1 -> -0.039704145 | E80: % | F80: Doit rester sous quelques pourcents. Un ecart plus large signale une incoherence entre la teneur en carbone des plastiques et le facteur CO2 de l'huile
B82: ENERGIE EXPORTEE | F82: Base d'une future certification RED III ou ISCC
A83: C11 | B83: Energie exportee sous forme d'huile | C83: =C42*'1-Inputs'!$C$100 -> 404841.47 | D83: =C83*'1-Inputs'!$C$8 -> 404841.47 | E83: GJ/an
A84: C12 | B84: Energie exportee sous forme de char | C84: =(C25*'1-Inputs'!$C$180*'1-Inputs'!$C$9*'1-Inputs'!$C$37+C24*'1-Inputs'!$C$180*'1-Inputs'!$C$9*'1-Inputs'!$C$101)/1000 -> 341815.41 | D84: =C84*'1-Inputs'!$C$8 -> 341815.41 | E84: GJ/an
A85: C13 | B85: Energie exportee totale | C85: =C83+C84 -> 746656.87 | D85: =C85*'1-Inputs'!$C$8 -> 746656.87 | E85: GJ/an
A86: C14 | B86: Energie exportee par tonne traitee | C86: =C85/C7 -> 16.161404 | E86: GJ/T
B88: RECETTE CARBONE
A89: C15 | B89: Reduction carbone retenue | C89: =C7*'1-Inputs'!$C$91 -> 0 | D89: =C89*'1-Inputs'!$C$8 -> 0 | E89: T CO2/an | F89: Egale a zero tant qu'aucune certification n'est obtenue. Saisie en cellule G2 de l'onglet 1-Inputs
A91: T7 — FLUX AJOUTES EN V6
A92: T7.1 | B92: Recyclables plastiques vendus (PET, PEHD) | C92: =C10*'1-Inputs'!$C$12*'1-Inputs'!$C$188*'1-Inputs'!$C$184*'1-Inputs'!$C$9/1000 -> 0 | D92: =C92*'1-Inputs'!$C$8 -> 0 | E92: T/an | F92: Zero par defaut
A93: T7.2 | B93: Carton vendu | C93: =C10*'1-Inputs'!$C$13*'1-Inputs'!$C$188*'1-Inputs'!$C$186*'1-Inputs'!$C$9/1000 -> 0 | D93: =C93*'1-Inputs'!$C$8 -> 0 | E93: T/an | F93: Zero par defaut
A94: T7.3 | B94: CO2 libere par la neutralisation | C94: =C26*'1-Inputs'!$C$9/1000*44/73 -> 86.781067 | D94: =C94*'1-Inputs'!$C$8 -> 86.781067 | E94: T/an | F94: CO2 mineral, pas fossile au sens du plastique. Environ 87 T/an
A95: T7.4 | B95: Carbonate ayant reagi | C95: =C26*'1-Inputs'!$C$9/1000*'1-Inputs'!$C$191 -> 197.2297 | D95: =C95*'1-Inputs'!$C$8 -> 197.2297 | E95: T/an | F95: Minimum stoechiometrique

Sheet 3-CAPEX
A1: INVESTISSEMENT
A4: Ref | B4: Poste | C4: Montant (EUR) | D4: % total | E4: Commentaire
A5: EQUIPEMENT
A6: 1 | B6: Machine URC-2000 | C6: ='1-Inputs'!$C$128*'1-Inputs'!$C$8 -> 50000000 | D6: =C6/$C$31 -> 0.78052131 | E6: x N
A7: 2 | B7: Installation et mise en service | C7: ='1-Inputs'!$C$129*'1-Inputs'!$C$8 -> 200000 | D7: =C7/$C$31 -> 0.0031220852 | E7: x N
A8: 3 | B8: Fret | C8: ='1-Inputs'!$C$130*'1-Inputs'!$C$8 -> 400000 | D8: =C8/$C$31 -> 0.0062441705 | E8: x N
A9: 4 | B9: Formation | C9: ='1-Inputs'!$C$131*'1-Inputs'!$C$8 -> 300000 | D9: =C9/$C$31 -> 0.0046831279 | E9: x N
A10: 5 | B10: Accessoires et pieces | C10: ='1-Inputs'!$C$132*'1-Inputs'!$C$8 -> 2000000 | D10: =C10/$C$31 -> 0.031220852 | E10: x N
A11: 6 | B11: Ligne de pre-tri | C11: ='1-Inputs'!$C$148*'1-Inputs'!$C$8*'1-Inputs'!$C$173 -> 1080000 | D11: =C11/$C$31 -> 0.01685926 | E11: x N x interrupteur pre-tri (K2)
A12: 7 | B12: Ligne de post-tri | C12: ='1-Inputs'!$C$149*'1-Inputs'!$C$8*'1-Inputs'!$C$174 -> 430000 | D12: =C12/$C$31 -> 0.0067124833 | E12: x N x interrupteur post-tri (K3)
A13: 8 | B13: ATEX et depoussierage | C13: ='1-Inputs'!$C$150*'1-Inputs'!$C$8 -> 650000 | D13: =C13/$C$31 -> 0.010146777 | E13: x N. Un systeme par reacteur
A14: 8b | B14: Cuve de neutralisation et de decantation | C14: =250000*'1-Inputs'!$C$8 -> 250000 | D14: =C14/$C$31 -> 0.0039026066 | E14: Equipement de procede, donc soumis a maintenance. Lit de pellets de calcaire puis decantation. Ordre de grandeur, a chiffrer sur devis
B15: Sous-total equipement | C15: =SUM(C5:C14) -> 55310000 | D15: =C15/$C$31 -> 0.86341267
A17: GENIE CIVIL ET ETUDES
A18: 9a | B18: Usine de traitement — surface | C18: =MAX(2600,'1-Inputs'!$C$133+'1-Inputs'!$C$134*('1-Inputs'!$C$8-1))*'1-Inputs'!$C$8 -> 3000 | E18: Plans UR2000-JP : 3 000 m2 a N=1, 14 230 m2 a N=5
A19: 9b | B19: Usine de traitement | C19: =C18*'1-Inputs'!$C$135 -> 2700000 | D19: =C19/$C$31 -> 0.042148151 | E19: 900 EUR/m2
A20: 9c | B20: Stockage dechets — surface | C20: =('1-Inputs'!$C$136+'1-Inputs'!$C$137*('1-Inputs'!$C$8-1))*'1-Inputs'!$C$8 -> 640 | E20: 640 m2 a N=1, 3 450 m2 a N=5
A21: 9d | B21: Stockage dechets | C21: =C20*'1-Inputs'!$C$138 -> 320000 | D21: =C21/$C$31 -> 0.0049953364 | E21: 500 EUR/m2
A22: 9e | B22: Stockage produits — surface | C22: =MAX(600,'1-Inputs'!$C$139+'1-Inputs'!$C$140*('1-Inputs'!$C$8-1))*'1-Inputs'!$C$8 -> 810 | E22: 810 m2 a N=1, 3 450 m2 a N=5
A23: 9f | B23: Stockage produits | C23: =C22*'1-Inputs'!$C$141 -> 405000 | D23: =C23/$C$31 -> 0.0063222226 | E23: 500 EUR/m2
A24: 9g | B24: Bureaux et locaux — surface | C24: =MAX(64,'1-Inputs'!$C$142+'1-Inputs'!$C$143*('1-Inputs'!$C$8-1))*'1-Inputs'!$C$8 -> 200 | E24: 200 m2 a N=1, 640 m2 a N=5
A25: 9h | B25: Bureaux et locaux | C25: =C24*'1-Inputs'!$C$144 -> 260000 | D25: =C25/$C$31 -> 0.0040587108 | E25: 1 300 EUR/m2
A26: 9i | B26: Surface batie totale | C26: =C18+C20+C22+C24 -> 4650 | E26: Recoupement plans : 4 650 m2 a N=1, 21 770 m2 a N=5
A27: 10 | B27: VRD, fondations, raccordements | C27: ='1-Inputs'!$C$145+'1-Inputs'!$C$146*('1-Inputs'!$C$8-1) -> 1300000 | D27: =C27/$C$31 -> 0.020293554 | E27: AJOUTE. N'etait pas distingue du batiment dans le V3
A28: 10b | B28: Sous-total genie civil | C28: =C19+C21+C23+C25+C27 -> 4985000 | D28: =C28/$C$31 -> 0.077817975 | E28: A comparer aux 5,0 MEUR forfaitaires du V3
A29: 11 | B29: Ingenierie, ICPE, MOE | C29: ='1-Inputs'!$C$151*(1+'1-Inputs'!$C$152*('1-Inputs'!$C$8-1)) -> 750000 | D29: =C29/$C$31 -> 0.01170782
A30: 12 | B30: Aleas | C30: ='1-Inputs'!$C$153*(C15+C28) -> 3014750 | D30: =C30/$C$31 -> 0.047061532 | E30: 5% de l'equipement et du genie civil
B31: TOTAL CAPEX | C31: =C15+C28+C29+C30 -> 64059750 | D31: =C31/$C$31 -> 1
B33: Emprise fonciere indicative | C33: =C26*1.28 -> 5952 | E33: Ratio emprise sur surface batie tire des plans : 28 900 / 21 770 a N=5, 5 265 / 4 650 a N=1
B34: CAPEX par tonne annuelle | C34: =C31/'2-Production'!D7 -> 1386.5747
B35: Dette | C35: =C31*'1-Inputs'!$C$156 -> 44841825
B36: Fonds propres | C36: =C31-C35 -> 19217925
B37: Amortissement annuel | C37: =C31/'1-Inputs'!$C$160 -> 4270650

Sheet 4-PL
A1: COMPTE DE RESULTAT ET TRESORERIE — 15 ANS
A2: Toutes les lignes suivent le nombre d'unites saisi a l'onglet 1-Inputs.
C4: Annee 1 | D4: Annee 2 | E4: Annee 3 | F4: Annee 4 | G4: Annee 5 | H4: Annee 6 | I4: Annee 7 | J4: Annee 8 | K4: Annee 9 | L4: Annee 10 | M4: Annee 11 | N4: Annee 12 | O4: Annee 13 | P4: Annee 14 | Q4: Annee 15
B5: Taux de charge | C5: =IF(1=1,'1-Inputs'!$C$162,IF(1=2,'1-Inputs'!$C$163,1)) -> 0.7 | D5: =IF(2=1,'1-Inputs'!$C$162,IF(2=2,'1-Inputs'!$C$163,1)) -> 0.85 | E5: =IF(3=1,'1-Inputs'!$C$162,IF(3=2,'1-Inputs'!$C$163,1)) -> 1 | F5: =IF(4=1,'1-Inputs'!$C$162,IF(4=2,'1-Inputs'!$C$163,1)) -> 1 | G5: =IF(5=1,'1-Inputs'!$C$162,IF(5=2,'1-Inputs'!$C$163,1)) -> 1 | H5: =IF(6=1,'1-Inputs'!$C$162,IF(6=2,'1-Inputs'!$C$163,1)) -> 1 | I5: =IF(7=1,'1-Inputs'!$C$162,IF(7=2,'1-Inputs'!$C$163,1)) -> 1 | J5: =IF(8=1,'1-Inputs'!$C$162,IF(8=2,'1-Inputs'!$C$163,1)) -> 1 | K5: =IF(9=1,'1-Inputs'!$C$162,IF(9=2,'1-Inputs'!$C$163,1)) -> 1 | L5: =IF(10=1,'1-Inputs'!$C$162,IF(10=2,'1-Inputs'!$C$163,1)) -> 1 | M5: =IF(11=1,'1-Inputs'!$C$162,IF(11=2,'1-Inputs'!$C$163,1)) -> 1 | N5: =IF(12=1,'1-Inputs'!$C$162,IF(12=2,'1-Inputs'!$C$163,1)) -> 1 | O5: =IF(13=1,'1-Inputs'!$C$162,IF(13=2,'1-Inputs'!$C$163,1)) -> 1 | P5: =IF(14=1,'1-Inputs'!$C$162,IF(14=2,'1-Inputs'!$C$163,1)) -> 1 | Q5: =IF(15=1,'1-Inputs'!$C$162,IF(15=2,'1-Inputs'!$C$163,1)) -> 1
B6: Tonnage traite (T) | C6: ='2-Production'!D7*C5 -> 32340 | D6: ='2-Production'!D7*D5 -> 39270 | E6: ='2-Production'!D7*E5 -> 46200 | F6: ='2-Production'!D7*F5 -> 46200 | G6: ='2-Production'!D7*G5 -> 46200 | H6: ='2-Production'!D7*H5 -> 46200 | I6: ='2-Production'!D7*I5 -> 46200 | J6: ='2-Production'!D7*J5 -> 46200 | K6: ='2-Production'!D7*K5 -> 46200 | L6: ='2-Production'!D7*L5 -> 46200 | M6: ='2-Production'!D7*M5 -> 46200 | N6: ='2-Production'!D7*N5 -> 46200 | O6: ='2-Production'!D7*O5 -> 46200 | P6: ='2-Production'!D7*P5 -> 46200 | Q6: ='2-Production'!D7*Q5 -> 46200
A8: RECETTES
B9: Gate fees | C9: =C6*'1-Inputs'!$C$65*(1+'1-Inputs'!$C$161)^0 -> 3557400 | D9: =D6*'1-Inputs'!$C$65*(1+'1-Inputs'!$C$161)^1 -> 4406094 | E9: =E6*'1-Inputs'!$C$65*(1+'1-Inputs'!$C$161)^2 -> 5287312.8 | F9: =F6*'1-Inputs'!$C$65*(1+'1-Inputs'!$C$161)^3 -> 5393059.1 | G9: =G6*'1-Inputs'!$C$65*(1+'1-Inputs'!$C$161)^4 -> 5500920.2 | H9: =H6*'1-Inputs'!$C$65*(1+'1-Inputs'!$C$161)^5 -> 5610938.6 | I9: =I6*'1-Inputs'!$C$65*(1+'1-Inputs'!$C$161)^6 -> 5723157.4 | J9: =J6*'1-Inputs'!$C$65*(1+'1-Inputs'!$C$161)^7 -> 5837620.6 | K9: =K6*'1-Inputs'!$C$65*(1+'1-Inputs'!$C$161)^8 -> 5954373 | L9: =L6*'1-Inputs'!$C$65*(1+'1-Inputs'!$C$161)^9 -> 6073460.4 | M9: =M6*'1-Inputs'!$C$65*(1+'1-Inputs'!$C$161)^10 -> 6194929.6 | N9: =N6*'1-Inputs'!$C$65*(1+'1-Inputs'!$C$161)^11 -> 6318828.2 | O9: =O6*'1-Inputs'!$C$65*(1+'1-Inputs'!$C$161)^12 -> 6445204.8 | P9: =P6*'1-Inputs'!$C$65*(1+'1-Inputs'!$C$161)^13 -> 6574108.9 | Q9: =Q6*'1-Inputs'!$C$65*(1+'1-Inputs'!$C$161)^14 -> 6705591.1
B10: Huile | C10: ='2-Production'!D42*C5*'1-Inputs'!$C$79*(1+'1-Inputs'!$C$161)^0 -> 4224473.6 | D10: ='2-Production'!D42*D5*'1-Inputs'!$C$79*(1+'1-Inputs'!$C$161)^1 -> 5232312.3 | E10: ='2-Production'!D42*E5*'1-Inputs'!$C$79*(1+'1-Inputs'!$C$161)^2 -> 6278774.8 | F10: ='2-Production'!D42*F5*'1-Inputs'!$C$79*(1+'1-Inputs'!$C$161)^3 -> 6404350.3 | G10: ='2-Production'!D42*G5*'1-Inputs'!$C$79*(1+'1-Inputs'!$C$161)^4 -> 6532437.3 | H10: ='2-Production'!D42*H5*'1-Inputs'!$C$79*(1+'1-Inputs'!$C$161)^5 -> 6663086 | I10: ='2-Production'!D42*I5*'1-Inputs'!$C$79*(1+'1-Inputs'!$C$161)^6 -> 6796347.8 | J10: ='2-Production'!D42*J5*'1-Inputs'!$C$79*(1+'1-Inputs'!$C$161)^7 -> 6932274.7 | K10: ='2-Production'!D42*K5*'1-Inputs'!$C$79*(1+'1-Inputs'!$C$161)^8 -> 7070920.2 | L10: ='2-Production'!D42*L5*'1-Inputs'!$C$79*(1+'1-Inputs'!$C$161)^9 -> 7212338.6 | M10: ='2-Production'!D42*M5*'1-Inputs'!$C$79*(1+'1-Inputs'!$C$161)^10 -> 7356585.4 | N10: ='2-Production'!D42*N5*'1-Inputs'!$C$79*(1+'1-Inputs'!$C$161)^11 -> 7503717.1 | O10: ='2-Production'!D42*O5*'1-Inputs'!$C$79*(1+'1-Inputs'!$C$161)^12 -> 7653791.4 | P10: ='2-Production'!D42*P5*'1-Inputs'!$C$79*(1+'1-Inputs'!$C$161)^13 -> 7806867.3 | Q10: ='2-Production'!D42*Q5*'1-Inputs'!$C$79*(1+'1-Inputs'!$C$161)^14 -> 7963004.6
B11: Char | C11: ='2-Production'!D43*C5*'1-Inputs'!$C$80*(1+'1-Inputs'!$C$161)^0 -> 957083.14 | D11: ='2-Production'!D43*D5*'1-Inputs'!$C$80*(1+'1-Inputs'!$C$161)^1 -> 1185415.8 | E11: ='2-Production'!D43*E5*'1-Inputs'!$C$80*(1+'1-Inputs'!$C$161)^2 -> 1422499 | F11: ='2-Production'!D43*F5*'1-Inputs'!$C$80*(1+'1-Inputs'!$C$161)^3 -> 1450949 | G11: ='2-Production'!D43*G5*'1-Inputs'!$C$80*(1+'1-Inputs'!$C$161)^4 -> 1479968 | H11: ='2-Production'!D43*H5*'1-Inputs'!$C$80*(1+'1-Inputs'!$C$161)^5 -> 1509567.3 | I11: ='2-Production'!D43*I5*'1-Inputs'!$C$80*(1+'1-Inputs'!$C$161)^6 -> 1539758.7 | J11: ='2-Production'!D43*J5*'1-Inputs'!$C$80*(1+'1-Inputs'!$C$161)^7 -> 1570553.8 | K11: ='2-Production'!D43*K5*'1-Inputs'!$C$80*(1+'1-Inputs'!$C$161)^8 -> 1601964.9 | L11: ='2-Production'!D43*L5*'1-Inputs'!$C$80*(1+'1-Inputs'!$C$161)^9 -> 1634004.2 | M11: ='2-Production'!D43*M5*'1-Inputs'!$C$80*(1+'1-Inputs'!$C$161)^10 -> 1666684.3 | N11: ='2-Production'!D43*N5*'1-Inputs'!$C$80*(1+'1-Inputs'!$C$161)^11 -> 1700018 | O11: ='2-Production'!D43*O5*'1-Inputs'!$C$80*(1+'1-Inputs'!$C$161)^12 -> 1734018.3 | P11: ='2-Production'!D43*P5*'1-Inputs'!$C$80*(1+'1-Inputs'!$C$161)^13 -> 1768698.7 | Q11: ='2-Production'!D43*Q5*'1-Inputs'!$C$80*(1+'1-Inputs'!$C$161)^14 -> 1804072.7
B12: Metaux | C12: =('2-Production'!D44*'1-Inputs'!$C$81+'2-Production'!D45*'1-Inputs'!$C$82+'2-Production'!D46*'1-Inputs'!$C$83)*C5*(1+'1-Inputs'!$C$161)^0 -> 658426.23 | D12: =('2-Production'!D44*'1-Inputs'!$C$81+'2-Production'!D45*'1-Inputs'!$C$82+'2-Production'!D46*'1-Inputs'!$C$83)*D5*(1+'1-Inputs'!$C$161)^1 -> 815507.92 | E12: =('2-Production'!D44*'1-Inputs'!$C$81+'2-Production'!D45*'1-Inputs'!$C$82+'2-Production'!D46*'1-Inputs'!$C$83)*E5*(1+'1-Inputs'!$C$161)^2 -> 978609.5 | F12: =('2-Production'!D44*'1-Inputs'!$C$81+'2-Production'!D45*'1-Inputs'!$C$82+'2-Production'!D46*'1-Inputs'!$C$83)*F5*(1+'1-Inputs'!$C$161)^3 -> 998181.69 | G12: =('2-Production'!D44*'1-Inputs'!$C$81+'2-Production'!D45*'1-Inputs'!$C$82+'2-Production'!D46*'1-Inputs'!$C$83)*G5*(1+'1-Inputs'!$C$161)^4 -> 1018145.3 | H12: =('2-Production'!D44*'1-Inputs'!$C$81+'2-Production'!D45*'1-Inputs'!$C$82+'2-Production'!D46*'1-Inputs'!$C$83)*H5*(1+'1-Inputs'!$C$161)^5 -> 1038508.2 | I12: =('2-Production'!D44*'1-Inputs'!$C$81+'2-Production'!D45*'1-Inputs'!$C$82+'2-Production'!D46*'1-Inputs'!$C$83)*I5*(1+'1-Inputs'!$C$161)^6 -> 1059278.4 | J12: =('2-Production'!D44*'1-Inputs'!$C$81+'2-Production'!D45*'1-Inputs'!$C$82+'2-Production'!D46*'1-Inputs'!$C$83)*J5*(1+'1-Inputs'!$C$161)^7 -> 1080464 | K12: =('2-Production'!D44*'1-Inputs'!$C$81+'2-Production'!D45*'1-Inputs'!$C$82+'2-Production'!D46*'1-Inputs'!$C$83)*K5*(1+'1-Inputs'!$C$161)^8 -> 1102073.2 | L12: =('2-Production'!D44*'1-Inputs'!$C$81+'2-Production'!D45*'1-Inputs'!$C$82+'2-Production'!D46*'1-Inputs'!$C$83)*L5*(1+'1-Inputs'!$C$161)^9 -> 1124114.7 | M12: =('2-Production'!D44*'1-Inputs'!$C$81+'2-Production'!D45*'1-Inputs'!$C$82+'2-Production'!D46*'1-Inputs'!$C$83)*M5*(1+'1-Inputs'!$C$161)^10 -> 1146597 | N12: =('2-Production'!D44*'1-Inputs'!$C$81+'2-Production'!D45*'1-Inputs'!$C$82+'2-Production'!D46*'1-Inputs'!$C$83)*N5*(1+'1-Inputs'!$C$161)^11 -> 1169528.9 | O12: =('2-Production'!D44*'1-Inputs'!$C$81+'2-Production'!D45*'1-Inputs'!$C$82+'2-Production'!D46*'1-Inputs'!$C$83)*O5*(1+'1-Inputs'!$C$161)^12 -> 1192919.5 | P12: =('2-Production'!D44*'1-Inputs'!$C$81+'2-Production'!D45*'1-Inputs'!$C$82+'2-Production'!D46*'1-Inputs'!$C$83)*P5*(1+'1-Inputs'!$C$161)^13 -> 1216777.9 | Q12: =('2-Production'!D44*'1-Inputs'!$C$81+'2-Production'!D45*'1-Inputs'!$C$82+'2-Production'!D46*'1-Inputs'!$C$83)*Q5*(1+'1-Inputs'!$C$161)^14 -> 1241113.5
B13: Verre et recyclables du pre-tri | C13: =('2-Production'!D48*'1-Inputs'!$C$84+'2-Production'!D92*'1-Inputs'!$C$185+'2-Production'!D93*'1-Inputs'!$C$187)*C5*(1+'1-Inputs'!$C$161)^0 -> 36605.646 | D13: =('2-Production'!D48*'1-Inputs'!$C$84+'2-Production'!D92*'1-Inputs'!$C$185+'2-Production'!D93*'1-Inputs'!$C$187)*D5*(1+'1-Inputs'!$C$161)^1 -> 45338.707 | E13: =('2-Production'!D48*'1-Inputs'!$C$84+'2-Production'!D92*'1-Inputs'!$C$185+'2-Production'!D93*'1-Inputs'!$C$187)*E5*(1+'1-Inputs'!$C$161)^2 -> 54406.449 | F13: =('2-Production'!D48*'1-Inputs'!$C$84+'2-Production'!D92*'1-Inputs'!$C$185+'2-Production'!D93*'1-Inputs'!$C$187)*F5*(1+'1-Inputs'!$C$161)^3 -> 55494.578 | G13: =('2-Production'!D48*'1-Inputs'!$C$84+'2-Production'!D92*'1-Inputs'!$C$185+'2-Production'!D93*'1-Inputs'!$C$187)*G5*(1+'1-Inputs'!$C$161)^4 -> 56604.469 | H13: =('2-Production'!D48*'1-Inputs'!$C$84+'2-Production'!D92*'1-Inputs'!$C$185+'2-Production'!D93*'1-Inputs'!$C$187)*H5*(1+'1-Inputs'!$C$161)^5 -> 57736.559 | I13: =('2-Production'!D48*'1-Inputs'!$C$84+'2-Production'!D92*'1-Inputs'!$C$185+'2-Production'!D93*'1-Inputs'!$C$187)*I5*(1+'1-Inputs'!$C$161)^6 -> 58891.29 | J13: =('2-Production'!D48*'1-Inputs'!$C$84+'2-Production'!D92*'1-Inputs'!$C$185+'2-Production'!D93*'1-Inputs'!$C$187)*J5*(1+'1-Inputs'!$C$161)^7 -> 60069.116 | K13: =('2-Production'!D48*'1-Inputs'!$C$84+'2-Production'!D92*'1-Inputs'!$C$185+'2-Production'!D93*'1-Inputs'!$C$187)*K5*(1+'1-Inputs'!$C$161)^8 -> 61270.498 | L13: =('2-Production'!D48*'1-Inputs'!$C$84+'2-Production'!D92*'1-Inputs'!$C$185+'2-Production'!D93*'1-Inputs'!$C$187)*L5*(1+'1-Inputs'!$C$161)^9 -> 62495.908 | M13: =('2-Production'!D48*'1-Inputs'!$C$84+'2-Production'!D92*'1-Inputs'!$C$185+'2-Production'!D93*'1-Inputs'!$C$187)*M5*(1+'1-Inputs'!$C$161)^10 -> 63745.826 | N13: =('2-Production'!D48*'1-Inputs'!$C$84+'2-Production'!D92*'1-Inputs'!$C$185+'2-Production'!D93*'1-Inputs'!$C$187)*N5*(1+'1-Inputs'!$C$161)^11 -> 65020.743 | O13: =('2-Production'!D48*'1-Inputs'!$C$84+'2-Production'!D92*'1-Inputs'!$C$185+'2-Production'!D93*'1-Inputs'!$C$187)*O5*(1+'1-Inputs'!$C$161)^12 -> 66321.157 | P13: =('2-Production'!D48*'1-Inputs'!$C$84+'2-Production'!D92*'1-Inputs'!$C$185+'2-Production'!D93*'1-Inputs'!$C$187)*P5*(1+'1-Inputs'!$C$161)^13 -> 67647.581 | Q13: =('2-Production'!D48*'1-Inputs'!$C$84+'2-Production'!D92*'1-Inputs'!$C$185+'2-Production'!D93*'1-Inputs'!$C$187)*Q5*(1+'1-Inputs'!$C$161)^14 -> 69000.532
B14: Credits carbone | C14: ='2-Production'!D89*C5*'1-Inputs'!$C$92*'1-Inputs'!$C$90*(1+'1-Inputs'!$C$161)^0 -> 0 | D14: ='2-Production'!D89*D5*'1-Inputs'!$C$92*'1-Inputs'!$C$90*(1+'1-Inputs'!$C$161)^1 -> 0 | E14: ='2-Production'!D89*E5*'1-Inputs'!$C$92*'1-Inputs'!$C$90*(1+'1-Inputs'!$C$161)^2 -> 0 | F14: ='2-Production'!D89*F5*'1-Inputs'!$C$92*'1-Inputs'!$C$90*(1+'1-Inputs'!$C$161)^3 -> 0 | G14: ='2-Production'!D89*G5*'1-Inputs'!$C$92*'1-Inputs'!$C$90*(1+'1-Inputs'!$C$161)^4 -> 0 | H14: ='2-Production'!D89*H5*'1-Inputs'!$C$92*'1-Inputs'!$C$90*(1+'1-Inputs'!$C$161)^5 -> 0 | I14: ='2-Production'!D89*I5*'1-Inputs'!$C$92*'1-Inputs'!$C$90*(1+'1-Inputs'!$C$161)^6 -> 0 | J14: ='2-Production'!D89*J5*'1-Inputs'!$C$92*'1-Inputs'!$C$90*(1+'1-Inputs'!$C$161)^7 -> 0 | K14: ='2-Production'!D89*K5*'1-Inputs'!$C$92*'1-Inputs'!$C$90*(1+'1-Inputs'!$C$161)^8 -> 0 | L14: ='2-Production'!D89*L5*'1-Inputs'!$C$92*'1-Inputs'!$C$90*(1+'1-Inputs'!$C$161)^9 -> 0 | M14: ='2-Production'!D89*M5*'1-Inputs'!$C$92*'1-Inputs'!$C$90*(1+'1-Inputs'!$C$161)^10 -> 0 | N14: ='2-Production'!D89*N5*'1-Inputs'!$C$92*'1-Inputs'!$C$90*(1+'1-Inputs'!$C$161)^11 -> 0 | O14: ='2-Production'!D89*O5*'1-Inputs'!$C$92*'1-Inputs'!$C$90*(1+'1-Inputs'!$C$161)^12 -> 0 | P14: ='2-Production'!D89*P5*'1-Inputs'!$C$92*'1-Inputs'!$C$90*(1+'1-Inputs'!$C$161)^13 -> 0 | Q14: ='2-Production'!D89*Q5*'1-Inputs'!$C$92*'1-Inputs'!$C$90*(1+'1-Inputs'!$C$161)^14 -> 0
B15: TOTAL RECETTES | C15: =SUM(C9:C14) -> 9433988.6 | D15: =SUM(D9:D14) -> 11684669 | E15: =SUM(E9:E14) -> 14021603 | F15: =SUM(F9:F14) -> 14302035 | G15: =SUM(G9:G14) -> 14588075 | H15: =SUM(H9:H14) -> 14879837 | I15: =SUM(I9:I14) -> 15177434 | J15: =SUM(J9:J14) -> 15480982 | ... Q15: =SUM(Q9:Q14) -> 17782782
A17: CHARGES
B18: Personnel | C18: =('1-Inputs'!$C$104+'1-Inputs'!$C$105*('1-Inputs'!$C$8-1)+'1-Inputs'!$C$106*'1-Inputs'!$C$8)*'1-Inputs'!$C$107*C5*(1+'1-Inputs'!$C$161)^0 -> 862400 | D18: =('1-Inputs'!$C$104+'1-Inputs'!$C$105*('1-Inputs'!$C$8-1)+'1-Inputs'!$C$106*'1-Inputs'!$C$8)*'1-Inputs'!$C$107*D5*(1+'1-Inputs'!$C$161)^1 -> 1068144 | E18: =('1-Inputs'!$C$104+'1-Inputs'!$C$105*('1-Inputs'!$C$8-1)+'1-Inputs'!$C$106*'1-Inputs'!$C$8)*'1-Inputs'!$C$107*E5*(1+'1-Inputs'!$C$161)^2 -> 1281772.8 | F18: =('1-Inputs'!$C$104+'1-Inputs'!$C$105*('1-Inputs'!$C$8-1)+'1-Inputs'!$C$106*'1-Inputs'!$C$8)*'1-Inputs'!$C$107*F5*(1+'1-Inputs'!$C$161)^3 -> 1307408.3 | G18: =('1-Inputs'!$C$104+'1-Inputs'!$C$105*('1-Inputs'!$C$8-1)+'1-Inputs'!$C$106*'1-Inputs'!$C$8)*'1-Inputs'!$C$107*G5*(1+'1-Inputs'!$C$161)^4 -> 1333556.4 | H18: =('1-Inputs'!$C$104+'1-Inputs'!$C$105*('1-Inputs'!$C$8-1)+'1-Inputs'!$C$106*'1-Inputs'!$C$8)*'1-Inputs'!$C$107*H5*(1+'1-Inputs'!$C$161)^5 -> 1360227.5 | I18: =('1-Inputs'!$C$104+'1-Inputs'!$C$105*('1-Inputs'!$C$8-1)+'1-Inputs'!$C$106*'1-Inputs'!$C$8)*'1-Inputs'!$C$107*I5*(1+'1-Inputs'!$C$161)^6 -> 1387432.1 | J18: =('1-Inputs'!$C$104+'1-Inputs'!$C$105*('1-Inputs'!$C$8-1)+'1-Inputs'!$C$106*'1-Inputs'!$C$8)*'1-Inputs'!$C$107*J5*(1+'1-Inputs'!$C$161)^7 -> 1415180.7 | K18: =('1-Inputs'!$C$104+'1-Inputs'!$C$105*('1-Inputs'!$C$8-1)+'1-Inputs'!$C$106*'1-Inputs'!$C$8)*'1-Inputs'!$C$107*K5*(1+'1-Inputs'!$C$161)^8 -> 1443484.4 | L18: =('1-Inputs'!$C$104+'1-Inputs'!$C$105*('1-Inputs'!$C$8-1)+'1-Inputs'!$C$106*'1-Inputs'!$C$8)*'1-Inputs'!$C$107*L5*(1+'1-Inputs'!$C$161)^9 -> 1472354 | M18: =('1-Inputs'!$C$104+'1-Inputs'!$C$105*('1-Inputs'!$C$8-1)+'1-Inputs'!$C$106*'1-Inputs'!$C$8)*'1-Inputs'!$C$107*M5*(1+'1-Inputs'!$C$161)^10 -> 1501801.1 | N18: =('1-Inputs'!$C$104+'1-Inputs'!$C$105*('1-Inputs'!$C$8-1)+'1-Inputs'!$C$106*'1-Inputs'!$C$8)*'1-Inputs'!$C$107*N5*(1+'1-Inputs'!$C$161)^11 -> 1531837.1 | O18: =('1-Inputs'!$C$104+'1-Inputs'!$C$105*('1-Inputs'!$C$8-1)+'1-Inputs'!$C$106*'1-Inputs'!$C$8)*'1-Inputs'!$C$107*O5*(1+'1-Inputs'!$C$161)^12 -> 1562473.9 | P18: =('1-Inputs'!$C$104+'1-Inputs'!$C$105*('1-Inputs'!$C$8-1)+'1-Inputs'!$C$106*'1-Inputs'!$C$8)*'1-Inputs'!$C$107*P5*(1+'1-Inputs'!$C$161)^13 -> 1593723.4 | Q18: =('1-Inputs'!$C$104+'1-Inputs'!$C$105*('1-Inputs'!$C$8-1)+'1-Inputs'!$C$106*'1-Inputs'!$C$8)*'1-Inputs'!$C$107*Q5*(1+'1-Inputs'!$C$161)^14 -> 1625597.8
B19: Taux de maintenance applique | C19: =IF(1<='1-Inputs'!$C$110,'1-Inputs'!$C$108,IF(1>='1-Inputs'!$C$111,'1-Inputs'!$C$109,'1-Inputs'!$C$108+('1-Inputs'!$C$109-'1-Inputs'!$C$108)*(1-'1-Inputs'!$C$110)/('1-Inputs'!$C$111-'1-Inputs'!$C$110))) -> 0.01 | D19: =IF(2<='1-Inputs'!$C$110,'1-Inputs'!$C$108,IF(2>='1-Inputs'!$C$111,'1-Inputs'!$C$109,'1-Inputs'!$C$108+('1-Inputs'!$C$109-'1-Inputs'!$C$108)*(2-'1-Inputs'!$C$110)/('1-Inputs'!$C$111-'1-Inputs'!$C$110))) -> 0.01 | E19: =IF(3<='1-Inputs'!$C$110,'1-Inputs'!$C$108,IF(3>='1-Inputs'!$C$111,'1-Inputs'!$C$109,'1-Inputs'!$C$108+('1-Inputs'!$C$109-'1-Inputs'!$C$108)*(3-'1-Inputs'!$C$110)/('1-Inputs'!$C$111-'1-Inputs'!$C$110))) -> 0.01 | F19: =IF(4<='1-Inputs'!$C$110,'1-Inputs'!$C$108,IF(4>='1-Inputs'!$C$111,'1-Inputs'!$C$109,'1-Inputs'!$C$108+('1-Inputs'!$C$109-'1-Inputs'!$C$108)*(4-'1-Inputs'!$C$110)/('1-Inputs'!$C$111-'1-Inputs'!$C$110))) -> 0.01 | G19: =IF(5<='1-Inputs'!$C$110,'1-Inputs'!$C$108,IF(5>='1-Inputs'!$C$111,'1-Inputs'!$C$109,'1-Inputs'!$C$108+('1-Inputs'!$C$109-'1-Inputs'!$C$108)*(5-'1-Inputs'!$C$110)/('1-Inputs'!$C$111-'1-Inputs'!$C$110))) -> 0.015 | H19: =IF(6<='1-Inputs'!$C$110,'1-Inputs'!$C$108,IF(6>='1-Inputs'!$C$111,'1-Inputs'!$C$109,'1-Inputs'!$C$108+('1-Inputs'!$C$109-'1-Inputs'!$C$108)*(6-'1-Inputs'!$C$110)/('1-Inputs'!$C$111-'1-Inputs'!$C$110))) -> 0.02 | I19: =IF(7<='1-Inputs'!$C$110,'1-Inputs'!$C$108,IF(7>='1-Inputs'!$C$111,'1-Inputs'!$C$109,'1-Inputs'!$C$108+('1-Inputs'!$C$109-'1-Inputs'!$C$108)*(7-'1-Inputs'!$C$110)/('1-Inputs'!$C$111-'1-Inputs'!$C$110))) -> 0.025 | J19: =IF(8<='1-Inputs'!$C$110,'1-Inputs'!$C$108,IF(8>='1-Inputs'!$C$111,'1-Inputs'!$C$109,'1-Inputs'!$C$108+('1-Inputs'!$C$109-'1-Inputs'!$C$108)*(8-'1-Inputs'!$C$110)/('1-Inputs'!$C$111-'1-Inputs'!$C$110))) -> 0.03 | K19: =IF(9<='1-Inputs'!$C$110,'1-Inputs'!$C$108,IF(9>='1-Inputs'!$C$111,'1-Inputs'!$C$109,'1-Inputs'!$C$108+('1-Inputs'!$C$109-'1-Inputs'!$C$108)*(9-'1-Inputs'!$C$110)/('1-Inputs'!$C$111-'1-Inputs'!$C$110))) -> 0.035 | L19: =IF(10<='1-Inputs'!$C$110,'1-Inputs'!$C$108,IF(10>='1-Inputs'!$C$111,'1-Inputs'!$C$109,'1-Inputs'!$C$108+('1-Inputs'!$C$109-'1-Inputs'!$C$108)*(10-'1-Inputs'!$C$110)/('1-Inputs'!$C$111-'1-Inputs'!$C$110))) -> 0.04 | M19: =IF(11<='1-Inputs'!$C$110,'1-Inputs'!$C$108,IF(11>='1-Inputs'!$C$111,'1-Inputs'!$C$109,'1-Inputs'!$C$108+('1-Inputs'!$C$109-'1-Inputs'!$C$108)*(11-'1-Inputs'!$C$110)/('1-Inputs'!$C$111-'1-Inputs'!$C$110))) -> 0.04 | N19: =IF(12<='1-Inputs'!$C$110,'1-Inputs'!$C$108,IF(12>='1-Inputs'!$C$111,'1-Inputs'!$C$109,'1-Inputs'!$C$108+('1-Inputs'!$C$109-'1-Inputs'!$C$108)*(12-'1-Inputs'!$C$110)/('1-Inputs'!$C$111-'1-Inputs'!$C$110))) -> 0.04 | O19: =IF(13<='1-Inputs'!$C$110,'1-Inputs'!$C$108,IF(13>='1-Inputs'!$C$111,'1-Inputs'!$C$109,'1-Inputs'!$C$108+('1-Inputs'!$C$109-'1-Inputs'!$C$108)*(13-'1-Inputs'!$C$110)/('1-Inputs'!$C$111-'1-Inputs'!$C$110))) -> 0.04 | P19: =IF(14<='1-Inputs'!$C$110,'1-Inputs'!$C$108,IF(14>='1-Inputs'!$C$111,'1-Inputs'!$C$109,'1-Inputs'!$C$108+('1-Inputs'!$C$109-'1-Inputs'!$C$108)*(14-'1-Inputs'!$C$110)/('1-Inputs'!$C$111-'1-Inputs'!$C$110))) -> 0.04 | Q19: =IF(15<='1-Inputs'!$C$110,'1-Inputs'!$C$108,IF(15>='1-Inputs'!$C$111,'1-Inputs'!$C$109,'1-Inputs'!$C$108+('1-Inputs'!$C$109-'1-Inputs'!$C$108)*(15-'1-Inputs'!$C$110)/('1-Inputs'!$C$111-'1-Inputs'!$C$110))) -> 0.04
B20: Maintenance | C20: =C19*'3-CAPEX'!$C$15*C5*(1+'1-Inputs'!$C$161)^0 -> 387170 | D20: =D19*'3-CAPEX'!$C$15*D5*(1+'1-Inputs'!$C$161)^1 -> 479537.7 | E20: =E19*'3-CAPEX'!$C$15*E5*(1+'1-Inputs'!$C$161)^2 -> 575445.24 | F20: =F19*'3-CAPEX'!$C$15*F5*(1+'1-Inputs'!$C$161)^3 -> 586954.14 | G20: =G19*'3-CAPEX'!$C$15*G5*(1+'1-Inputs'!$C$161)^4 -> 898039.84 | H20: =H19*'3-CAPEX'!$C$15*H5*(1+'1-Inputs'!$C$161)^5 -> 1221334.2 | I20: =I19*'3-CAPEX'!$C$15*I5*(1+'1-Inputs'!$C$161)^6 -> 1557201.1 | J20: =J19*'3-CAPEX'!$C$15*J5*(1+'1-Inputs'!$C$161)^7 -> 1906014.1 | K20: =K19*'3-CAPEX'!$C$15*K5*(1+'1-Inputs'!$C$161)^8 -> 2268156.8 | L20: =L19*'3-CAPEX'!$C$15*L5*(1+'1-Inputs'!$C$161)^9 -> 2644022.8 | M20: =M19*'3-CAPEX'!$C$15*M5*(1+'1-Inputs'!$C$161)^10 -> 2696903.3 | N20: =N19*'3-CAPEX'!$C$15*N5*(1+'1-Inputs'!$C$161)^11 -> 2750841.3 | O20: =O19*'3-CAPEX'!$C$15*O5*(1+'1-Inputs'!$C$161)^12 -> 2805858.1 | P20: =P19*'3-CAPEX'!$C$15*P5*(1+'1-Inputs'!$C$161)^13 -> 2861975.3 | Q20: =Q19*'3-CAPEX'!$C$15*Q5*(1+'1-Inputs'!$C$161)^14 -> 2919214.8
B21: Electricite | C21: ='1-Inputs'!$C$113*'1-Inputs'!$C$8*'1-Inputs'!$C$9*'1-Inputs'!$C$87*C5*(1+'1-Inputs'!$C$161)^0 -> 103950 | D21: ='1-Inputs'!$C$113*'1-Inputs'!$C$8*'1-Inputs'!$C$9*'1-Inputs'!$C$87*D5*(1+'1-Inputs'!$C$161)^1 -> 128749.5 | E21: ='1-Inputs'!$C$113*'1-Inputs'!$C$8*'1-Inputs'!$C$9*'1-Inputs'!$C$87*E5*(1+'1-Inputs'!$C$161)^2 -> 154499.4 | F21: ='1-Inputs'!$C$113*'1-Inputs'!$C$8*'1-Inputs'!$C$9*'1-Inputs'!$C$87*F5*(1+'1-Inputs'!$C$161)^3 -> 157589.39 | G21: ='1-Inputs'!$C$113*'1-Inputs'!$C$8*'1-Inputs'!$C$9*'1-Inputs'!$C$87*G5*(1+'1-Inputs'!$C$161)^4 -> 160741.18 | H21: ='1-Inputs'!$C$113*'1-Inputs'!$C$8*'1-Inputs'!$C$9*'1-Inputs'!$C$87*H5*(1+'1-Inputs'!$C$161)^5 -> 163956 | I21: ='1-Inputs'!$C$113*'1-Inputs'!$C$8*'1-Inputs'!$C$9*'1-Inputs'!$C$87*I5*(1+'1-Inputs'!$C$161)^6 -> 167235.12 | J21: ='1-Inputs'!$C$113*'1-Inputs'!$C$8*'1-Inputs'!$C$9*'1-Inputs'!$C$87*J5*(1+'1-Inputs'!$C$161)^7 -> 170579.82 | K21: ='1-Inputs'!$C$113*'1-Inputs'!$C$8*'1-Inputs'!$C$9*'1-Inputs'!$C$87*K5*(1+'1-Inputs'!$C$161)^8 -> 173991.42 | L21: ='1-Inputs'!$C$113*'1-Inputs'!$C$8*'1-Inputs'!$C$9*'1-Inputs'!$C$87*L5*(1+'1-Inputs'!$C$161)^9 -> 177471.25 | M21: ='1-Inputs'!$C$113*'1-Inputs'!$C$8*'1-Inputs'!$C$9*'1-Inputs'!$C$87*M5*(1+'1-Inputs'!$C$161)^10 -> 181020.67 | N21: ='1-Inputs'!$C$113*'1-Inputs'!$C$8*'1-Inputs'!$C$9*'1-Inputs'!$C$87*N5*(1+'1-Inputs'!$C$161)^11 -> 184641.08 | O21: ='1-Inputs'!$C$113*'1-Inputs'!$C$8*'1-Inputs'!$C$9*'1-Inputs'!$C$87*O5*(1+'1-Inputs'!$C$161)^12 -> 188333.91 | P21: ='1-Inputs'!$C$113*'1-Inputs'!$C$8*'1-Inputs'!$C$9*'1-Inputs'!$C$87*P5*(1+'1-Inputs'!$C$161)^13 -> 192100.58 | Q21: ='1-Inputs'!$C$113*'1-Inputs'!$C$8*'1-Inputs'!$C$9*'1-Inputs'!$C$87*Q5*(1+'1-Inputs'!$C$161)^14 -> 195942.6
B22: Fioul de secours | C22: ='2-Production'!D37*'1-Inputs'!$C$9*'1-Inputs'!$C$86*C5*(1+'1-Inputs'!$C$161)^0 -> 129074.65 | D22: ='2-Production'!D37*'1-Inputs'!$C$9*'1-Inputs'!$C$86*D5*(1+'1-Inputs'!$C$161)^1 -> 159868.17 | E22: ='2-Production'!D37*'1-Inputs'!$C$9*'1-Inputs'!$C$86*E5*(1+'1-Inputs'!$C$161)^2 -> 191841.8 | F22: ='2-Production'!D37*'1-Inputs'!$C$9*'1-Inputs'!$C$86*F5*(1+'1-Inputs'!$C$161)^3 -> 195678.64 | G22: ='2-Production'!D37*'1-Inputs'!$C$9*'1-Inputs'!$C$86*G5*(1+'1-Inputs'!$C$161)^4 -> 199592.21 | H22: ='2-Production'!D37*'1-Inputs'!$C$9*'1-Inputs'!$C$86*H5*(1+'1-Inputs'!$C$161)^5 -> 203584.06 | I22: ='2-Production'!D37*'1-Inputs'!$C$9*'1-Inputs'!$C$86*I5*(1+'1-Inputs'!$C$161)^6 -> 207655.74 | J22: ='2-Production'!D37*'1-Inputs'!$C$9*'1-Inputs'!$C$86*J5*(1+'1-Inputs'!$C$161)^7 -> 211808.85 | K22: ='2-Production'!D37*'1-Inputs'!$C$9*'1-Inputs'!$C$86*K5*(1+'1-Inputs'!$C$161)^8 -> 216045.03 | L22: ='2-Production'!D37*'1-Inputs'!$C$9*'1-Inputs'!$C$86*L5*(1+'1-Inputs'!$C$161)^9 -> 220365.93 | M22: ='2-Production'!D37*'1-Inputs'!$C$9*'1-Inputs'!$C$86*M5*(1+'1-Inputs'!$C$161)^10 -> 224773.25 | N22: ='2-Production'!D37*'1-Inputs'!$C$9*'1-Inputs'!$C$86*N5*(1+'1-Inputs'!$C$161)^11 -> 229268.71 | O22: ='2-Production'!D37*'1-Inputs'!$C$9*'1-Inputs'!$C$86*O5*(1+'1-Inputs'!$C$161)^12 -> 233854.09 | P22: ='2-Production'!D37*'1-Inputs'!$C$9*'1-Inputs'!$C$86*P5*(1+'1-Inputs'!$C$161)^13 -> 238531.17 | Q22: ='2-Production'!D37*'1-Inputs'!$C$9*'1-Inputs'!$C$86*Q5*(1+'1-Inputs'!$C$161)^14 -> 243301.79
B23: Elimination des residus | C23: ='2-Production'!D56*'1-Inputs'!$C$85*C5*(1+'1-Inputs'!$C$161)^0 -> 494920.38 | D23: ='2-Production'!D56*'1-Inputs'!$C$85*D5*(1+'1-Inputs'!$C$161)^1 -> 612994.24 | E23: ='2-Production'!D56*'1-Inputs'!$C$85*E5*(1+'1-Inputs'!$C$161)^2 -> 735593.09 | F23: ='2-Production'!D56*'1-Inputs'!$C$85*F5*(1+'1-Inputs'!$C$161)^3 -> 750304.95 | G23: ='2-Production'!D56*'1-Inputs'!$C$85*G5*(1+'1-Inputs'!$C$161)^4 -> 765311.05 | H23: ='2-Production'!D56*'1-Inputs'!$C$85*H5*(1+'1-Inputs'!$C$161)^5 -> 780617.27 | I23: ='2-Production'!D56*'1-Inputs'!$C$85*I5*(1+'1-Inputs'!$C$161)^6 -> 796229.61 | J23: ='2-Production'!D56*'1-Inputs'!$C$85*J5*(1+'1-Inputs'!$C$161)^7 -> 812154.2 | K23: ='2-Production'!D56*'1-Inputs'!$C$85*K5*(1+'1-Inputs'!$C$161)^8 -> 828397.29 | L23: ='2-Production'!D56*'1-Inputs'!$C$85*L5*(1+'1-Inputs'!$C$161)^9 -> 844965.23 | M23: ='2-Production'!D56*'1-Inputs'!$C$85*M5*(1+'1-Inputs'!$C$161)^10 -> 861864.54 | N23: ='2-Production'!D56*'1-Inputs'!$C$85*N5*(1+'1-Inputs'!$C$161)^11 -> 879101.83 | O23: ='2-Production'!D56*'1-Inputs'!$C$85*O5*(1+'1-Inputs'!$C$161)^12 -> 896683.87 | P23: ='2-Production'!D56*'1-Inputs'!$C$85*P5*(1+'1-Inputs'!$C$161)^13 -> 914617.54 | Q23: ='2-Production'!D56*'1-Inputs'!$C$85*Q5*(1+'1-Inputs'!$C$161)^14 -> 932909.89
B24: Couche catalytique halogenes | C24: ='1-Inputs'!$C$115*'1-Inputs'!$C$8*C5*(1+'1-Inputs'!$C$161)^0 -> 105000 | D24: ='1-Inputs'!$C$115*'1-Inputs'!$C$8*D5*(1+'1-Inputs'!$C$161)^1 -> 130050 | E24: ='1-Inputs'!$C$115*'1-Inputs'!$C$8*E5*(1+'1-Inputs'!$C$161)^2 -> 156060 | F24: ='1-Inputs'!$C$115*'1-Inputs'!$C$8*F5*(1+'1-Inputs'!$C$161)^3 -> 159181.2 | G24: ='1-Inputs'!$C$115*'1-Inputs'!$C$8*G5*(1+'1-Inputs'!$C$161)^4 -> 162364.82 | H24: ='1-Inputs'!$C$115*'1-Inputs'!$C$8*H5*(1+'1-Inputs'!$C$161)^5 -> 165612.12 | I24: ='1-Inputs'!$C$115*'1-Inputs'!$C$8*I5*(1+'1-Inputs'!$C$161)^6 -> 168924.36 | J24: ='1-Inputs'!$C$115*'1-Inputs'!$C$8*J5*(1+'1-Inputs'!$C$161)^7 -> 172302.85 | K24: ='1-Inputs'!$C$115*'1-Inputs'!$C$8*K5*(1+'1-Inputs'!$C$161)^8 -> 175748.91 | L24: ='1-Inputs'!$C$115*'1-Inputs'!$C$8*L5*(1+'1-Inputs'!$C$161)^9 -> 179263.89 | M24: ='1-Inputs'!$C$115*'1-Inputs'!$C$8*M5*(1+'1-Inputs'!$C$161)^10 -> 182849.16 | N24: ='1-Inputs'!$C$115*'1-Inputs'!$C$8*N5*(1+'1-Inputs'!$C$161)^11 -> 186506.15 | O24: ='1-Inputs'!$C$115*'1-Inputs'!$C$8*O5*(1+'1-Inputs'!$C$161)^12 -> 190236.27 | P24: ='1-Inputs'!$C$115*'1-Inputs'!$C$8*P5*(1+'1-Inputs'!$C$161)^13 -> 194040.99 | Q24: ='1-Inputs'!$C$115*'1-Inputs'!$C$8*Q5*(1+'1-Inputs'!$C$161)^14 -> 197921.81
B25: Ceramique SEA CORAL | C25: ='1-Inputs'!$C$116*'1-Inputs'!$C$8*(1+'1-Inputs'!$C$161)^0 -> 15000 | D25: ='1-Inputs'!$C$116*'1-Inputs'!$C$8*(1+'1-Inputs'!$C$161)^1 -> 15300 | E25: ='1-Inputs'!$C$116*'1-Inputs'!$C$8*(1+'1-Inputs'!$C$161)^2 -> 15606 | F25: ='1-Inputs'!$C$116*'1-Inputs'!$C$8*(1+'1-Inputs'!$C$161)^3 -> 15918.12 | G25: ='1-Inputs'!$C$116*'1-Inputs'!$C$8*(1+'1-Inputs'!$C$161)^4 -> 16236.482 | H25: ='1-Inputs'!$C$116*'1-Inputs'!$C$8*(1+'1-Inputs'!$C$161)^5 -> 16561.212 | I25: ='1-Inputs'!$C$116*'1-Inputs'!$C$8*(1+'1-Inputs'!$C$161)^6 -> 16892.436 | J25: ='1-Inputs'!$C$116*'1-Inputs'!$C$8*(1+'1-Inputs'!$C$161)^7 -> 17230.285 | K25: ='1-Inputs'!$C$116*'1-Inputs'!$C$8*(1+'1-Inputs'!$C$161)^8 -> 17574.891 | L25: ='1-Inputs'!$C$116*'1-Inputs'!$C$8*(1+'1-Inputs'!$C$161)^9 -> 17926.389 | M25: ='1-Inputs'!$C$116*'1-Inputs'!$C$8*(1+'1-Inputs'!$C$161)^10 -> 18284.916 | N25: ='1-Inputs'!$C$116*'1-Inputs'!$C$8*(1+'1-Inputs'!$C$161)^11 -> 18650.615 | O25: ='1-Inputs'!$C$116*'1-Inputs'!$C$8*(1+'1-Inputs'!$C$161)^12 -> 19023.627 | P25: ='1-Inputs'!$C$116*'1-Inputs'!$C$8*(1+'1-Inputs'!$C$161)^13 -> 19404.099 | Q25: ='1-Inputs'!$C$116*'1-Inputs'!$C$8*(1+'1-Inputs'!$C$161)^14 -> 19792.181
B26: Carbonate de calcium (neutralisation) | C26: ='2-Production'!D50*'1-Inputs'!$C$120*C5*(1+'1-Inputs'!$C$161)^0 -> 20709.118 | D26: ='2-Production'!D50*'1-Inputs'!$C$120*D5*(1+'1-Inputs'!$C$161)^1 -> 25649.722 | E26: ='2-Production'!D50*'1-Inputs'!$C$120*E5*(1+'1-Inputs'!$C$161)^2 -> 30779.667 | F26: ='2-Production'!D50*'1-Inputs'!$C$120*F5*(1+'1-Inputs'!$C$161)^3 -> 31395.26 | G26: ='2-Production'!D50*'1-Inputs'!$C$120*G5*(1+'1-Inputs'!$C$161)^4 -> 32023.165 | H26: ='2-Production'!D50*'1-Inputs'!$C$120*H5*(1+'1-Inputs'!$C$161)^5 -> 32663.629 | I26: ='2-Production'!D50*'1-Inputs'!$C$120*I5*(1+'1-Inputs'!$C$161)^6 -> 33316.901 | J26: ='2-Production'!D50*'1-Inputs'!$C$120*J5*(1+'1-Inputs'!$C$161)^7 -> 33983.239 | K26: ='2-Production'!D50*'1-Inputs'!$C$120*K5*(1+'1-Inputs'!$C$161)^8 -> 34662.904 | L26: ='2-Production'!D50*'1-Inputs'!$C$120*L5*(1+'1-Inputs'!$C$161)^9 -> 35356.162 | M26: ='2-Production'!D50*'1-Inputs'!$C$120*M5*(1+'1-Inputs'!$C$161)^10 -> 36063.285 | N26: ='2-Production'!D50*'1-Inputs'!$C$120*N5*(1+'1-Inputs'!$C$161)^11 -> 36784.551 | O26: ='2-Production'!D50*'1-Inputs'!$C$120*O5*(1+'1-Inputs'!$C$161)^12 -> 37520.242 | P26: ='2-Production'!D50*'1-Inputs'!$C$120*P5*(1+'1-Inputs'!$C$161)^13 -> 38270.647 | Q26: ='2-Production'!D50*'1-Inputs'!$C$120*Q5*(1+'1-Inputs'!$C$161)^14 -> 39036.06
B27: Charbon actif (affinage eau) | C27: ='1-Inputs'!$C$121*'1-Inputs'!$C$8*C5*(1+'1-Inputs'!$C$161)^0 -> 28000 | D27: ='1-Inputs'!$C$121*'1-Inputs'!$C$8*D5*(1+'1-Inputs'!$C$161)^1 -> 34680 | E27: ='1-Inputs'!$C$121*'1-Inputs'!$C$8*E5*(1+'1-Inputs'!$C$161)^2 -> 41616 | F27: ='1-Inputs'!$C$121*'1-Inputs'!$C$8*F5*(1+'1-Inputs'!$C$161)^3 -> 42448.32 | G27: ='1-Inputs'!$C$121*'1-Inputs'!$C$8*G5*(1+'1-Inputs'!$C$161)^4 -> 43297.286 | H27: ='1-Inputs'!$C$121*'1-Inputs'!$C$8*H5*(1+'1-Inputs'!$C$161)^5 -> 44163.232 | I27: ='1-Inputs'!$C$121*'1-Inputs'!$C$8*I5*(1+'1-Inputs'!$C$161)^6 -> 45046.497 | J27: ='1-Inputs'!$C$121*'1-Inputs'!$C$8*J5*(1+'1-Inputs'!$C$161)^7 -> 45947.427 | K27: ='1-Inputs'!$C$121*'1-Inputs'!$C$8*K5*(1+'1-Inputs'!$C$161)^8 -> 46866.375 | L27: ='1-Inputs'!$C$121*'1-Inputs'!$C$8*L5*(1+'1-Inputs'!$C$161)^9 -> 47803.703 | M27: ='1-Inputs'!$C$121*'1-Inputs'!$C$8*M5*(1+'1-Inputs'!$C$161)^10 -> 48759.777 | N27: ='1-Inputs'!$C$121*'1-Inputs'!$C$8*N5*(1+'1-Inputs'!$C$161)^11 -> 49734.972 | O27: ='1-Inputs'!$C$121*'1-Inputs'!$C$8*O5*(1+'1-Inputs'!$C$161)^12 -> 50729.672 | P27: ='1-Inputs'!$C$121*'1-Inputs'!$C$8*P5*(1+'1-Inputs'!$C$161)^13 -> 51744.265 | Q27: ='1-Inputs'!$C$121*'1-Inputs'!$C$8*Q5*(1+'1-Inputs'!$C$161)^14 -> 52779.151
B28: Elimination du concentrat halogene | C28: ='2-Production'!D55*'1-Inputs'!$C$118*C5*(1+'1-Inputs'!$C$161)^0 -> 77880.959 | D28: ='2-Production'!D55*'1-Inputs'!$C$118*D5*(1+'1-Inputs'!$C$161)^1 -> 96461.131 | E28: ='2-Production'!D55*'1-Inputs'!$C$118*E5*(1+'1-Inputs'!$C$161)^2 -> 115753.36 | F28: ='2-Production'!D55*'1-Inputs'!$C$118*F5*(1+'1-Inputs'!$C$161)^3 -> 118068.42 | G28: ='2-Production'!D55*'1-Inputs'!$C$118*G5*(1+'1-Inputs'!$C$161)^4 -> 120429.79 | H28: ='2-Production'!D55*'1-Inputs'!$C$118*H5*(1+'1-Inputs'!$C$161)^5 -> 122838.39 | I28: ='2-Production'!D55*'1-Inputs'!$C$118*I5*(1+'1-Inputs'!$C$161)^6 -> 125295.16 | J28: ='2-Production'!D55*'1-Inputs'!$C$118*J5*(1+'1-Inputs'!$C$161)^7 -> 127801.06 | K28: ='2-Production'!D55*'1-Inputs'!$C$118*K5*(1+'1-Inputs'!$C$161)^8 -> 130357.08 | L28: ='2-Production'!D55*'1-Inputs'!$C$118*L5*(1+'1-Inputs'!$C$161)^9 -> 132964.22 | M28: ='2-Production'!D55*'1-Inputs'!$C$118*M5*(1+'1-Inputs'!$C$161)^10 -> 135623.51 | N28: ='2-Production'!D55*'1-Inputs'!$C$118*N5*(1+'1-Inputs'!$C$161)^11 -> 138335.98 | O28: ='2-Production'!D55*'1-Inputs'!$C$118*O5*(1+'1-Inputs'!$C$161)^12 -> 141102.7 | P28: ='2-Production'!D55*'1-Inputs'!$C$118*P5*(1+'1-Inputs'!$C$161)^13 -> 143924.75 | Q28: ='2-Production'!D55*'1-Inputs'!$C$118*Q5*(1+'1-Inputs'!$C$161)^14 -> 146803.25
B29: Assurance | C29: ='1-Inputs'!$C$114*'3-CAPEX'!$C$31*(1+'1-Inputs'!$C$161)^0 -> 320298.75 | D29: ='1-Inputs'!$C$114*'3-CAPEX'!$C$31*(1+'1-Inputs'!$C$161)^1 -> 326704.72 | E29: ='1-Inputs'!$C$114*'3-CAPEX'!$C$31*(1+'1-Inputs'!$C$161)^2 -> 333238.82 | F29: ='1-Inputs'!$C$114*'3-CAPEX'!$C$31*(1+'1-Inputs'!$C$161)^3 -> 339903.6 | G29: ='1-Inputs'!$C$114*'3-CAPEX'!$C$31*(1+'1-Inputs'!$C$161)^4 -> 346701.67 | H29: ='1-Inputs'!$C$114*'3-CAPEX'!$C$31*(1+'1-Inputs'!$C$161)^5 -> 353635.7 | I29: ='1-Inputs'!$C$114*'3-CAPEX'!$C$31*(1+'1-Inputs'!$C$161)^6 -> 360708.42 | J29: ='1-Inputs'!$C$114*'3-CAPEX'!$C$31*(1+'1-Inputs'!$C$161)^7 -> 367922.58 | K29: ='1-Inputs'!$C$114*'3-CAPEX'!$C$31*(1+'1-Inputs'!$C$161)^8 -> 375281.04 | L29: ='1-Inputs'!$C$114*'3-CAPEX'!$C$31*(1+'1-Inputs'!$C$161)^9 -> 382786.66 | M29: ='1-Inputs'!$C$114*'3-CAPEX'!$C$31*(1+'1-Inputs'!$C$161)^10 -> 390442.39 | N29: ='1-Inputs'!$C$114*'3-CAPEX'!$C$31*(1+'1-Inputs'!$C$161)^11 -> 398251.24 | O29: ='1-Inputs'!$C$114*'3-CAPEX'!$C$31*(1+'1-Inputs'!$C$161)^12 -> 406216.26 | P29: ='1-Inputs'!$C$114*'3-CAPEX'!$C$31*(1+'1-Inputs'!$C$161)^13 -> 414340.59 | Q29: ='1-Inputs'!$C$114*'3-CAPEX'!$C$31*(1+'1-Inputs'!$C$161)^14 -> 422627.4
B30: Provision et divers | C30: ='1-Inputs'!$C$112*'3-CAPEX'!$C$31*C5*(1+'1-Inputs'!$C$161)^0 -> 896836.5 | D30: ='1-Inputs'!$C$112*'3-CAPEX'!$C$31*D5*(1+'1-Inputs'!$C$161)^1 -> 1110796.1 | E30: ='1-Inputs'!$C$112*'3-CAPEX'!$C$31*E5*(1+'1-Inputs'!$C$161)^2 -> 1332955.3 | F30: ='1-Inputs'!$C$112*'3-CAPEX'!$C$31*F5*(1+'1-Inputs'!$C$161)^3 -> 1359614.4 | G30: ='1-Inputs'!$C$112*'3-CAPEX'!$C$31*G5*(1+'1-Inputs'!$C$161)^4 -> 1386806.7 | H30: ='1-Inputs'!$C$112*'3-CAPEX'!$C$31*H5*(1+'1-Inputs'!$C$161)^5 -> 1414542.8 | I30: ='1-Inputs'!$C$112*'3-CAPEX'!$C$31*I5*(1+'1-Inputs'!$C$161)^6 -> 1442833.7 | J30: ='1-Inputs'!$C$112*'3-CAPEX'!$C$31*J5*(1+'1-Inputs'!$C$161)^7 -> 1471690.3 | K30: ='1-Inputs'!$C$112*'3-CAPEX'!$C$31*K5*(1+'1-Inputs'!$C$161)^8 -> 1501124.1 | L30: ='1-Inputs'!$C$112*'3-CAPEX'!$C$31*L5*(1+'1-Inputs'!$C$161)^9 -> 1531146.6 | M30: ='1-Inputs'!$C$112*'3-CAPEX'!$C$31*M5*(1+'1-Inputs'!$C$161)^10 -> 1561769.6 | N30: ='1-Inputs'!$C$112*'3-CAPEX'!$C$31*N5*(1+'1-Inputs'!$C$161)^11 -> 1593004.9 | O30: ='1-Inputs'!$C$112*'3-CAPEX'!$C$31*O5*(1+'1-Inputs'!$C$161)^12 -> 1624865 | P30: ='1-Inputs'!$C$112*'3-CAPEX'!$C$31*P5*(1+'1-Inputs'!$C$161)^13 -> 1657362.3 | Q30: ='1-Inputs'!$C$112*'3-CAPEX'!$C$31*Q5*(1+'1-Inputs'!$C$161)^14 -> 1690509.6
B31: TOTAL CHARGES | C31: =C18+SUM(C20:C30) -> 3441240.4 | D31: =D18+SUM(D20:D30) -> 4188935.3 | E31: =E18+SUM(E20:E30) -> 4965161.5 | F31: =F18+SUM(F20:F30) -> 5064464.7 | G31: =G18+SUM(G20:G30) -> 5465100.6 | H31: =H18+SUM(H20:H30) -> 5879736.1 | I31: =I18+SUM(I20:I30) -> 6308771.1 | J31: =J18+SUM(J20:J30) -> 6752615.5 | ... Q31: =Q18+SUM(Q20:Q30) -> 8486436.4
A33: RESULTAT
B34: EBITDA | C34: =C15-C31 -> 5992748.3 | D34: =D15-D31 -> 7495733.5 | E34: =E15-E31 -> 9056441.1 | F34: =F15-F31 -> 9237569.9 | G34: =G15-G31 -> 9122974.7 | H34: =H15-H31 -> 9000100.6 | I34: =I15-I31 -> 8868662.4 | J34: =J15-J31 -> 8728366.7 | ... Q34: =Q15-Q31 -> 9296346
B35: Marge EBITDA | C35: =C34/C15 -> 0.63522954 | D35: =D34/D15 -> 0.64150158 | E35: =E34/E15 -> 0.64589201 | F35: =F34/F15 -> 0.64589201 | G35: =G34/G15 -> 0.62537206 | H35: =H34/H15 -> 0.60485211 | I35: =I34/I15 -> 0.58433216 | J35: =J34/J15 -> 0.5638122 | ... Q35: =Q34/Q15 -> 0.5227723
B36: EBITDA par tonne | C36: =C34/C6 -> 185.30452 | D36: =D34/D6 -> 190.87684 | E36: =E34/E6 -> 196.02686 | F36: =F34/F6 -> 199.9474 | G36: =G34/G6 -> 197.46698 | H36: =H34/H6 -> 194.80737 | I36: =I34/I6 -> 191.96239 | J36: =J34/J6 -> 188.92569 | ... Q36: =Q34/Q6 -> 201.21961
B37: Amortissement | C37: =-IF(1<='1-Inputs'!$C$160,'3-CAPEX'!$C$37,0) -> -4270650 | D37: =-IF(2<='1-Inputs'!$C$160,'3-CAPEX'!$C$37,0) -> -4270650 | E37: =-IF(3<='1-Inputs'!$C$160,'3-CAPEX'!$C$37,0) -> -4270650 | F37: =-IF(4<='1-Inputs'!$C$160,'3-CAPEX'!$C$37,0) -> -4270650 | G37: =-IF(5<='1-Inputs'!$C$160,'3-CAPEX'!$C$37,0) -> -4270650 | H37: =-IF(6<='1-Inputs'!$C$160,'3-CAPEX'!$C$37,0) -> -4270650 | I37: =-IF(7<='1-Inputs'!$C$160,'3-CAPEX'!$C$37,0) -> -4270650 | J37: =-IF(8<='1-Inputs'!$C$160,'3-CAPEX'!$C$37,0) -> -4270650 | K37: =-IF(9<='1-Inputs'!$C$160,'3-CAPEX'!$C$37,0) -> -4270650 | L37: =-IF(10<='1-Inputs'!$C$160,'3-CAPEX'!$C$37,0) -> -4270650 | M37: =-IF(11<='1-Inputs'!$C$160,'3-CAPEX'!$C$37,0) -> -4270650 | N37: =-IF(12<='1-Inputs'!$C$160,'3-CAPEX'!$C$37,0) -> -4270650 | O37: =-IF(13<='1-Inputs'!$C$160,'3-CAPEX'!$C$37,0) -> -4270650 | P37: =-IF(14<='1-Inputs'!$C$160,'3-CAPEX'!$C$37,0) -> -4270650 | Q37: =-IF(15<='1-Inputs'!$C$160,'3-CAPEX'!$C$37,0) -> -4270650
B38: EBIT | C38: =C34+C37 -> 1722098.3 | D38: =D34+D37 -> 3225083.5 | E38: =E34+E37 -> 4785791.1 | F38: =F34+F37 -> 4966919.9 | G38: =G34+G37 -> 4852324.7 | H38: =H34+H37 -> 4729450.6 | I38: =I34+I37 -> 4598012.4 | J38: =J34+J37 -> 4457716.7 | ... Q38: =Q34+Q37 -> 5025696
B39: Interets | C39: =IF(AND(1<='1-Inputs'!$C$158,'3-CAPEX'!$C$35>0),CUMIPMT('1-Inputs'!$C$157/12,'1-Inputs'!$C$158*12,'3-CAPEX'!$C$35,12*(1-1)+1,12*1,0),0) -> -5247977.6 | D39: =IF(AND(2<='1-Inputs'!$C$158,'3-CAPEX'!$C$35>0),CUMIPMT('1-Inputs'!$C$157/12,'1-Inputs'!$C$158*12,'3-CAPEX'!$C$35,12*(2-1)+1,12*2,0),0) -> -4934438 | E39: =IF(AND(3<='1-Inputs'!$C$158,'3-CAPEX'!$C$35>0),CUMIPMT('1-Inputs'!$C$157/12,'1-Inputs'!$C$158*12,'3-CAPEX'!$C$35,12*(3-1)+1,12*3,0),0) -> -4581133.8 | F39: =IF(AND(4<='1-Inputs'!$C$158,'3-CAPEX'!$C$35>0),CUMIPMT('1-Inputs'!$C$157/12,'1-Inputs'!$C$158*12,'3-CAPEX'!$C$35,12*(4-1)+1,12*4,0),0) -> -4183021.7 | G39: =IF(AND(5<='1-Inputs'!$C$158,'3-CAPEX'!$C$35>0),CUMIPMT('1-Inputs'!$C$157/12,'1-Inputs'!$C$158*12,'3-CAPEX'!$C$35,12*(5-1)+1,12*5,0),0) -> -3734419.1 | H39: =IF(AND(6<='1-Inputs'!$C$158,'3-CAPEX'!$C$35>0),CUMIPMT('1-Inputs'!$C$157/12,'1-Inputs'!$C$158*12,'3-CAPEX'!$C$35,12*(6-1)+1,12*6,0),0) -> -3228922.5 | I39: =IF(AND(7<='1-Inputs'!$C$158,'3-CAPEX'!$C$35>0),CUMIPMT('1-Inputs'!$C$157/12,'1-Inputs'!$C$158*12,'3-CAPEX'!$C$35,12*(7-1)+1,12*7,0),0) -> -2659316.2 | J39: =IF(AND(8<='1-Inputs'!$C$158,'3-CAPEX'!$C$35>0),CUMIPMT('1-Inputs'!$C$157/12,'1-Inputs'!$C$158*12,'3-CAPEX'!$C$35,12*(8-1)+1,12*8,0),0) -> -2017469.6 | K39: =IF(AND(9<='1-Inputs'!$C$158,'3-CAPEX'!$C$35>0),CUMIPMT('1-Inputs'!$C$157/12,'1-Inputs'!$C$158*12,'3-CAPEX'!$C$35,12*(9-1)+1,12*9,0),0) -> -1294220.7 | L39: =IF(AND(10<='1-Inputs'!$C$158,'3-CAPEX'!$C$35>0),CUMIPMT('1-Inputs'!$C$157/12,'1-Inputs'!$C$158*12,'3-CAPEX'!$C$35,12*(10-1)+1,12*10,0),0) -> -479245.84 | M39: =IF(AND(11<='1-Inputs'!$C$158,'3-CAPEX'!$C$35>0),CUMIPMT('1-Inputs'!$C$157/12,'1-Inputs'!$C$158*12,'3-CAPEX'!$C$35,12*(11-1)+1,12*11,0),0) -> 0 | N39: =IF(AND(12<='1-Inputs'!$C$158,'3-CAPEX'!$C$35>0),CUMIPMT('1-Inputs'!$C$157/12,'1-Inputs'!$C$158*12,'3-CAPEX'!$C$35,12*(12-1)+1,12*12,0),0) -> 0 | O39: =IF(AND(13<='1-Inputs'!$C$158,'3-CAPEX'!$C$35>0),CUMIPMT('1-Inputs'!$C$157/12,'1-Inputs'!$C$158*12,'3-CAPEX'!$C$35,12*(13-1)+1,12*13,0),0) -> 0 | P39: =IF(AND(14<='1-Inputs'!$C$158,'3-CAPEX'!$C$35>0),CUMIPMT('1-Inputs'!$C$157/12,'1-Inputs'!$C$158*12,'3-CAPEX'!$C$35,12*(14-1)+1,12*14,0),0) -> 0 | Q39: =IF(AND(15<='1-Inputs'!$C$158,'3-CAPEX'!$C$35>0),CUMIPMT('1-Inputs'!$C$157/12,'1-Inputs'!$C$158*12,'3-CAPEX'!$C$35,12*(15-1)+1,12*15,0),0) -> 0
B40: Resultat avant impot | C40: =C38+C39 -> -3525879.3 | D40: =D38+D39 -> -1709354.5 | E40: =E38+E39 -> 204657.33 | F40: =F38+F39 -> 783898.19 | G40: =G38+G39 -> 1117905.6 | H40: =H38+H39 -> 1500528.2 | I40: =I38+I39 -> 1938696.3 | J40: =J38+J39 -> 2440247.1 | ... Q40: =Q38+Q39 -> 5025696
B41: Impot | C41: =-MAX(0,C40)*'1-Inputs'!$C$159 -> 0 | D41: =-MAX(0,D40)*'1-Inputs'!$C$159 -> 0 | E41: =-MAX(0,E40)*'1-Inputs'!$C$159 -> -51164.331 | F41: =-MAX(0,F40)*'1-Inputs'!$C$159 -> -195974.55 | G41: =-MAX(0,G40)*'1-Inputs'!$C$159 -> -279476.4 | H41: =-MAX(0,H40)*'1-Inputs'!$C$159 -> -375132.05 | I41: =-MAX(0,I40)*'1-Inputs'!$C$159 -> -484674.07 | J41: =-MAX(0,J40)*'1-Inputs'!$C$159 -> -610061.78 | ... Q41: =-MAX(0,Q40)*'1-Inputs'!$C$159 -> -1256424
B42: Resultat net | C42: =C40+C41 -> -3525879.3 | D42: =D40+D41 -> -1709354.5 | E42: =E40+E41 -> 153492.99 | F42: =F40+F41 -> 587923.64 | G42: =G40+G41 -> 838429.19 | H42: =H40+H41 -> 1125396.1 | I42: =I40+I41 -> 1454022.2 | J42: =J40+J41 -> 1830185.3 | ... Q42: =Q40+Q41 -> 3769272
A44: TRESORERIE
B45: Flux d'exploitation apres impot et interets | C45: =C34+C41+C39 -> 744770.74 | D45: =D34+D41+D39 -> 2561295.5 | E45: =E34+E41+E39 -> 4424143 | F45: =F34+F41+F39 -> 4858573.6 | G45: =G34+G41+G39 -> 5109079.2 | H45: =H34+H41+H39 -> 5396046.1 | I45: =I34+I41+I39 -> 5724672.2 | J45: =J34+J41+J39 -> 6100835.3 | ... Q45: =Q34+Q41+Q39 -> 8039922
B46: Remboursement du capital | C46: =IF(AND(1<='1-Inputs'!$C$158,'3-CAPEX'!$C$35>0),CUMPRINC('1-Inputs'!$C$157/12,'1-Inputs'!$C$158*12,'3-CAPEX'!$C$35,12*(1-1)+1,12*1,0),0) -> -2472221.4 | D46: =IF(AND(2<='1-Inputs'!$C$158,'3-CAPEX'!$C$35>0),CUMPRINC('1-Inputs'!$C$157/12,'1-Inputs'!$C$158*12,'3-CAPEX'!$C$35,12*(2-1)+1,12*2,0),0) -> -2785761 | E46: =IF(AND(3<='1-Inputs'!$C$158,'3-CAPEX'!$C$35>0),CUMPRINC('1-Inputs'!$C$157/12,'1-Inputs'!$C$158*12,'3-CAPEX'!$C$35,12*(3-1)+1,12*3,0),0) -> -3139065.2 | F46: =IF(AND(4<='1-Inputs'!$C$158,'3-CAPEX'!$C$35>0),CUMPRINC('1-Inputs'!$C$157/12,'1-Inputs'!$C$158*12,'3-CAPEX'!$C$35,12*(4-1)+1,12*4,0),0) -> -3537177.3 | G46: =IF(AND(5<='1-Inputs'!$C$158,'3-CAPEX'!$C$35>0),CUMPRINC('1-Inputs'!$C$157/12,'1-Inputs'!$C$158*12,'3-CAPEX'!$C$35,12*(5-1)+1,12*5,0),0) -> -3985779.9 | H46: =IF(AND(6<='1-Inputs'!$C$158,'3-CAPEX'!$C$35>0),CUMPRINC('1-Inputs'!$C$157/12,'1-Inputs'!$C$158*12,'3-CAPEX'!$C$35,12*(6-1)+1,12*6,0),0) -> -4491276.5 | I46: =IF(AND(7<='1-Inputs'!$C$158,'3-CAPEX'!$C$35>0),CUMPRINC('1-Inputs'!$C$157/12,'1-Inputs'!$C$158*12,'3-CAPEX'!$C$35,12*(7-1)+1,12*7,0),0) -> -5060882.8 | J46: =IF(AND(8<='1-Inputs'!$C$158,'3-CAPEX'!$C$35>0),CUMPRINC('1-Inputs'!$C$157/12,'1-Inputs'!$C$158*12,'3-CAPEX'!$C$35,12*(8-1)+1,12*8,0),0) -> -5702729.4 | K46: =IF(AND(9<='1-Inputs'!$C$158,'3-CAPEX'!$C$35>0),CUMPRINC('1-Inputs'!$C$157/12,'1-Inputs'!$C$158*12,'3-CAPEX'!$C$35,12*(9-1)+1,12*9,0),0) -> -6425978.3 | L46: =IF(AND(10<='1-Inputs'!$C$158,'3-CAPEX'!$C$35>0),CUMPRINC('1-Inputs'!$C$157/12,'1-Inputs'!$C$158*12,'3-CAPEX'!$C$35,12*(10-1)+1,12*10,0),0) -> -7240953.1 | M46: =IF(AND(11<='1-Inputs'!$C$158,'3-CAPEX'!$C$35>0),CUMPRINC('1-Inputs'!$C$157/12,'1-Inputs'!$C$158*12,'3-CAPEX'!$C$35,12*(11-1)+1,12*11,0),0) -> 0 | N46: =IF(AND(12<='1-Inputs'!$C$158,'3-CAPEX'!$C$35>0),CUMPRINC('1-Inputs'!$C$157/12,'1-Inputs'!$C$158*12,'3-CAPEX'!$C$35,12*(12-1)+1,12*12,0),0) -> 0 | O46: =IF(AND(13<='1-Inputs'!$C$158,'3-CAPEX'!$C$35>0),CUMPRINC('1-Inputs'!$C$157/12,'1-Inputs'!$C$158*12,'3-CAPEX'!$C$35,12*(13-1)+1,12*13,0),0) -> 0 | P46: =IF(AND(14<='1-Inputs'!$C$158,'3-CAPEX'!$C$35>0),CUMPRINC('1-Inputs'!$C$157/12,'1-Inputs'!$C$158*12,'3-CAPEX'!$C$35,12*(14-1)+1,12*14,0),0) -> 0 | Q46: =IF(AND(15<='1-Inputs'!$C$158,'3-CAPEX'!$C$35>0),CUMPRINC('1-Inputs'!$C$157/12,'1-Inputs'!$C$158*12,'3-CAPEX'!$C$35,12*(15-1)+1,12*15,0),0) -> 0
B47: Variation du BFR | C47: =-'1-Inputs'!$C$165*(C15-IF(1=1,0,OFFSET(C15,0,-1)))+IF(1=15,'1-Inputs'!$C$165*C15,0) -> -471699.43 | D47: =-'1-Inputs'!$C$165*(D15-IF(2=1,0,OFFSET(D15,0,-1)))+IF(2=15,'1-Inputs'!$C$165*D15,0) -> -112534.01 | E47: =-'1-Inputs'!$C$165*(E15-IF(3=1,0,OFFSET(E15,0,-1)))+IF(3=15,'1-Inputs'!$C$165*E15,0) -> -116846.69 | F47: =-'1-Inputs'!$C$165*(F15-IF(4=1,0,OFFSET(F15,0,-1)))+IF(4=15,'1-Inputs'!$C$165*F15,0) -> -14021.603 | G47: =-'1-Inputs'!$C$165*(G15-IF(5=1,0,OFFSET(G15,0,-1)))+IF(5=15,'1-Inputs'!$C$165*G15,0) -> -14302.035 | H47: =-'1-Inputs'!$C$165*(H15-IF(6=1,0,OFFSET(H15,0,-1)))+IF(6=15,'1-Inputs'!$C$165*H15,0) -> -14588.075 | I47: =-'1-Inputs'!$C$165*(I15-IF(7=1,0,OFFSET(I15,0,-1)))+IF(7=15,'1-Inputs'!$C$165*I15,0) -> -14879.837 | J47: =-'1-Inputs'!$C$165*(J15-IF(8=1,0,OFFSET(J15,0,-1)))+IF(8=15,'1-Inputs'!$C$165*J15,0) -> -15177.434 | K47: =-'1-Inputs'!$C$165*(K15-IF(9=1,0,OFFSET(K15,0,-1)))+IF(9=15,'1-Inputs'!$C$165*K15,0) -> -15480.982 | L47: =-'1-Inputs'!$C$165*(L15-IF(10=1,0,OFFSET(L15,0,-1)))+IF(10=15,'1-Inputs'!$C$165*L15,0) -> -15790.602 | M47: =-'1-Inputs'!$C$165*(M15-IF(11=1,0,OFFSET(M15,0,-1)))+IF(11=15,'1-Inputs'!$C$165*M15,0) -> -16106.414 | N47: =-'1-Inputs'!$C$165*(N15-IF(12=1,0,OFFSET(N15,0,-1)))+IF(12=15,'1-Inputs'!$C$165*N15,0) -> -16428.542 | O47: =-'1-Inputs'!$C$165*(O15-IF(13=1,0,OFFSET(O15,0,-1)))+IF(13=15,'1-Inputs'!$C$165*O15,0) -> -16757.113 | P47: =-'1-Inputs'!$C$165*(P15-IF(14=1,0,OFFSET(P15,0,-1)))+IF(14=15,'1-Inputs'!$C$165*P15,0) -> -17092.255 | Q47: =-'1-Inputs'!$C$165*(Q15-IF(15=1,0,OFFSET(Q15,0,-1)))+IF(15=15,'1-Inputs'!$C$165*Q15,0) -> 871705.02
B48: Flux libre | C48: =C45+C46+C47 -> -2199150.1 | D48: =D45+D46+D47 -> -336999.46 | E48: =E45+E46+E47 -> 1168231.1 | F48: =F45+F46+F47 -> 1307374.8 | G48: =G45+G46+G47 -> 1108997.3 | H48: =H45+H46+H47 -> 890181.53 | I48: =I45+I46+I47 -> 648909.55 | J48: =J45+J46+J47 -> 382928.47 | ... Q48: =Q45+Q46+Q47 -> 8911627
B49: Flux cumule | C49: =IF(1=1,C48,OFFSET(C49,0,-1)+C48) -> -2199150.1 | D49: =IF(2=1,D48,OFFSET(D49,0,-1)+D48) -> -2536149.6 | E49: =IF(3=1,E48,OFFSET(E49,0,-1)+E48) -> -1367918.5 | F49: =IF(4=1,F48,OFFSET(F49,0,-1)+F48) -> -60543.746 | G49: =IF(5=1,G48,OFFSET(G49,0,-1)+G48) -> 1048453.5 | H49: =IF(6=1,H48,OFFSET(H49,0,-1)+H48) -> 1938635.1 | I49: =IF(7=1,I48,OFFSET(I49,0,-1)+I48) -> 2587544.6 | J49: =IF(8=1,J48,OFFSET(J49,0,-1)+J48) -> 2970473.1 | K49: =IF(9=1,K48,OFFSET(K49,0,-1)+K48) -> 3060194.5 | L49: =IF(10=1,L48,OFFSET(L49,0,-1)+L48) -> 2826669.1 | M49: =IF(11=1,M48,OFFSET(M49,0,-1)+M48) -> 10319515 | N49: =IF(12=1,N48,OFFSET(N49,0,-1)+N48) -> 17940865 | O49: =IF(13=1,O48,OFFSET(O49,0,-1)+O48) -> 25693289 | P49: =IF(14=1,P48,OFFSET(P49,0,-1)+P48) -> 33579407 | Q49: =IF(15=1,Q48,OFFSET(Q49,0,-1)+Q48) -> 42491034
B51: Flux du projet (avant financement) | C51: =C34-MAX(0,C34+C37)*'1-Inputs'!$C$159+C47 -> 5090524.3 | D51: =D34-MAX(0,D34+D37)*'1-Inputs'!$C$159+D47 -> 6576928.6 | E51: =E34-MAX(0,E34+E37)*'1-Inputs'!$C$159+E47 -> 7743146.6 | F51: =F34-MAX(0,F34+F37)*'1-Inputs'!$C$159+F47 -> 7981818.3 | G51: =G34-MAX(0,G34+G37)*'1-Inputs'!$C$159+G47 -> 7895591.5 | H51: =H34-MAX(0,H34+H37)*'1-Inputs'!$C$159+H47 -> 7803149.9 | I51: =I34-MAX(0,I34+I37)*'1-Inputs'!$C$159+I47 -> 7704279.5 | J51: =J34-MAX(0,J34+J37)*'1-Inputs'!$C$159+J47 -> 7598760.1 | ... Q51: =Q34-MAX(0,Q34+Q37)*'1-Inputs'!$C$159+Q47 -> 8911627
B53: Serie projet, annee 0 a 15 | C53: =-'3-CAPEX'!C31 -> -64059750 | D53: =C51 -> 5090524.3 | E53: =D51 -> 6576928.6 | F53: =E51 -> 7743146.6 | G53: =F51 -> 7981818.3 | H53: =G51 -> 7895591.5 | I53: =H51 -> 7803149.9 | J53: =I51 -> 7704279.5 | K53: =J51 -> 7598760.1 | ... R53: =Q51 -> 8911627
B54: Serie fonds propres, annee 0 a 15 | C54: =-'3-CAPEX'!C36 -> -19217925 | D54: =C48 -> -2199150.1 | E54: =D48 -> -336999.46 | F54: =E48 -> 1168231.1 | G54: =F48 -> 1307374.8 | H54: =G48 -> 1108997.3 | I54: =H48 -> 890181.53 | J54: =I48 -> 648909.55 | K54: =J48 -> 382928.47 | ... R54: =Q48 -> 8911627
B56: VAN du projet au CMPC | C56: =C53+NPV('1-Inputs'!$C$164,D53:R53) -> -8396262.5
B57: TRI du projet | C57: =IRR(C53:R53) -> 0.077399926
B58: TRI des fonds propres | C58: =IRR(C54:R54) -> 0.06445544
B59: Fonds propres investis | C59: ='3-CAPEX'!C36 -> 19217925
B60: Retour brut CAPEX / EBITDA annee 3 (annees) | C60: ='3-CAPEX'!C31/E34 -> 7.0733911
B61: Gate fee d'equilibre annee 3 (EUR/T) | C61: =(E31+'3-CAPEX'!C31/'1-Inputs'!$C$160-(E15-E9))/E6 -> 10.855448 | E61: CORRIGE le 19/09/2026 : la formule precedente comptait les gate fees deux fois. Lecture : (charges + amortissement - recettes produits hors gate fees) / tonnage.

Sheet 5-Segments
A1: COMPTES DES LIGNES DE TRI — ANNEE 3, REGIME NOMINAL
A2: Chaque ligne se paie-t-elle ? Recettes directes et elimination evitee, moins personnel, maintenance au regime etabli et amortissement. Toutes unites.
A4: Ref | B4: Poste | C4: EUR/an | D4: Commentaire
A5: LIGNE DE PRE-TRI
A6: P1 | B6: Tonnage extrait (ferreux, alu, verre, recyclables) | C6: ='2-Production'!D15*'1-Inputs'!$C$20*'1-Inputs'!$C$177*'1-Inputs'!$C$9/1000+'2-Production'!D15*'1-Inputs'!$C$21*'1-Inputs'!$C$178*'1-Inputs'!$C$9/1000+'2-Production'!D48+'2-Production'!D92+'2-Production'!D93 -> 3627.7395 | D6: T/an
A7: P2 | B7: Vente ferreux et aluminium | C7: =('2-Production'!D15*'1-Inputs'!$C$20*'1-Inputs'!$C$177*'1-Inputs'!$C$9/1000*'1-Inputs'!$C$81+'2-Production'!D15*'1-Inputs'!$C$21*'1-Inputs'!$C$178*'1-Inputs'!$C$9/1000*'1-Inputs'!$C$82)*(1+'1-Inputs'!$C$161)^2*'4-PL'!$E$5 -> 794899.41
A8: P3 | B8: Vente verre et recyclables | C8: ='4-PL'!E13 -> 54406.449
A9: P4 | B9: Elimination evitee | C9: =C6*'1-Inputs'!$C$85*(1+'1-Inputs'!$C$161)^2*'4-PL'!$E$5 -> 415173.02 | D9: Sans tri, ces tonnes finiraient en residus a 110 EUR/T
A10: P5 | B10: Personnel pre-tri | C10: =-'1-Inputs'!$C$173*'1-Inputs'!$C$175*'1-Inputs'!$C$8*'1-Inputs'!$C$107*(1+'1-Inputs'!$C$161)^2*'4-PL'!$E$5 -> -233049.6
A11: P6 | B11: Maintenance (regime etabli) | C11: =-'1-Inputs'!$C$109*'3-CAPEX'!C11*(1+'1-Inputs'!$C$161)^2*'4-PL'!$E$5 -> -44945.28 | D11: 4% : prudent, l annee 3 est encore sous garantie
A12: P7 | B12: Amortissement | C12: =-'3-CAPEX'!C11/'1-Inputs'!$C$160 -> -72000
A13: P8 | B13: RESULTAT DE LA LIGNE DE PRE-TRI | C13: =SUM(C7:C12) -> 914484 | D13: Positif : la ligne se paie
A15: LIGNE DE POST-TRI
A16: Q1 | B16: Metaux extraits du char | C16: ='2-Production'!D15*'1-Inputs'!$C$20*(1-'1-Inputs'!$C$177)*'1-Inputs'!$C$181*'1-Inputs'!$C$9/1000+'2-Production'!D15*'1-Inputs'!$C$21*(1-'1-Inputs'!$C$178)*'1-Inputs'!$C$181*'1-Inputs'!$C$9/1000+'2-Production'!D46 -> 303.3492 | D16: T/an
A17: Q2 | B17: Vente des metaux du char | C17: =('2-Production'!D15*'1-Inputs'!$C$20*(1-'1-Inputs'!$C$177)*'1-Inputs'!$C$181*'1-Inputs'!$C$9/1000*'1-Inputs'!$C$81+'2-Production'!D15*'1-Inputs'!$C$21*(1-'1-Inputs'!$C$178)*'1-Inputs'!$C$181*'1-Inputs'!$C$9/1000*'1-Inputs'!$C$82+'2-Production'!D46*'1-Inputs'!$C$83)*(1+'1-Inputs'!$C$161)^2*'4-PL'!$E$5 -> 183710.09
A18: Q3 | B18: Elimination evitee | C18: =C16*'1-Inputs'!$C$85*(1+'1-Inputs'!$C$161)^2*'4-PL'!$E$5 -> 34716.496
A19: Q4 | B19: Personnel post-tri | C19: =-'1-Inputs'!$C$174*'1-Inputs'!$C$176*'1-Inputs'!$C$8*'1-Inputs'!$C$107*(1+'1-Inputs'!$C$161)^2*'4-PL'!$E$5 -> -174787.2
A20: Q5 | B20: Maintenance (regime etabli) | C20: =-'1-Inputs'!$C$109*'3-CAPEX'!C12*(1+'1-Inputs'!$C$161)^2*'4-PL'!$E$5 -> -17894.88
A21: Q6 | B21: Amortissement | C21: =-'3-CAPEX'!C12/'1-Inputs'!$C$160 -> -28666.667
A22: Q7 | B22: RESULTAT DE LA LIGNE DE POST-TRI | C22: =SUM(C17:C21) -> -2922.1643 | D22: Non compte : le criblage conditionne la qualite du char, donc son prix. Voir le selecteur K1
